Workbook

Sheet Dashboard
A1: SwingScope Momentum Batch 2026-09-28 — 21-Day Dashboard
A2: Signal 2026-09-28 • Day 18 of 21 • Holding • Exit ~2026-10-29 • Updated 23-Oct-2026 17:22
B4: PROGRESS Day 18/21
L5: 86%
B7: CURRENT DAY | E7: LAST SESSION | H7: INVESTED | K7: MARKET VALUE
B8: Day 18 / 21 | E8: 2026-10-23 | H8: ='Daily Closes'!E16 | K8: ='Daily Closes'!AB16
B9: Holding | E9: Exit ~2026-10-29 | H9: Qty × entry price | K9: At latest close
B11: GROSS P&L | E11: GROSS RETURN | H11: EST. COSTS | K11: NET P&L
B12: ='Daily Closes'!AD16 | E12: ='Daily Closes'!AC16 | H12: ='Daily Closes'!E16*0.006 | K12: =B12-H12
B13: Before costs | E13: vs entry | H13: 0.6% round trip | K13: After est. costs
B15: NIFTY 50 | E15: ALPHA vs NIFTY | H15: WINNERS / LOSERS | K15: MAX DRAWDOWN
B16: -0.0079125558 | E16: -0.080260754 | H16: 0 / 10 | K16: -0.15058472
B17: Same window | E17: Gross return − Nifty | H17: of 10 stocks | K17: Peak-to-trough, portfolio
B19: STOCK LEAGUE TABLE (sorted by return)
B20: Symbol | C20: Qty | D20: Entry ₹ | E20: Last ₹ | F20: Return % | G20: P&L ₹ | H20: Max gain % | I20: Max loss % | J20: Weight % | K20: Contrib %
B21: LAURUSLABS | C21: 7 | D21: 2020.7 | E21: 1970 | F21: -0.02509 | G21: -354.9 | H21: 0.024002 | I21: -0.02509 | J21: 0.101067 | K21: -0.002536
B22: ACUTAAS | C22: 4 | D22: 3290 | E22: 3137.7 | F22: -0.046292 | G22: -609.2 | H22: 0.004286 | I22: -0.070912 | J22: 0.09403 | K22: -0.004353
B23: ATHERENERG | C23: 10 | D23: 1460.2 | E23: 1380 | F23: -0.054924 | G23: -802 | H23: 0.03479 | I23: -0.054924 | J23: 0.104333 | K23: -0.00573
B24: THANGAMAYL | C24: 2 | D24: 5010 | E24: 4690.5 | F24: -0.063772 | G24: -639 | H24: 0.038822 | I24: -0.063772 | J24: 0.071594 | K24: -0.004566
B25: DIACABS | C25: 44 | D25: 336.9 | E25: 315.05 | F25: -0.064856 | G25: -961.4 | H25: 0.130751 | I25: -0.064856 | J25: 0.105917 | K25: -0.006869
B26: E2E | C26: 23 | D26: 619.55 | E26: 566.05 | F26: -0.086353 | G26: -1230.5 | H26: 0.207812 | I26: -0.086353 | J26: 0.101816 | K26: -0.008792
B27: TDPOWERSYS | C27: 20 | D27: 719 | E27: 639.55 | F27: -0.110501 | G27: -1589 | H27: 0.148331 | I27: -0.110501 | J27: 0.102747 | K27: -0.011354
B28: AEROFLEX | C28: 29 | D28: 511.3 | E28: 451.3 | F28: -0.117348 | G28: -1740 | H28: 0.112263 | I28: -0.117348 | J28: 0.105946 | K28: -0.012433
B29: RRKABEL | C29: 6 | D29: 2459.8 | E29: 2140 | F29: -0.130011 | G29: -1918.8 | H29: 0.134117 | I29: -0.130011 | J29: 0.105454 | K29: -0.01371
B30: KIRLOSENG | C30: 7 | D30: 2141.2 | E30: 1784.7 | F30: -0.166495 | G30: -2495.5 | H30: 0.121801 | I30: -0.166495 | J30: 0.107094 | K30: -0.017831

Sheet Daily Closes
A1: SwingScope Batch 2026-09-28 — Daily Close Tracker
A2: Signal 2026-09-28 • Day 18 of 21 • Holding • Exit ~2026-10-29 • Updated 23-Oct-2026 17:22
A3: Closes from Day 0 (signal) to Day 21 (exit). Highlighted column = latest session. Grey = future session (projected date).
A4: # | B4: Symbol | C4: ISIN | D4: Qty | E4: Entry ₹ | F4: Day 0 | G4: Day 1 | H4: Day 2 | I4: Day 3 | J4: Day 4 | K4: Day 5 | L4: Day 6 | M4: Day 7 | N4: Day 8 | O4: Day 9 | P4: Day 10 | Q4: Day 11 | R4: Day 12 | S4: Day 13 | T4: Day 14 | U4: Day 15 | V4: Day 16 | W4: Day 17 | X4: Day 18 | Y4: Day 19 | Z4: Day 20 | AA4: Day 21 | AB4: Last Close | AC4: Return % | AD4: P&L ₹ | AE4: Day Chg % | AF4: Trend
F5: 28-Sep | G5: 29-Sep | H5: 30-Sep | I5: 01-Oct | J5: 02-Oct | K5: 05-Oct | L5: 06-Oct | M5: 07-Oct | N5: 08-Oct | O5: 09-Oct | P5: 12-Oct | Q5: 13-Oct | R5: 14-Oct | S5: 15-Oct | T5: 16-Oct | U5: 19-Oct | V5: 21-Oct | W5: 22-Oct | X5: 23-Oct | Y5: 27-Oct (p) | Z5: 28-Oct (p) | AA5: 29-Oct (p)
A6: 1 | B6: TDPOWERSYS | C6: INE419M01035 | D6: 20 | E6: 719 | F6: 722 | G6: 777.35 | H6: 786.05 | I6: 792.15 | J6: 792.15 | K6: 812.9 | L6: 816 | M6: 821.1 | N6: 793.5 | O6: 793.75 | P6: 825.65 | Q6: 797.85 | R6: 783.7 | S6: 734.75 | T6: 735.15 | U6: 737 | V6: 689.35 | W6: 673.4 | X6: 639.55 | AB6: =LOOKUP(2,1/(F6:AA6<>""),F6:AA6) | AC6: =AB6/E6-1 | AD6: =D6*(AB6-E6) | AE6: =IFERROR(X6/W6-1,0) | AF6: =IF(AC6>0,"▲ Up",IF(AC6<0,"▼ Down","■ Flat"))
A7: 2 | B7: AEROFLEX | C7: INE024001021 | D7: 29 | E7: 511.3 | F7: 513.4 | G7: 539.6 | H7: 536.6 | I7: 521.35 | J7: 521.35 | K7: 544.35 | L7: 560.75 | M7: 563.85 | N7: 529 | O7: 520.5 | P7: 567.9 | Q7: 557.6 | R7: 568.7 | S7: 510.95 | T7: 525.8 | U7: 505.2 | V7: 488.95 | W7: 479.45 | X7: 451.3 | AB7: =LOOKUP(2,1/(F7:AA7<>""),F7:AA7) | AC7: =AB7/E7-1 | AD7: =D7*(AB7-E7) | AE7: =IFERROR(X7/W7-1,0) | AF7: =IF(AC7>0,"▲ Up",IF(AC7<0,"▼ Down","■ Flat"))
A8: 3 | B8: ATHERENERG | C8: INE0LEZ01016 | D8: 10 | E8: 1460.2 | F8: 1454.9 | G8: 1407 | H8: 1425 | I8: 1406.1 | J8: 1406.1 | K8: 1409.9 | L8: 1446 | M8: 1455 | N8: 1406 | O8: 1434.4 | P8: 1511 | Q8: 1494.9 | R8: 1467 | S8: 1470 | T8: 1470 | U8: 1459 | V8: 1447.2 | W8: 1425.3 | X8: 1380 | AB8: =LOOKUP(2,1/(F8:AA8<>""),F8:AA8) | AC8: =AB8/E8-1 | AD8: =D8*(AB8-E8) | AE8: =IFERROR(X8/W8-1,0) | AF8: =IF(AC8>0,"▲ Up",IF(AC8<0,"▼ Down","■ Flat"))
A9: 4 | B9: THANGAMAYL | C9: INE085J01014 | D9: 2 | E9: 5010 | F9: 5011.5 | G9: 5204.5 | H9: 5062 | I9: 4861 | J9: 4861 | K9: 4747 | L9: 4758.5 | M9: 4803 | N9: 4810.5 | O9: 4889.5 | P9: 4890.5 | Q9: 4900.5 | R9: 4849.5 | S9: 4791 | T9: 5098 | U9: 5017.5 | V9: 4860.5 | W9: 4782.5 | X9: 4690.5 | AB9: =LOOKUP(2,1/(F9:AA9<>""),F9:AA9) | AC9: =AB9/E9-1 | AD9: =D9*(AB9-E9) | AE9: =IFERROR(X9/W9-1,0) | AF9: =IF(AC9>0,"▲ Up",IF(AC9<0,"▼ Down","■ Flat"))
A10: 5 | B10: RRKABEL | C10: INE777K01022 | D10: 6 | E10: 2459.8 | F10: 2459.8 | G10: 2523.2 | H10: 2518.6 | I10: 2518.2 | J10: 2518.2 | K10: 2648 | L10: 2789.7 | M10: 2722.5 | N10: 2696.4 | O10: 2705.6 | P10: 2721.5 | Q10: 2614.2 | R10: 2664.1 | S10: 2603.9 | T10: 2388 | U10: 2387.8 | V10: 2327.8 | W10: 2263.1 | X10: 2140 | AB10: =LOOKUP(2,1/(F10:AA10<>""),F10:AA10) | AC10: =AB10/E10-1 | AD10: =D10*(AB10-E10) | AE10: =IFERROR(X10/W10-1,0) | AF10: =IF(AC10>0,"▲ Up",IF(AC10<0,"▼ Down","■ Flat"))
A11: 6 | B11: ACUTAAS | C11: INE00FF01025 | D11: 4 | E11: 3290 | F11: 3214.4 | G11: 3304.1 | H11: 3279.4 | I11: 3196.5 | J11: 3196.5 | K11: 3122.2 | L11: 3156.7 | M11: 3174.2 | N11: 3056.7 | O11: 3160.6 | P11: 3144.1 | Q11: 3176.7 | R11: 3160.5 | S11: 3132.5 | T11: 3206 | U11: 3253.4 | V11: 3152.4 | W11: 3215.3 | X11: 3137.7 | AB11: =LOOKUP(2,1/(F11:AA11<>""),F11:AA11) | AC11: =AB11/E11-1 | AD11: =D11*(AB11-E11) | AE11: =IFERROR(X11/W11-1,0) | AF11: =IF(AC11>0,"▲ Up",IF(AC11<0,"▼ Down","■ Flat"))
A12: 7 | B12: DIACABS | C12: INE989C01038 | D12: 44 | E12: 336.9 | F12: 339.25 | G12: 352.05 | H12: 354.2 | I12: 345 | J12: 345 | K12: 350.8 | L12: 368.3 | M12: 369.15 | N12: 371.9 | O12: 380.95 | P12: 379.7 | Q12: 377.55 | R12: 378.75 | S12: 373.75 | T12: 362.4 | U12: 345.85 | V12: 337.85 | W12: 326.65 | X12: 315.05 | AB12: =LOOKUP(2,1/(F12:AA12<>""),F12:AA12) | AC12: =AB12/E12-1 | AD12: =D12*(AB12-E12) | AE12: =IFERROR(X12/W12-1,0) | AF12: =IF(AC12>0,"▲ Up",IF(AC12<0,"▼ Down","■ Flat"))
A13: 8 | B13: KIRLOSENG | C13: INE146L01010 | D13: 7 | E13: 2141.2 | F13: 2141.2 | G13: 2402 | H13: 2304.2 | I13: 2242.7 | J13: 2242.7 | K13: 2243.7 | L13: 2266.1 | M13: 2230.8 | N13: 2163 | O13: 2210.4 | P13: 2193 | Q13: 2180.8 | R13: 2148.3 | S13: 2066.3 | T13: 2025.6 | U13: 1973.2 | V13: 1908.7 | W13: 1869 | X13: 1784.7 | AB13: =LOOKUP(2,1/(F13:AA13<>""),F13:AA13) | AC13: =AB13/E13-1 | AD13: =D13*(AB13-E13) | AE13: =IFERROR(X13/W13-1,0) | AF13: =IF(AC13>0,"▲ Up",IF(AC13<0,"▼ Down","■ Flat"))
A14: 9 | B14: E2E | C14: INE255Z01027 | D14: 23 | E14: 619.55 | F14: 625.9 | G14: 651.8 | H14: 650.5 | I14: 648 | J14: 648 | K14: 656.1 | L14: 688.9 | M14: 723.3 | N14: 714.15 | O14: 704.6 | P14: 735.55 | Q14: 735.75 | R14: 748.3 | S14: 710.9 | T14: 694.85 | U14: 660.15 | V14: 627.15 | W14: 595.8 | X14: 566.05 | AB14: =LOOKUP(2,1/(F14:AA14<>""),F14:AA14) | AC14: =AB14/E14-1 | AD14: =D14*(AB14-E14) | AE14: =IFERROR(X14/W14-1,0) | AF14: =IF(AC14>0,"▲ Up",IF(AC14<0,"▼ Down","■ Flat"))
A15: 10 | B15: LAURUSLABS | C15: INE947Q01028 | D15: 7 | E15: 2020.7 | F15: 2010.7 | G15: 1979 | H15: 1980 | I15: 1984 | J15: 1984 | K15: 1971.4 | L15: 2050 | M15: 2052.8 | N15: 1997.9 | O15: 2036.6 | P15: 2069.2 | Q15: 2059.4 | R15: 2036.9 | S15: 2018.5 | T15: 2060.1 | U15: 2069 | V15: 2012.5 | W15: 2002.5 | X15: 1970 | AB15: =LOOKUP(2,1/(F15:AA15<>""),F15:AA15) | AC15: =AB15/E15-1 | AD15: =D15*(AB15-E15) | AE15: =IFERROR(X15/W15-1,0) | AF15: =IF(AC15>0,"▲ Up",IF(AC15<0,"▼ Down","■ Flat"))
B16: PORTFOLIO | D16: =SUM(D6:D15) | E16: =SUMPRODUCT(D6:D15,E6:E15) | F16: =IF(COUNT(F6:F15)=0,"",SUMPRODUCT($D$6:$D$15,F6:F15)) | G16: =IF(COUNT(G6:G15)=0,"",SUMPRODUCT($D$6:$D$15,G6:G15)) | H16: =IF(COUNT(H6:H15)=0,"",SUMPRODUCT($D$6:$D$15,H6:H15)) | I16: =IF(COUNT(I6:I15)=0,"",SUMPRODUCT($D$6:$D$15,I6:I15)) | J16: =IF(COUNT(J6:J15)=0,"",SUMPRODUCT($D$6:$D$15,J6:J15)) | K16: =IF(COUNT(K6:K15)=0,"",SUMPRODUCT($D$6:$D$15,K6:K15)) | L16: =IF(COUNT(L6:L15)=0,"",SUMPRODUCT($D$6:$D$15,L6:L15)) | M16: =IF(COUNT(M6:M15)=0,"",SUMPRODUCT($D$6:$D$15,M6:M15)) | ... AA16: =IF(COUNT(AA6:AA15)=0,"",SUMPRODUCT($D$6:$D$15,AA6:AA15)) | AB16: =SUMPRODUCT(D6:D15,AB6:AB15) | AC16: =AB16/E16-1 | AD16: =SUM(AD6:AD15)

Sheet Returns %
A1: Cumulative Return vs Entry (%)
A2: Each cell = close ÷ entry − 1. Colour scale: red → white → green.
A3: Formulas link to 'Daily Closes' — edit a close there and this sheet updates.
A4: # | B4: Symbol | C4: ISIN | D4: Qty | E4: Entry ₹ | F4: Day 0 | G4: Day 1 | H4: Day 2 | I4: Day 3 | J4: Day 4 | K4: Day 5 | L4: Day 6 | M4: Day 7 | N4: Day 8 | O4: Day 9 | P4: Day 10 | Q4: Day 11 | R4: Day 12 | S4: Day 13 | T4: Day 14 | U4: Day 15 | V4: Day 16 | W4: Day 17 | X4: Day 18 | Y4: Day 19 | Z4: Day 20 | AA4: Day 21
F5: ='Daily Closes'!F5 | G5: ='Daily Closes'!G5 | H5: ='Daily Closes'!H5 | I5: ='Daily Closes'!I5 | J5: ='Daily Closes'!J5 | K5: ='Daily Closes'!K5 | L5: ='Daily Closes'!L5 | M5: ='Daily Closes'!M5 | ... AA5: ='Daily Closes'!AA5
A6: ='Daily Closes'!A6 | B6: ='Daily Closes'!B6 | C6: ='Daily Closes'!C6 | D6: ='Daily Closes'!D6 | E6: ='Daily Closes'!E6 | F6: — | G6: =IF('Daily Closes'!G6="","",'Daily Closes'!G6/$E6-1) | H6: =IF('Daily Closes'!H6="","",'Daily Closes'!H6/$E6-1) | I6: =IF('Daily Closes'!I6="","",'Daily Closes'!I6/$E6-1) | J6: =IF('Daily Closes'!J6="","",'Daily Closes'!J6/$E6-1) | K6: =IF('Daily Closes'!K6="","",'Daily Closes'!K6/$E6-1) | L6: =IF('Daily Closes'!L6="","",'Daily Closes'!L6/$E6-1) | M6: =IF('Daily Closes'!M6="","",'Daily Closes'!M6/$E6-1) | N6: =IF('Daily Closes'!N6="","",'Daily Closes'!N6/$E6-1) | ... AA6: =IF('Daily Closes'!AA6="","",'Daily Closes'!AA6/$E6-1)
A7: ='Daily Closes'!A7 | B7: ='Daily Closes'!B7 | C7: ='Daily Closes'!C7 | D7: ='Daily Closes'!D7 | E7: ='Daily Closes'!E7 | F7: — | G7: =IF('Daily Closes'!G7="","",'Daily Closes'!G7/$E7-1) | H7: =IF('Daily Closes'!H7="","",'Daily Closes'!H7/$E7-1) | I7: =IF('Daily Closes'!I7="","",'Daily Closes'!I7/$E7-1) | J7: =IF('Daily Closes'!J7="","",'Daily Closes'!J7/$E7-1) | K7: =IF('Daily Closes'!K7="","",'Daily Closes'!K7/$E7-1) | L7: =IF('Daily Closes'!L7="","",'Daily Closes'!L7/$E7-1) | M7: =IF('Daily Closes'!M7="","",'Daily Closes'!M7/$E7-1) | N7: =IF('Daily Closes'!N7="","",'Daily Closes'!N7/$E7-1) | ... AA7: =IF('Daily Closes'!AA7="","",'Daily Closes'!AA7/$E7-1)
A8: ='Daily Closes'!A8 | B8: ='Daily Closes'!B8 | C8: ='Daily Closes'!C8 | D8: ='Daily Closes'!D8 | E8: ='Daily Closes'!E8 | F8: — | G8: =IF('Daily Closes'!G8="","",'Daily Closes'!G8/$E8-1) | H8: =IF('Daily Closes'!H8="","",'Daily Closes'!H8/$E8-1) | I8: =IF('Daily Closes'!I8="","",'Daily Closes'!I8/$E8-1) | J8: =IF('Daily Closes'!J8="","",'Daily Closes'!J8/$E8-1) | K8: =IF('Daily Closes'!K8="","",'Daily Closes'!K8/$E8-1) | L8: =IF('Daily Closes'!L8="","",'Daily Closes'!L8/$E8-1) | M8: =IF('Daily Closes'!M8="","",'Daily Closes'!M8/$E8-1) | N8: =IF('Daily Closes'!N8="","",'Daily Closes'!N8/$E8-1) | ... AA8: =IF('Daily Closes'!AA8="","",'Daily Closes'!AA8/$E8-1)
A9: ='Daily Closes'!A9 | B9: ='Daily Closes'!B9 | C9: ='Daily Closes'!C9 | D9: ='Daily Closes'!D9 | E9: ='Daily Closes'!E9 | F9: — | G9: =IF('Daily Closes'!G9="","",'Daily Closes'!G9/$E9-1) | H9: =IF('Daily Closes'!H9="","",'Daily Closes'!H9/$E9-1) | I9: =IF('Daily Closes'!I9="","",'Daily Closes'!I9/$E9-1) | J9: =IF('Daily Closes'!J9="","",'Daily Closes'!J9/$E9-1) | K9: =IF('Daily Closes'!K9="","",'Daily Closes'!K9/$E9-1) | L9: =IF('Daily Closes'!L9="","",'Daily Closes'!L9/$E9-1) | M9: =IF('Daily Closes'!M9="","",'Daily Closes'!M9/$E9-1) | N9: =IF('Daily Closes'!N9="","",'Daily Closes'!N9/$E9-1) | ... AA9: =IF('Daily Closes'!AA9="","",'Daily Closes'!AA9/$E9-1)
A10: ='Daily Closes'!A10 | B10: ='Daily Closes'!B10 | C10: ='Daily Closes'!C10 | D10: ='Daily Closes'!D10 | E10: ='Daily Closes'!E10 | F10: — | G10: =IF('Daily Closes'!G10="","",'Daily Closes'!G10/$E10-1) | H10: =IF('Daily Closes'!H10="","",'Daily Closes'!H10/$E10-1) | I10: =IF('Daily Closes'!I10="","",'Daily Closes'!I10/$E10-1) | J10: =IF('Daily Closes'!J10="","",'Daily Closes'!J10/$E10-1) | K10: =IF('Daily Closes'!K10="","",'Daily Closes'!K10/$E10-1) | L10: =IF('Daily Closes'!L10="","",'Daily Closes'!L10/$E10-1) | M10: =IF('Daily Closes'!M10="","",'Daily Closes'!M10/$E10-1) | N10: =IF('Daily Closes'!N10="","",'Daily Closes'!N10/$E10-1) | ... AA10: =IF('Daily Closes'!AA10="","",'Daily Closes'!AA10/$E10-1)
A11: ='Daily Closes'!A11 | B11: ='Daily Closes'!B11 | C11: ='Daily Closes'!C11 | D11: ='Daily Closes'!D11 | E11: ='Daily Closes'!E11 | F11: — | G11: =IF('Daily Closes'!G11="","",'Daily Closes'!G11/$E11-1) | H11: =IF('Daily Closes'!H11="","",'Daily Closes'!H11/$E11-1) | I11: =IF('Daily Closes'!I11="","",'Daily Closes'!I11/$E11-1) | J11: =IF('Daily Closes'!J11="","",'Daily Closes'!J11/$E11-1) | K11: =IF('Daily Closes'!K11="","",'Daily Closes'!K11/$E11-1) | L11: =IF('Daily Closes'!L11="","",'Daily Closes'!L11/$E11-1) | M11: =IF('Daily Closes'!M11="","",'Daily Closes'!M11/$E11-1) | N11: =IF('Daily Closes'!N11="","",'Daily Closes'!N11/$E11-1) | ... AA11: =IF('Daily Closes'!AA11="","",'Daily Closes'!AA11/$E11-1)
A12: ='Daily Closes'!A12 | B12: ='Daily Closes'!B12 | C12: ='Daily Closes'!C12 | D12: ='Daily Closes'!D12 | E12: ='Daily Closes'!E12 | F12: — | G12: =IF('Daily Closes'!G12="","",'Daily Closes'!G12/$E12-1) | H12: =IF('Daily Closes'!H12="","",'Daily Closes'!H12/$E12-1) | I12: =IF('Daily Closes'!I12="","",'Daily Closes'!I12/$E12-1) | J12: =IF('Daily Closes'!J12="","",'Daily Closes'!J12/$E12-1) | K12: =IF('Daily Closes'!K12="","",'Daily Closes'!K12/$E12-1) | L12: =IF('Daily Closes'!L12="","",'Daily Closes'!L12/$E12-1) | M12: =IF('Daily Closes'!M12="","",'Daily Closes'!M12/$E12-1) | N12: =IF('Daily Closes'!N12="","",'Daily Closes'!N12/$E12-1) | ... AA12: =IF('Daily Closes'!AA12="","",'Daily Closes'!AA12/$E12-1)
A13: ='Daily Closes'!A13 | B13: ='Daily Closes'!B13 | C13: ='Daily Closes'!C13 | D13: ='Daily Closes'!D13 | E13: ='Daily Closes'!E13 | F13: — | G13: =IF('Daily Closes'!G13="","",'Daily Closes'!G13/$E13-1) | H13: =IF('Daily Closes'!H13="","",'Daily Closes'!H13/$E13-1) | I13: =IF('Daily Closes'!I13="","",'Daily Closes'!I13/$E13-1) | J13: =IF('Daily Closes'!J13="","",'Daily Closes'!J13/$E13-1) | K13: =IF('Daily Closes'!K13="","",'Daily Closes'!K13/$E13-1) | L13: =IF('Daily Closes'!L13="","",'Daily Closes'!L13/$E13-1) | M13: =IF('Daily Closes'!M13="","",'Daily Closes'!M13/$E13-1) | N13: =IF('Daily Closes'!N13="","",'Daily Closes'!N13/$E13-1) | ... AA13: =IF('Daily Closes'!AA13="","",'Daily Closes'!AA13/$E13-1)
A14: ='Daily Closes'!A14 | B14: ='Daily Closes'!B14 | C14: ='Daily Closes'!C14 | D14: ='Daily Closes'!D14 | E14: ='Daily Closes'!E14 | F14: — | G14: =IF('Daily Closes'!G14="","",'Daily Closes'!G14/$E14-1) | H14: =IF('Daily Closes'!H14="","",'Daily Closes'!H14/$E14-1) | I14: =IF('Daily Closes'!I14="","",'Daily Closes'!I14/$E14-1) | J14: =IF('Daily Closes'!J14="","",'Daily Closes'!J14/$E14-1) | K14: =IF('Daily Closes'!K14="","",'Daily Closes'!K14/$E14-1) | L14: =IF('Daily Closes'!L14="","",'Daily Closes'!L14/$E14-1) | M14: =IF('Daily Closes'!M14="","",'Daily Closes'!M14/$E14-1) | N14: =IF('Daily Closes'!N14="","",'Daily Closes'!N14/$E14-1) | ... AA14: =IF('Daily Closes'!AA14="","",'Daily Closes'!AA14/$E14-1)
A15: ='Daily Closes'!A15 | B15: ='Daily Closes'!B15 | C15: ='Daily Closes'!C15 | D15: ='Daily Closes'!D15 | E15: ='Daily Closes'!E15 | F15: — | G15: =IF('Daily Closes'!G15="","",'Daily Closes'!G15/$E15-1) | H15: =IF('Daily Closes'!H15="","",'Daily Closes'!H15/$E15-1) | I15: =IF('Daily Closes'!I15="","",'Daily Closes'!I15/$E15-1) | J15: =IF('Daily Closes'!J15="","",'Daily Closes'!J15/$E15-1) | K15: =IF('Daily Closes'!K15="","",'Daily Closes'!K15/$E15-1) | L15: =IF('Daily Closes'!L15="","",'Daily Closes'!L15/$E15-1) | M15: =IF('Daily Closes'!M15="","",'Daily Closes'!M15/$E15-1) | N15: =IF('Daily Closes'!N15="","",'Daily Closes'!N15/$E15-1) | ... AA15: =IF('Daily Closes'!AA15="","",'Daily Closes'!AA15/$E15-1)
B16: PORTFOLIO | G16: =IF('Daily Closes'!G16="","",'Daily Closes'!G16/'Daily Closes'!$E$16-1) | H16: =IF('Daily Closes'!H16="","",'Daily Closes'!H16/'Daily Closes'!$E$16-1) | I16: =IF('Daily Closes'!I16="","",'Daily Closes'!I16/'Daily Closes'!$E$16-1) | J16: =IF('Daily Closes'!J16="","",'Daily Closes'!J16/'Daily Closes'!$E$16-1) | K16: =IF('Daily Closes'!K16="","",'Daily Closes'!K16/'Daily Closes'!$E$16-1) | L16: =IF('Daily Closes'!L16="","",'Daily Closes'!L16/'Daily Closes'!$E$16-1) | M16: =IF('Daily Closes'!M16="","",'Daily Closes'!M16/'Daily Closes'!$E$16-1) | N16: =IF('Daily Closes'!N16="","",'Daily Closes'!N16/'Daily Closes'!$E$16-1) | ... AA16: =IF('Daily Closes'!AA16="","",'Daily Closes'!AA16/'Daily Closes'!$E$16-1)

Sheet P&L
A1: Mark-to-Market P&L (₹)
A2: Qty × (close − entry). Gross of costs.
A4: # | B4: Symbol | C4: ISIN | D4: Qty | E4: Entry ₹ | F4: Day 0 | G4: Day 1 | H4: Day 2 | I4: Day 3 | J4: Day 4 | K4: Day 5 | L4: Day 6 | M4: Day 7 | N4: Day 8 | O4: Day 9 | P4: Day 10 | Q4: Day 11 | R4: Day 12 | S4: Day 13 | T4: Day 14 | U4: Day 15 | V4: Day 16 | W4: Day 17 | X4: Day 18 | Y4: Day 19 | Z4: Day 20 | AA4: Day 21
A6: ='Daily Closes'!A6 | B6: ='Daily Closes'!B6 | C6: ='Daily Closes'!C6 | D6: ='Daily Closes'!D6 | E6: ='Daily Closes'!E6 | F6: — | G6: =IF('Daily Closes'!G6="","",$D6*('Daily Closes'!G6-$E6)) | H6: =IF('Daily Closes'!H6="","",$D6*('Daily Closes'!H6-$E6)) | I6: =IF('Daily Closes'!I6="","",$D6*('Daily Closes'!I6-$E6)) | J6: =IF('Daily Closes'!J6="","",$D6*('Daily Closes'!J6-$E6)) | K6: =IF('Daily Closes'!K6="","",$D6*('Daily Closes'!K6-$E6)) | L6: =IF('Daily Closes'!L6="","",$D6*('Daily Closes'!L6-$E6)) | M6: =IF('Daily Closes'!M6="","",$D6*('Daily Closes'!M6-$E6)) | N6: =IF('Daily Closes'!N6="","",$D6*('Daily Closes'!N6-$E6)) | ... AA6: =IF('Daily Closes'!AA6="","",$D6*('Daily Closes'!AA6-$E6))
A7: ='Daily Closes'!A7 | B7: ='Daily Closes'!B7 | C7: ='Daily Closes'!C7 | D7: ='Daily Closes'!D7 | E7: ='Daily Closes'!E7 | F7: — | G7: =IF('Daily Closes'!G7="","",$D7*('Daily Closes'!G7-$E7)) | H7: =IF('Daily Closes'!H7="","",$D7*('Daily Closes'!H7-$E7)) | I7: =IF('Daily Closes'!I7="","",$D7*('Daily Closes'!I7-$E7)) | J7: =IF('Daily Closes'!J7="","",$D7*('Daily Closes'!J7-$E7)) | K7: =IF('Daily Closes'!K7="","",$D7*('Daily Closes'!K7-$E7)) | L7: =IF('Daily Closes'!L7="","",$D7*('Daily Closes'!L7-$E7)) | M7: =IF('Daily Closes'!M7="","",$D7*('Daily Closes'!M7-$E7)) | N7: =IF('Daily Closes'!N7="","",$D7*('Daily Closes'!N7-$E7)) | ... AA7: =IF('Daily Closes'!AA7="","",$D7*('Daily Closes'!AA7-$E7))
A8: ='Daily Closes'!A8 | B8: ='Daily Closes'!B8 | C8: ='Daily Closes'!C8 | D8: ='Daily Closes'!D8 | E8: ='Daily Closes'!E8 | F8: — | G8: =IF('Daily Closes'!G8="","",$D8*('Daily Closes'!G8-$E8)) | H8: =IF('Daily Closes'!H8="","",$D8*('Daily Closes'!H8-$E8)) | I8: =IF('Daily Closes'!I8="","",$D8*('Daily Closes'!I8-$E8)) | J8: =IF('Daily Closes'!J8="","",$D8*('Daily Closes'!J8-$E8)) | K8: =IF('Daily Closes'!K8="","",$D8*('Daily Closes'!K8-$E8)) | L8: =IF('Daily Closes'!L8="","",$D8*('Daily Closes'!L8-$E8)) | M8: =IF('Daily Closes'!M8="","",$D8*('Daily Closes'!M8-$E8)) | N8: =IF('Daily Closes'!N8="","",$D8*('Daily Closes'!N8-$E8)) | ... AA8: =IF('Daily Closes'!AA8="","",$D8*('Daily Closes'!AA8-$E8))
A9: ='Daily Closes'!A9 | B9: ='Daily Closes'!B9 | C9: ='Daily Closes'!C9 | D9: ='Daily Closes'!D9 | E9: ='Daily Closes'!E9 | F9: — | G9: =IF('Daily Closes'!G9="","",$D9*('Daily Closes'!G9-$E9)) | H9: =IF('Daily Closes'!H9="","",$D9*('Daily Closes'!H9-$E9)) | I9: =IF('Daily Closes'!I9="","",$D9*('Daily Closes'!I9-$E9)) | J9: =IF('Daily Closes'!J9="","",$D9*('Daily Closes'!J9-$E9)) | K9: =IF('Daily Closes'!K9="","",$D9*('Daily Closes'!K9-$E9)) | L9: =IF('Daily Closes'!L9="","",$D9*('Daily Closes'!L9-$E9)) | M9: =IF('Daily Closes'!M9="","",$D9*('Daily Closes'!M9-$E9)) | N9: =IF('Daily Closes'!N9="","",$D9*('Daily Closes'!N9-$E9)) | ... AA9: =IF('Daily Closes'!AA9="","",$D9*('Daily Closes'!AA9-$E9))
A10: ='Daily Closes'!A10 | B10: ='Daily Closes'!B10 | C10: ='Daily Closes'!C10 | D10: ='Daily Closes'!D10 | E10: ='Daily Closes'!E10 | F10: — | G10: =IF('Daily Closes'!G10="","",$D10*('Daily Closes'!G10-$E10)) | H10: =IF('Daily Closes'!H10="","",$D10*('Daily Closes'!H10-$E10)) | I10: =IF('Daily Closes'!I10="","",$D10*('Daily Closes'!I10-$E10)) | J10: =IF('Daily Closes'!J10="","",$D10*('Daily Closes'!J10-$E10)) | K10: =IF('Daily Closes'!K10="","",$D10*('Daily Closes'!K10-$E10)) | L10: =IF('Daily Closes'!L10="","",$D10*('Daily Closes'!L10-$E10)) | M10: =IF('Daily Closes'!M10="","",$D10*('Daily Closes'!M10-$E10)) | N10: =IF('Daily Closes'!N10="","",$D10*('Daily Closes'!N10-$E10)) | ... AA10: =IF('Daily Closes'!AA10="","",$D10*('Daily Closes'!AA10-$E10))
A11: ='Daily Closes'!A11 | B11: ='Daily Closes'!B11 | C11: ='Daily Closes'!C11 | D11: ='Daily Closes'!D11 | E11: ='Daily Closes'!E11 | F11: — | G11: =IF('Daily Closes'!G11="","",$D11*('Daily Closes'!G11-$E11)) | H11: =IF('Daily Closes'!H11="","",$D11*('Daily Closes'!H11-$E11)) | I11: =IF('Daily Closes'!I11="","",$D11*('Daily Closes'!I11-$E11)) | J11: =IF('Daily Closes'!J11="","",$D11*('Daily Closes'!J11-$E11)) | K11: =IF('Daily Closes'!K11="","",$D11*('Daily Closes'!K11-$E11)) | L11: =IF('Daily Closes'!L11="","",$D11*('Daily Closes'!L11-$E11)) | M11: =IF('Daily Closes'!M11="","",$D11*('Daily Closes'!M11-$E11)) | N11: =IF('Daily Closes'!N11="","",$D11*('Daily Closes'!N11-$E11)) | ... AA11: =IF('Daily Closes'!AA11="","",$D11*('Daily Closes'!AA11-$E11))
A12: ='Daily Closes'!A12 | B12: ='Daily Closes'!B12 | C12: ='Daily Closes'!C12 | D12: ='Daily Closes'!D12 | E12: ='Daily Closes'!E12 | F12: — | G12: =IF('Daily Closes'!G12="","",$D12*('Daily Closes'!G12-$E12)) | H12: =IF('Daily Closes'!H12="","",$D12*('Daily Closes'!H12-$E12)) | I12: =IF('Daily Closes'!I12="","",$D12*('Daily Closes'!I12-$E12)) | J12: =IF('Daily Closes'!J12="","",$D12*('Daily Closes'!J12-$E12)) | K12: =IF('Daily Closes'!K12="","",$D12*('Daily Closes'!K12-$E12)) | L12: =IF('Daily Closes'!L12="","",$D12*('Daily Closes'!L12-$E12)) | M12: =IF('Daily Closes'!M12="","",$D12*('Daily Closes'!M12-$E12)) | N12: =IF('Daily Closes'!N12="","",$D12*('Daily Closes'!N12-$E12)) | ... AA12: =IF('Daily Closes'!AA12="","",$D12*('Daily Closes'!AA12-$E12))
A13: ='Daily Closes'!A13 | B13: ='Daily Closes'!B13 | C13: ='Daily Closes'!C13 | D13: ='Daily Closes'!D13 | E13: ='Daily Closes'!E13 | F13: — | G13: =IF('Daily Closes'!G13="","",$D13*('Daily Closes'!G13-$E13)) | H13: =IF('Daily Closes'!H13="","",$D13*('Daily Closes'!H13-$E13)) | I13: =IF('Daily Closes'!I13="","",$D13*('Daily Closes'!I13-$E13)) | J13: =IF('Daily Closes'!J13="","",$D13*('Daily Closes'!J13-$E13)) | K13: =IF('Daily Closes'!K13="","",$D13*('Daily Closes'!K13-$E13)) | L13: =IF('Daily Closes'!L13="","",$D13*('Daily Closes'!L13-$E13)) | M13: =IF('Daily Closes'!M13="","",$D13*('Daily Closes'!M13-$E13)) | N13: =IF('Daily Closes'!N13="","",$D13*('Daily Closes'!N13-$E13)) | ... AA13: =IF('Daily Closes'!AA13="","",$D13*('Daily Closes'!AA13-$E13))
A14: ='Daily Closes'!A14 | B14: ='Daily Closes'!B14 | C14: ='Daily Closes'!C14 | D14: ='Daily Closes'!D14 | E14: ='Daily Closes'!E14 | F14: — | G14: =IF('Daily Closes'!G14="","",$D14*('Daily Closes'!G14-$E14)) | H14: =IF('Daily Closes'!H14="","",$D14*('Daily Closes'!H14-$E14)) | I14: =IF('Daily Closes'!I14="","",$D14*('Daily Closes'!I14-$E14)) | J14: =IF('Daily Closes'!J14="","",$D14*('Daily Closes'!J14-$E14)) | K14: =IF('Daily Closes'!K14="","",$D14*('Daily Closes'!K14-$E14)) | L14: =IF('Daily Closes'!L14="","",$D14*('Daily Closes'!L14-$E14)) | M14: =IF('Daily Closes'!M14="","",$D14*('Daily Closes'!M14-$E14)) | N14: =IF('Daily Closes'!N14="","",$D14*('Daily Closes'!N14-$E14)) | ... AA14: =IF('Daily Closes'!AA14="","",$D14*('Daily Closes'!AA14-$E14))
A15: ='Daily Closes'!A15 | B15: ='Daily Closes'!B15 | C15: ='Daily Closes'!C15 | D15: ='Daily Closes'!D15 | E15: ='Daily Closes'!E15 | F15: — | G15: =IF('Daily Closes'!G15="","",$D15*('Daily Closes'!G15-$E15)) | H15: =IF('Daily Closes'!H15="","",$D15*('Daily Closes'!H15-$E15)) | I15: =IF('Daily Closes'!I15="","",$D15*('Daily Closes'!I15-$E15)) | J15: =IF('Daily Closes'!J15="","",$D15*('Daily Closes'!J15-$E15)) | K15: =IF('Daily Closes'!K15="","",$D15*('Daily Closes'!K15-$E15)) | L15: =IF('Daily Closes'!L15="","",$D15*('Daily Closes'!L15-$E15)) | M15: =IF('Daily Closes'!M15="","",$D15*('Daily Closes'!M15-$E15)) | N15: =IF('Daily Closes'!N15="","",$D15*('Daily Closes'!N15-$E15)) | ... AA15: =IF('Daily Closes'!AA15="","",$D15*('Daily Closes'!AA15-$E15))
B16: TOTAL | G16: =IF(COUNT(G6:G15)=0,"",SUM(G6:G15)) | H16: =IF(COUNT(H6:H15)=0,"",SUM(H6:H15)) | I16: =IF(COUNT(I6:I15)=0,"",SUM(I6:I15)) | J16: =IF(COUNT(J6:J15)=0,"",SUM(J6:J15)) | K16: =IF(COUNT(K6:K15)=0,"",SUM(K6:K15)) | L16: =IF(COUNT(L6:L15)=0,"",SUM(L6:L15)) | M16: =IF(COUNT(M6:M15)=0,"",SUM(M6:M15)) | N16: =IF(COUNT(N6:N15)=0,"",SUM(N6:N15)) | ... AA16: =IF(COUNT(AA6:AA15)=0,"",SUM(AA6:AA15))

Sheet Portfolio Path
A1: Portfolio Path — Day by Day
A2: Value, P&L, return, drawdown and Nifty 50 comparison
A4: Day | B4: Date | C4: Status | D4: Portfolio Value ₹ | E4: P&L ₹ | F4: Return % | G4: Daily % | H4: Drawdown % | I4: Nifty 50 %
A5: 0 | B5: 2026-09-28 | C5: Signal | D5: 139903 | E5: 0 | F5: 0 | I5: 0
A6: 1 | B6: 2026-09-29 | C6: Entry | D6: 145178.6 | E6: 5223.55 | F6: 0.037323 | H6: 0 | I6: -0.002812
A7: 2 | B7: 2026-09-30 | C7: Hold | D7: 144421.3 | E7: 4466.25 | F7: 0.031912 | G7: -0.005216 | H7: -0.005216 | I7: -0.007015
A8: 3 | B8: 2026-10-01 | C8: Hold | D8: 142311.25 | E8: 2356.2 | F8: 0.016835 | G8: -0.01461 | H8: -0.019751 | I8: -0.015729
A9: 4 | B9: 2026-10-02 | C9: Hold | D9: 142311.25 | E9: 2356.2 | F9: 0.016835 | G9: 0 | H9: -0.019751 | I9: -0.015729
A10: 5 | B10: 2026-10-05 | C10: Hold | D10: 144045.15 | E10: 4090.1 | F10: 0.029224 | G10: 0.012184 | H10: -0.007807 | I10: -0.009855
A11: 6 | B11: 2026-10-06 | C11: Hold | D11: 148186.35 | E11: 8231.3 | F11: 0.058814 | G11: 0.028749 | H11: 0 | I11: -0.000182
A12: 7 | B12: 2026-10-07 | C12: Hold | D12: 148825.15 | E12: 8870.1 | F12: 0.063378 | G12: 0.004311 | H12: 0 | I12: -0.007779
A13: 8 | B13: 2026-10-08 | C13: Hold | D13: 145212.55 | E13: 5257.5 | F13: 0.037566 | G13: -0.024274 | H13: -0.024274 | I13: -0.024076
A14: 9 | B14: 2026-10-09 | C14: Hold | D14: 146665.1 | E14: 6710.05 | F14: 0.047944 | G14: 0.010003 | H14: -0.014514 | I14: -0.011405
A15: 10 | B15: 2026-10-12 | C15: Hold | D15: 150238.35 | E15: 10283.3 | F15: 0.073476 | G15: 0.024363 | H15: 0 | I15: -0.018301
A16: 11 | B16: 2026-10-13 | C16: Hold | D16: 148485.25 | E16: 8530.2 | F16: 0.06095 | G16: -0.011669 | H16: -0.011669 | I16: -0.002559
A17: 12 | B17: 2026-10-14 | C17: Hold | D17: 148334.2 | E17: 8379.15 | F17: 0.05987 | G17: -0.001017 | H17: -0.012674 | I17: -0.006916
A18: 13 | B18: 2026-10-15 | C18: Hold | D18: 143337.25 | E18: 3382.2 | F18: 0.024166 | G18: -0.033687 | H18: -0.045934 | I18: 0.00953
... A23: 18 | B23: 2026-10-23 | C23: Hold | D23: 127614.75 | E23: -12340.3 | F23: -0.088173 | G23: -0.039092 | H23: -0.150585 | I23: -0.007913
A24: 19 | B24: 2026-10-27 | C24: Hold (upcoming)
A25: 20 | B25: 2026-10-28 | C25: Exit reminder (upcoming)
A26: 21 | B26: 2026-10-29 | C26: Exit (upcoming)

Sheet Batch Info
A1: Batch Details (from SwingScope HTML)
A2: SwingScope batch 2026-09-28
B4: Batch ID | C4: 2026-09-28
B5: Signal date (Day 0) | C5: 2026-09-28
B6: Exit (HTML estimate) | C6: 2026-10-27
B7: Exit (projected, NSE calendar) | C7: 2026-10-29
B8: Hold | C8: 21 sessions — no stop, no target
B9: Universe | C9: liquidity top 400 of all NSE stocks
B10: Capital committed (at signal close) | C10: 139903
B11: Estimated costs | C11: 859
B12: Cost % | C12: 0.6%
B13: Market regime | C13: Down — the signal's weakest regime historically
B14: Stocks with a warning | C14: 0 of 10
B17: # | C17: Symbol | D17: ISIN | E17: Qty | F17: Signal close | G17: Amount | H17: 12-1 % | I17: 6-1 % | J17: 3-1 % | K17: Vol % | L17: Traded daily (cr) | M17: From 12m high % | N17: Signal rank | O17: Data quality | P17: Watch
B18: 1 | C18: TDPOWERSYS | D18: INE419M01035 | E18: 20 | F18: 722 | G18: 14440 | H18: 177 | I18: 72.2 | J18: 19.6 | K18: 60.1 | L18: 128 | M18: -10.3 | N18: 6 | O18: Green | P18: Nothing flagged
B19: 2 | C19: AEROFLEX | D19: INE024001021 | E19: 29 | F19: 513.4 | G19: 14889 | H19: 175 | I19: 107 | J19: 10.7 | K19: 67.3 | L19: 53 | M19: -10.5 | N19: 7 | O19: Green | P19: Nothing flagged
B20: 3 | C20: ATHERENERG | D20: INE0LEZ01016 | E20: 10 | F20: 1454.9 | G20: 14549 | H20: 166 | I20: 97.5 | J20: 31.1 | K20: 49.4 | L20: 493 | M20: -15.7 | N20: 9 | O20: Green | P20: Nothing flagged
B21: 4 | C21: THANGAMAYL | D21: INE085J01014 | E21: 2 | F21: 5011.5 | G21: 10023 | H21: 154 | I21: 66.3 | J21: -14 | K21: 59.8 | L21: 71 | M21: -31.4 | N21: 11 | O21: Green | P21: Nothing flagged
B22: 5 | C22: RRKABEL | D22: INE777K01022 | E22: 6 | F22: 2459.8 | G22: 14759 | H22: 126 | I22: 110 | J22: 18.2 | K22: 44 | L22: 93 | M22: -16 | N22: 15 | O22: Green | P22: Nothing flagged
B23: 6 | C23: ACUTAAS | D23: INE00FF01025 | E23: 4 | F23: 3214.4 | G23: 12858 | H23: 126 | I23: 36.7 | J23: -5.6 | K23: 46.7 | L23: 101 | M23: -13 | N23: 16 | O23: Green | P23: Nothing flagged
B24: 7 | C24: DIACABS | D24: INE989C01038 | E24: 44 | F24: 339.25 | G24: 14927 | H24: 124 | I24: 180 | J24: 61.7 | K24: 53.6 | L24: 51 | M24: -14.1 | N24: 17 | O24: Green | P24: Nothing flagged
B25: 8 | C25: KIRLOSENG | D25: INE146L01010 | E25: 7 | F25: 2141.2 | G25: 14988 | H25: 123 | I25: 58.2 | J25: -11.2 | K25: 49.9 | L25: 87 | M25: -16.5 | N25: 18 | O25: Green | P25: Nothing flagged
B26: 9 | C26: E2E | D26: INE255Z01027 | E26: 23 | F26: 625.9 | G26: 14396 | H26: 109 | I26: 186 | J26: 56 | K26: 56.2 | L26: 49 | M26: -8.8 | N26: 20 | O26: Green | P26: Nothing flagged
B27: 10 | C27: LAURUSLABS | D27: INE947Q01028 | E27: 7 | F27: 2010.7 | G27: 14075 | H27: 109 | I27: 94.4 | J27: 27.2 | K27: 28.1 | L27: 300 | M27: -1.1 | N27: 21 | O27: Green | P27: Nothing flagged
B30: Evidence behind the rule (backtest, from HTML)
B31: Backtest, 2017–2026 | Replayed point in time on your survivorship-free archive. Not live results. | Signal strength | IC +0.041 | rank IC over 113 monthly dates, 2017-2026 (t 2.52); validated benchmark 0.026 | Top vs bottom decile | +1.89% | per 21-session hold, before costs (t 2.94) | Top-10 picks | +1.45% | per hold after 0.60% costs; Nifty 50 earned +1.02% before costs | Entry timing | Open wins | buying at the open beat all 30 support-entry rules (best -0.12% per hold) | Down markets | IC +0.009 | over 27 down-regime dates, against +0.050 over 86 up-regime dates
B32: Live record | No results yet | The first live result arrives when this system finishes its first batch. Live results are kept apart from the backtest and never mixed in.
B34: Corporate actions (splits, bonuses, dividends)
B35: None recorded during this hold.

Sheet Research
A1: Stock-by-Stock Research & Swing-Trade Shortlist
A2: Views from your research notes · written 2026-09-28 13:27
A4: Rank | B4: Symbol | C4: Company | D4: View | E4: Conviction | F4: Why | G4: Since entry % | H4: Call check
A5: 1 | B5: LAURUSLABS | C5: Laurus Labs | D5: Bullish | E5: 2 | F5: Relative strength near highs, lowest volatility, defensive sector | G5: -0.025090315 | H5: ✗ Off track
A6: 2 | B6: TDPOWERSYS | C6: TD Power Systems | D6: Bullish | E6: 1.5 | F6: Guidance raised, shallow pullback. Check for a fundraise. | G6: -0.1105007 | H6: ✗ Off track
A7: 3 | B7: ATHERENERG | C7: Ather Energy | D7: Bullish | E7: 1.25 | F7: Strong catalysts and brokers, but still pulling back | G7: -0.054923983 | H7: ✗ Off track
A8: 4 | B8: RRKABEL | C8: RR Kabel | D8: Moderately bullish | E8: 1 | F8: Strong Q1, moderate volatility | G8: -0.13001057 | H8: ✗ Off track
A9: 5 | B9: AEROFLEX | C9: Aeroflex Industries | D9: Bullish, risky | E9: 1.25 | F9: Strong growth, expensive, volatile, thin liquidity | G9: -0.11734794 | H9: ✗ Off track
A10: 6 | B10: E2E | C10: E2E Networks | D10: Speculative | E10: 0.5 | F10: Big revenue jump, P/E near 400 | G10: -0.086352998 | H10: ↓ Lagging
A11: 7 | B11: ACUTAAS | C11: Acutaas Chemicals | D11: Neutral | E11: 0 | F11: No catalyst, sideways trend | G11: -0.046291793 | H11: ↓ Lagging
A12: 8 | B12: DIACABS | C12: Diamond Power Infra | D12: Neutral to bearish | E12: -1 | F12: Extended, weak balance sheet | G12: -0.06485604 | H12: ✓ On track
A13: 9 | B13: KIRLOSENG | C13: Kirloskar Oil Engines | D13: Neutral to bearish | E13: -1 | F13: Margins and momentum fading | G13: -0.16649542 | H13: ✓ On track
A14: 10 | B14: THANGAMAYL | C14: Thangamayil Jewellery | D14: Bearish | E14: -2 | F14: Downtrend, avoid | G14: -0.063772455 | H14: ✓ On track
A16: STOCK BY STOCK — catalysts, risks and sources
A17: Rank | B17: Symbol | C17: Company | D17: Type | E17: Point | G17: Source | H17: Link
A18: 1 | B18: LAURUSLABS | C18: Laurus Labs | D18: Catalyst | E18: Its close is only 1.1% below its 12-month high, and its volatility is the lowest of the ten (28%).
A19: 1 | B19: LAURUSLABS | C19: Laurus Labs | D19: Catalyst | E19: FY26 profit after tax was ₹740 crore vs ₹380 crore the year before. | G19: torusdigital | H19: open ↗
A20: 1 | B20: LAURUSLABS | C20: Laurus Labs | D20: Catalyst | E20: It is up about 94% in six months and holding near highs while the index falls. | G20: anandrathi | H20: open ↗
A21: 1 | B21: LAURUSLABS | C21: Laurus Labs | D21: Catalyst | E21: Pharma is also defensive in a risk-off tape. | G21: anandrathi | H21: open ↗
A22: 1 | B22: LAURUSLABS | C22: Laurus Labs | D22: Risk | E22: P/E is high, so it can still pull back. | G22: anandrathi | H22: open ↗
A23: 2 | B23: TDPOWERSYS | C23: TD Power Systems | D23: Context | E23: The stock is 10% below its high, a shallow pullback within a strong uptrend.
A24: 2 | B24: TDPOWERSYS | C24: TD Power Systems | D24: Catalyst | E24: Q1 FY27 revenue rose about 72% YoY. | G24: 5paisa | H24: open ↗
A25: 2 | B25: TDPOWERSYS | C25: TD Power Systems | D25: Catalyst | E25: It raised its FY27 revenue guidance to ₹2,600 crore. | G25: fyers | H25: open ↗
A26: 2 | B26: TDPOWERSYS | C26: TD Power Systems | D26: Risk | E26: A board meeting on 14 Aug was set to consider raising funds, so check whether a dilutive QIP is pending. | G26: 5paisa | H26: open ↗
A27: 2 | B27: TDPOWERSYS | C27: TD Power Systems | D27: Risk | E27: Valuation is stretched (P/E around 70). | G27: 5paisa | H27: open ↗
A28: 3 | B28: ATHERENERG | C28: Ather Energy | D28: Catalyst | E28: Q1 revenue grew 89% and the loss narrowed 71%. | G28: indmoney | H28: open ↗
A29: 3 | B29: ATHERENERG | C29: Ather Energy | D29: Catalyst | E29: It was also added to the MSCI India Domestic Small Cap Index. | G29: indmoney | H29: open ↗
A30: 3 | B30: ATHERENERG | C30: Ather Energy | D30: Catalyst | E30: Hero MotoCorp is lifting its stake to about 32.8%. | G30: freepressjournal | H30: open ↗
A31: 3 | B31: ATHERENERG | C31: Ather Energy | D31: Catalyst | E31: A global broker raised its target to ₹1,926. | G31: hdfcsky | H31: open ↗
A32: 3 | B32: ATHERENERG | C32: Ather Energy | D32: Context | E32: The stock has slid about 16% from its early-September high, so the story is intact but the price is digesting a big run.
A33: 3 | B33: ATHERENERG | C33: Ather Energy | D33: Catalyst | E33: High oil prices are a tailwind for the EV theme.
A34: 4 | B34: RRKABEL | C34: RR Kabel | D34: Catalyst | E34: Q1 PAT jumped 129% and EBITDA doubled. | G34: 5paisa | H34: open ↗
A35: 4 | B35: RRKABEL | C35: RR Kabel | D35: Catalyst | E35: CLSA initiated at Outperform with a ₹2,850 target. | G35: fyers | H35: open ↗
A36: 4 | B36: RRKABEL | C36: RR Kabel | D36: Context | E36: The stock is 16% off its high, so it is consolidating.
A37: 4 | B37: RRKABEL | C37: RR Kabel | D37: Catalyst | E37: Volatility is moderate (44%), which is better than most here.
A38: 5 | B38: AEROFLEX | C38: Aeroflex Industries | D38: Catalyst | E38: Q1 FY27 revenue grew 72.4% and PAT rose 162%. | G38: sahi | H38: open ↗
A39: 5 | B39: AEROFLEX | C39: Aeroflex Industries | D39: Catalyst | E39: Liquid-cooling skid capacity was raised 50%, with further expansion planned. | G39: sahi | H39: open ↗
A40: 5 | B40: AEROFLEX | C40: Aeroflex Industries | D40: Risk | E40: P/E is about 102, volatility is the highest of the ten (67%), and liquidity is thin (₹53 cr/day). | G40: share | H40: open ↗
A41: 5 | B41: AEROFLEX | C41: Aeroflex Industries | D41: Risk | E41: That makes it the most fragile in a falling market. | G41: share | H41: open ↗
A42: 6 | B42: E2E | C42: E2E Networks | D42: Catalyst | E42: Q1 revenue was ₹156.76 crore vs ₹36.11 crore a year earlier, with a profit of ₹43.88 crore, on GPU cluster expansion. | G42: angelone | H42: open ↗
A43: 6 | B43: E2E | C43: E2E Networks | D43: Risk | E43: P/E is about 398 and the stock fell 11.8% in the month to 18 Sep. | G43: anandrathi | H43: open ↗
A44: 6 | B44: E2E | C44: E2E Networks | D44: Context | E44: It has bounced since. | G44: anandrathi | H44: open ↗
A45: 6 | B45: E2E | C45: E2E Networks | D45: Risk | E45: It is an AI-theme stock with thin liquidity and gap risk in both directions.
A46: 7 | B46: ACUTAAS | C46: Acutaas Chemicals | D46: Catalyst | E46: It received PLI approval for an electrolyte additives plan and commissioned a high-potency API pilot plant. | G46: fyers | H46: open ↗
A47: 7 | B47: ACUTAAS | C47: Acutaas Chemicals | D47: Risk | E47: Quarterly revenue and profit were lower sequentially (₹327 cr and ₹76 cr in Jun vs ₹436 cr and ₹137 cr in Mar). | G47: anandrathi | H47: open ↗
A48: 7 | B48: ACUTAAS | C48: Acutaas Chemicals | D48: Risk | E48: The 6-1 return is negative. | G48: anandrathi | H48: open ↗
A49: 7 | B49: ACUTAAS | C49: Acutaas Chemicals | D49: Risk | E49: The price has moved sideways since June.
A50: 7 | B50: ACUTAAS | C50: Acutaas Chemicals | D50: Risk | E50: There is no clear trigger for a 21-day move.
A51: 8 | B51: DIACABS | C51: Diamond Power Infra | D51: Risk | E51: It hit a 52-week high of about ₹395 on 17 Sep, up 202% in six months, with a P/E near 128. | G51: anandrathi | H51: open ↗
A52: 8 | B52: DIACABS | C52: Diamond Power Infra | D52: Risk | E52: Book value per share was negative in the July data. | G52: bajajfinserv | H52: open ↗
A53: 8 | B53: DIACABS | C53: Diamond Power Infra | D53: Risk | E53: It is now 14% off that high.
A54: 8 | B54: DIACABS | C54: Diamond Power Infra | D54: Context | E54: The T&D order-book story is real, but the valuation and balance sheet make it a momentum-only trade.
A55: 9 | B55: KIRLOSENG | C55: Kirloskar Oil Engines | D55: Risk | E55: June-quarter revenue was ₹1,482 cr vs ₹1,284 cr a year ago, but EBITDA slipped to ₹176 cr from ₹184 cr, so margins are compressing. | G55: anandrathi | H55: open ↗
A56: 9 | B56: KIRLOSENG | C56: Kirloskar Oil Engines | D56: Risk | E56: The 6-1 return is −11% and the stock is 16.5% below its high.
A57: 9 | B57: KIRLOSENG | C57: Kirloskar Oil Engines | D57: Risk | E57: Momentum is fading.
A58: 10 | B58: THANGAMAYL | C58: Thangamayil Jewellery | D58: Context | E58: It hit a high of ₹7,429 and traded near ₹5,085 on 22 Sep. | G58: anandrathi | H58: open ↗
A59: 10 | B59: THANGAMAYL | C59: Thangamayil Jewellery | D59: Risk | E59: It is now about 31% below the peak. | G59: anandrathi | H59: open ↗
A60: 10 | B60: THANGAMAYL | C60: Thangamayil Jewellery | D60: Risk | E60: Q1 EBITDA (₹145 cr) fell from ₹214 cr in the March quarter. | G60: anandrathi | H60: open ↗
A61: 10 | B61: THANGAMAYL | C61: Thangamayil Jewellery | D61: Risk | E61: It has the weakest chart in the batch: a clear downtrend, a negative 6-1 return, and a gold-price-sensitive business.

Sheet News & Sentiment
A1: Positive News & Sentiment
A2: Fetched 2026-10-23 17:22
A4: Symbol | B4: Published | C4: Headline | D4: Source | E4: Sentiment | F4: Label | G4: Link
A5: MARKET | B5: 2026-10-23 16:48 | C5: Sensex, Nifty Extend Losing Streak to Fourth Session as Crude Surges above $114 | D5: The Indian Awaaz | E5: 0.077 | F5: Neutral | G5: open ↗
A6: MARKET | B6: 2026-10-23 15:07 | C6: Sensex, Nifty Fall for Fourth Consecutive Session as Geopolitical Tensions Rattle Indian Markets | D6: INDIA New England News | E6: -0.34 | F6: Negative | G6: open ↗
A7: AEROFLEX | B7: 2026-10-23 14:26 | C7: Aeroflex Enterprises NSE:AEROENTER Stilonn Acquisition | D7: Kalkine India | E7: 0 | F7: Neutral | G7: open ↗
A8: MARKET | B8: 2026-10-23 13:04 | C8: Stock Market Weekly Wrap: Rs 16 lakh crore mcap wiped out as Sensex sheds 1,605 points — what lies ahead? | D8: Zee Business | E8: -0.66 | F8: Negative | G8: open ↗
A9: MARKET | B9: 2026-10-23 12:56 | C9: Indian Renewable Energy Stocks Decline as Inox Wind Falls 5.45% on October 23 | D9: SolarQuarter | E9: -0.477 | F9: Negative | G9: open ↗
A10: MARKET | B10: 2026-10-23 12:00 | C10: Market wrap: Eternal, Apollo Hospital, Shriram Finance, Adani Enterprises among top gainers and losers on | D10: The Economic Times | E10: -0.382 | F10: Negative | G10: open ↗
A11: MARKET | B11: 2026-10-23 11:34 | C11: Sensex Fall Today: Sensex Drops 1,279 Points, Nifty Near 22,400 | D11: Business Outreach Magazine | E11: 0.077 | F11: Neutral | G11: open ↗
A12: MARKET | B12: 2026-10-23 11:22 | C12: Share Market Today: Nifty 50, Bank Nifty | Oct 23, 2026 | D12: Liquide Blog | E12: 0.66 | F12: Positive | G12: open ↗
A13: MARKET | B13: 2026-10-23 11:20 | C13: Indian Equities Fall for Fourth Day as West Asia Tensions Drive Oil Prices Higher | D13: Rediff | E13: -0.625 | F13: Negative | G13: open ↗
A14: MARKET | B14: 2026-10-23 11:19 | C14: Markets extend losses for 4th day amid selling pressure, oil price surge | D14: DT Next | E14: -0.026 | F14: Neutral | G14: open ↗
A15: MARKET | B15: 2026-10-23 10:54 | C15: Markets Fall for 4th Day as Crude Nears $114; Nifty Ends at 22,600 | D15: HDFC Sky | E15: -0.527 | F15: Negative | G15: open ↗
A16: MARKET | B16: 2026-10-23 10:46 | C16: Sensex Today Ends 126 Points lower | Nifty Below 22,650 | Tata Steel Drown 3% | D16: Equitymaster | E16: -0.421 | F16: Negative | G16: open ↗
... A135: E2E | B135: 2026-10-16 21:00 | C135: E2E Networks Ltd (NSE:E2E) Q2 2027 Earnings Call Highlights: Revenue Surges 411% YoY on ... | D135: Yahoo Finance | E135: 0.494 | F135: Positive | G135: open ↗

Sheet _state
A1: {"batch": {"batch_id": "2026-09-28", "title": "SwingScope batch 2026-09-28", "signal_date": "2026-09-28", "exit_date_est": "2026-10-27", "hold_sessions": 21, "universe": "liquidity top 400 of all NSE stocks", "capital": 139903.0, "est_costs": 859.0, "cost_pct": 0.6, "regime": "Down", "regime_note": "the signal's weakest regime historically", "warnings": "0 of 10", "evidence": ["Backtest, 2017\u20132026 | Replayed point in time on your survivorship-free archive. Not live results. | Signal strength | IC +0.041 | rank IC over 113 monthly dates, 2017-2026 (t 2.52); validated benchmark 0.026 | Top vs bottom decile | +1.89% | per 21-session hold, before costs (t 2.94) | Top-10 picks | +1.45% | per hold after 0.60% costs; Nifty 50 earned +1.02% before costs | Entry timing | Open wins | buying at the open beat all 30 support-entry rules (best -0.12% per hold) | Down markets | IC +0.009 | over 27 down-regime dates, against +0.050 over 86 up-regime dates", "Live record | No results yet | The first live result arrives when this system finishes its first batch. Live results are kept apart from the backtest and never mixed in."], "stocks": [{"rank": 1, "symbol": "TDPOWERSYS", "isin": "INE419M01035", "qty": 20, "last_close": 722.0, "amount": 14440.0, "spark_12m": "2.0,31.7 2.4,32.0 2.9,31.7 3.3,31.1 3.7,31.1 4.2,31.1 4.6,31.0 5.0,30.6 5.4,30.4 5.9,29.2 6.3,29.3 6.7,29.5 7.2,29.8 7.6,30.1 8.0,30.4 8.5,30.5 8.9,30.3 9.3,29.4 9.7,29.3 10.2,28.8 10.6,29.1 11.0,28.9 11.5,29.1 11.9,29.2 12.3,29.1 12.8,29.0 13.2,28.4 13.6,28.0 14.0,25.5 14.5,24.3 14.9,24.2 15.3,24.8 15.8,25.3 16.2,25.2 16.6,25.4 17.1,24.2 17.5,25.4 17.9,25.2 18.4,25.2 18.8,25.7 19.2,25.8 19.6,25.9 20.1,26.9 20.5,25.8 20.9,25.9 21.4,24.9 21.8,24.9 22.2,25.4 22.7,25.0 23.1,25.0 23.5,25.8 23.9,26.8 24.4,27.7 24.8,28.3 25.2,27.7 25.7,28.1 26.1,28.2 26.5,27.9 27.0,27.6 27.4,27.9 27.8,27.1 28.2,27.6 28.7,27.1 29.1,26.4 29.5,26.7 30.0,27.0 30.4,27.3 30.8,27.7 31.3,27.5 31.7,27.5 32.1,28.3 32.5,28.0 33.0,27.7 33.4,27.9 33.8,27.5 34.3,27.9 34.7,28.3 35.1,28.8 35.6,27.9 36.0,28.2 36.4,28.5 36.9,28.7 37.3,29.2 37.7,29.4 38.1,29.5 38.6,29.7 39.0,29.6 39.4,28.8 39.9,28.2 40.3,26.7 40.7,26.2 41.2,24.3 41.6,24.1 42.0,24.5 42.4,25.2 42.9,24.8 43.3,23.3 43.7,22.8 44.2,23.4 44.6,23.8 45.0,23.1 45.5,22.8 45.9,22.8 46.3,22.4 46.7,22.4 47.2,21.8 47.6,22.3 48.0,22.5 48.5,22.5 48.9,21.8 49.3,22.2 49.8,22.6 50.2,22.4 50.6,22.5 51.1,23.5 51.5,24.3 51.9,24.7 52.3,24.4 52.8,25.3 53.2,24.9 53.6,24.3 54.1,23.7 54.5,23.8 54.9,23.0 55.4,24.2 55.8,23.1 56.2,22.3 56.6,23.4 57.1,23.3 57.5,23.0 57.9,23.0 58.4,22.5 58.8,22.5 59.2,22.4 59.7,22.6 60.1,21.2 60.5,21.5 60.9,20.8 61.4,20.0 61.8,19.2 62.2,18.3 62.7,18.6 63.1,17.4 63.5,17.2 64.0,16.0 64.4,16.6 64.8,15.0 65.3,15.0 65.7,14.8 66.1,14.6 66.5,14.2 67.0,14.5 67.4,12.2 67.8,13.0 68.3,14.1 68.7,14.4 69.1,14.2 69.6,14.0 70.0,10.4 70.4,9.9 70.8,11.9 71.3,12.6 71.7,10.6 72.1,10.8 72.6,10.7 73.0,8.8 73.4,9.8 73.9,10.2 74.3,12.7 74.7,12.5 75.1,11.1 75.6,10.0 76.0,10.3 76.4,12.8 76.9,12.6 77.3,14.8 77.7,15.6 78.2,13.7 78.6,13.6 79.0,14.4 79.5,12.7 79.9,11.6 80.3,11.5 80.7,10.0 81.2,9.2 81.6,11.7 82.0,12.0 82.5,12.6 82.9,12.4 83.3,13.7 83.8,13.8 84.2,16.6 84.6,14.2 85.0,15.7 85.5,16.9 85.9,16.6 86.3,14.9 86.8,14.9 87.2,15.6 87.6,14.2 88.1,15.6 88.5,15.5 88.9,15.2 89.3,15.5 89.8,14.6 90.2,15.2 90.6,15.9 91.1,15.2 91.5,15.9 91.9,18.1 92.4,17.5 92.8,15.5 93.2,16.0 93.6,15.5 94.1,13.5 94.5,12.7 94.9,11.8 95.4,12.5 95.8,11.4 96.2,5.6 96.7,5.6 97.1,5.5 97.5,3.7 98.0,2.7 98.4,3.8 98.8,4.9 99.2,4.1 99.7,3.4 100.1,6.2 100.5,6.3 101.0,5.6 101.4,4.9 101.8,3.6 102.3,4.6 102.7,5.9 103.1,6.6 103.5,5.6 104.0,6.0 104.4,4.0 104.8,4.8 105.3,4.4 105.7,2.0 106.1,6.5 106.6,8.1 107.0,6.7 107.4,4.3 107.8,5.2 108.3,4.7 108.7,4.2 109.1,5.5 109.6,5.0 110.0,6.7", "ret_12_1": 177.0, "ret_6_1": 72.2, "ret_3_1": 19.6, "volatility": 60.1, "traded_daily_cr": 128.0, "watch": "Nothing flagged", "from_12m_high": -10.3, "signal_rank": 6, "data_quality": "Green"}, {"rank": 2, "symbol": "AEROFLEX", "isin": "INE024001021", "qty": 29, "last_close": 513.4, "amount": 14889.0, "spark_12m": "2.0,29.8 2.4,29.6 2.9,29.5 3.3,30.0 3.7,30.1 4.2,30.5 4.6,30.8 5.0,30.9 5.4,30.9 5.9,30.5 6.3,30.7 6.7,30.8 7.2,30.9 7.6,31.0 8.0,31.0 8.5,31.1 8.9,31.2 9.3,31.2 9.7,31.2 10.2,31.2 10.6,31.4 11.0,31.1 11.5,31.0 11.9,31.0 12.3,31.0 12.8,30.1 13.2,30.1 13.6,30.5 14.0,30.0 14.5,29.8 14.9,30.3 15.3,30.5 15.8,30.0 16.2,30.0 16.6,30.2 17.1,30.2 17.5,30.1 17.9,29.9 18.4,30.1 18.8,30.3 19.2,30.2 19.6,30.2 20.1,30.5 20.5,30.9 20.9,30.2 21.4,30.2 21.8,30.4 22.2,30.0 22.7,30.2 23.1,30.3 23.5,30.6 23.9,30.6 24.4,30.7 24.8,31.3 25.2,31.0 25.7,30.7 26.1,30.9 26.5,30.7 27.0,30.3 27.4,30.5 27.8,30.3 28.2,30.7 28.7,29.5 29.1,29.2 29.5,28.8 30.0,28.6 30.4,28.9 30.8,29.1 31.3,29.3 31.7,29.5 32.1,29.6 32.5,29.2 33.0,29.0 33.4,29.3 33.8,29.1 34.3,29.9 34.7,30.2 35.1,30.2 35.6,30.5 36.0,30.7 36.4,30.8 36.9,30.9 37.3,31.3 37.7,31.8 38.1,31.5 38.6,32.0 39.0,31.7 39.4,31.4 39.9,30.4 40.3,30.6 40.7,31.0 41.2,30.1 41.6,29.9 42.0,29.9 42.4,30.1 42.9,29.3 43.3,29.4 43.7,29.6 44.2,29.5 44.6,30.0 45.0,29.6 45.5,28.5 45.9,27.1 46.3,27.0 46.7,27.3 47.2,27.6 47.6,27.7 48.0,27.0 48.5,26.9 48.9,26.5 49.3,27.2 49.8,27.7 50.2,27.3 50.6,27.6 51.1,27.9 51.5,27.5 51.9,26.5 52.3,26.3 52.8,26.5 53.2,25.6 53.6,25.3 54.1,25.6 54.5,26.8 54.9,26.6 55.4,27.3 55.8,25.3 56.2,25.3 56.6,26.1 57.1,26.2 57.5,25.4 57.9,25.2 58.4,25.0 58.8,25.7 59.2,24.6 59.7,23.6 60.1,22.6 60.5,22.6 60.9,22.3 61.4,22.1 61.8,21.0 62.2,21.7 62.7,22.6 63.1,21.5 63.5,22.1 64.0,23.4 64.4,22.2 64.8,22.3 65.3,21.4 65.7,21.4 66.1,21.6 66.5,20.5 67.0,18.6 67.4,13.6 67.8,11.7 68.3,14.7 68.7,17.1 69.1,17.1 69.6,17.4 70.0,16.7 70.4,16.8 70.8,15.9 71.3,15.2 71.7,16.0 72.1,14.3 72.6,13.5 73.0,14.3 73.4,14.0 73.9,14.4 74.3,15.4 74.7,13.1 75.1,12.1 75.6,11.7 76.0,13.1 76.4,14.6 76.9,12.7 77.3,13.5 77.7,13.9 78.2,11.1 78.6,8.9 79.0,9.4 79.5,6.5 79.9,8.1 80.3,6.8 80.7,6.6 81.2,7.1 81.6,8.8 82.0,9.7 82.5,9.6 82.9,9.4 83.3,8.1 83.8,8.9 84.2,10.5 84.6,10.3 85.0,13.6 85.5,14.5 85.9,14.2 86.3,13.6 86.8,13.0 87.2,13.8 87.6,13.0 88.1,13.8 88.5,13.8 88.9,14.1 89.3,13.6 89.8,14.0 90.2,13.1 90.6,13.0 91.1,13.2 91.5,11.2 91.9,10.9 92.4,12.6 92.8,12.0 93.2,12.3 93.6,9.9 94.1,10.5 94.5,11.8 94.9,12.7 95.4,13.1 95.8,12.9 96.2,11.2 96.7,11.1 97.1,10.2 97.5,10.5 98.0,8.3 98.4,9.2 98.8,9.1 99.2,7.1 99.7,7.0 100.1,7.6 100.5,4.7 101.0,5.7 101.4,4.3 101.8,5.5 102.3,3.6 102.7,4.4 103.1,4.3 103.5,4.6 104.0,3.1 104.4,2.0 104.8,2.9 105.3,2.7 105.7,2.7 106.1,6.8 106.6,8.7 107.0,7.5 107.4,6.5 107.8,6.2 108.3,6.1 108.7,5.8 109.1,5.3 109.6,5.5 110.0,6.3", "ret_12_1": 175.0, "ret_6_1": 107.0, "ret_3_1": 10.7, "volatility": 67.3, "traded_daily_cr": 53.0, "watch": "Nothing flagged", "from_12m_high": -10.5, "signal_rank": 7, "data_quality": "Green"}, {"rank": 3, "symbol": "ATHERENERG", "isin": "INE0LEZ01016", "qty": 10, "last_close": 1454.9, "amount": 14549.0, "spark_12m": "2.0,30.9 2.4,30.7 2.9,31.2 3.3,30.9 3.7,31.6 4.2,32.0 4.6,31.0 5.0,31.4 5.4,30.8 5.9,30.7 6.3,30.0 6.7,29.7 7.2,29.5 7.6,29.9 8.0,30.6 8.5,30.2 8.9,30.1 9.3,29.6 9.7,28.2 10.2,28.1 10.6,27.4 11.0,26.3 11.5,27.1 11.9,27.8 12.3,27.1 12.8,27.0 13.2,27.8 13.6,27.8 14.0,28.2 14.5,28.2 14.9,28.8 15.3,29.6 15.8,29.1 16.2,29.8 16.6,29.0 17.1,29.8 17.5,29.5 17.9,29.2 18.4,29.3 18.8,28.7 19.2,28.3 19.6,28.0 20.1,28.1 20.5,28.6 20.9,28.3 21.4,28.1 21.8,27.7 22.2,27.5 22.7,27.7 23.1,28.3 23.5,28.4 23.9,28.7 24.4,28.6 24.8,28.5 25.2,29.2 25.7,29.3 26.1,29.3 26.5,29.3 27.0,28.3 27.4,28.6 27.8,28.9 28.2,28.9 28.7,27.9 29.1,28.0 29.5,27.8 30.0,27.4 30.4,27.7 30.8,27.5 31.3,27.1 31.7,26.6 32.1,27.0 32.5,26.9 33.0,28.3 33.4,28.1 33.8,28.1 34.3,28.6 34.7,29.6 35.1,29.5 35.6,29.1 36.0,29.3 36.4,30.0 36.9,29.8 37.3,30.3 37.7,30.1 38.1,29.7 38.6,29.9 39.0,30.0 39.4,30.3 39.9,30.4 40.3,29.9 40.7,30.3 41.2,28.6 41.6,28.0 42.0,27.6 42.4,27.8 42.9,27.3 43.3,27.3 43.7,27.5 44.2,27.3 44.6,27.7 45.0,27.7 45.5,27.3 45.9,27.2 46.3,27.1 46.7,27.7 47.2,27.5 47.6,28.0 48.0,27.8 48.5,27.9 48.9,27.7 49.3,27.8 49.8,27.9 50.2,28.3 50.6,28.6 51.1,28.4 51.5,28.1 51.9,27.9 52.3,27.7 52.8,27.8 53.2,27.6 53.6,27.3 54.1,26.7 54.5,26.6 54.9,25.9 55.4,26.7 55.8,26.5 56.2,26.0 56.6,25.5 57.1,26.6 57.5,26.2 57.9,26.4 58.4,25.8 58.8,26.4 59.2,26.2 59.7,24.9 60.1,23.8 60.5,22.7 60.9,23.6 61.4,23.7 61.8,24.1 62.2,23.2 62.7,23.0 63.1,22.7 63.5,22.9 64.0,23.3 64.4,21.8 64.8,22.1 65.3,21.9 65.7,22.0 66.1,22.0 66.5,21.9 67.0,23.0 67.4,22.7 67.8,22.5 68.3,21.1 68.7,22.3 69.1,21.6 69.6,21.9 70.0,21.9 70.4,22.6 70.8,22.6 71.3,22.7 71.7,23.2 72.1,23.3 72.6,22.3 73.0,21.6 73.4,21.5 73.9,21.3 74.3,21.9 74.7,21.4 75.1,19.8 75.6,20.7 76.0,19.5 76.4,20.3 76.9,19.5 77.3,19.3 77.7,19.7 78.2,19.6 78.6,19.7 79.0,20.4 79.5,20.6 79.9,21.1 80.3,21.1 80.7,21.4 81.2,20.2 81.6,20.6 82.0,20.4 82.5,18.2 82.9,16.8 83.3,17.1 83.8,16.7 84.2,17.1 84.6,17.2 85.0,16.8 85.5,15.3 85.9,14.8 86.3,14.6 86.8,15.7 87.2,15.3 87.6,12.9 88.1,13.6 88.5,13.2 88.9,12.9 89.3,13.1 89.8,13.6 90.2,14.5 90.6,15.1 91.1,14.9 91.5,15.2 91.9,14.1 92.4,14.3 92.8,13.8 93.2,13.5 93.6,9.0 94.1,8.4 94.5,8.9 94.9,8.2 95.4,8.6 95.8,7.1 96.2,6.0 96.7,7.0 97.1,7.4 97.5,8.1 98.0,8.6 98.4,9.3 98.8,9.0 99.2,8.7 99.7,8.9 100.1,9.2 100.5,7.8 101.0,7.8 101.4,4.8 101.8,2.2 102.3,2.0 102.7,3.0 103.1,4.2 103.5,5.6 104.0,5.2 104.4,5.7 104.8,5.7 105.3,3.7 105.7,3.8 106.1,6.0 106.6,6.0 107.0,6.4 107.4,4.2 107.8,5.4 108.3,6.6 108.7,7.7 109.1,7.7 109.6,7.8 110.0,8.8", "ret_12_1": 166.0, "ret_6_1": 97.5, "ret_3_1": 31.1, "volatility": 49.4, "traded_daily_cr": 493.0, "watch": "Nothing flagged", "from_12m_high": -15.7, "signal_rank": 9, "data_quality": "Green"}, {"rank": 4, "symbol": "THANGAMAYL", "isin": "INE085J01014", "qty": 2, "last_close": 5011.5, "amount": 10023.0, "spark_12m": "2.0,30.9 2.4,31.1 2.9,31.4 3.3,31.4 3.7,31.4 4.2,31.6 4.6,31.7 5.0,31.6 5.4,31.6 5.9,31.2 6.3,31.3 6.7,31.6 7.2,31.2 7.6,31.5 8.0,31.6 8.5,31.5 8.9,31.8 9.3,31.9 9.7,31.9 10.2,31.9 10.6,31.9 11.0,31.9 11.5,32.0 11.9,31.5 12.3,31.6 12.8,31.3 13.2,31.4 13.6,31.3 14.0,30.8 14.5,28.3 14.9,25.9 15.3,25.7 15.8,23.9 16.2,25.3 16.6,24.8 17.1,24.1 17.5,24.4 17.9,24.5 18.4,24.7 18.8,24.9 19.2,25.1 19.6,25.2 20.1,26.0 20.5,24.8 20.9,24.8 21.4,24.7 21.8,24.8 22.2,24.7 22.7,24.1 23.1,25.2 23.5,24.6 23.9,24.8 24.4,24.9 24.8,25.2 25.2,24.7 25.7,24.9 26.1,24.9 26.5,25.0 27.0,25.0 27.4,24.9 27.8,24.4 28.2,24.6 28.7,24.2 29.1,23.8 29.5,23.7 30.0,24.5 30.4,25.0 30.8,25.0 31.3,25.0 31.7,24.9 32.1,24.7 32.5,24.8 33.0,24.2 33.4,23.4 33.8,21.4 34.3,21.2 34.7,22.7 35.1,22.3 35.6,21.9 36.0,21.5 36.4,21.8 36.9,22.1 37.3,22.1 37.7,21.2 38.1,22.6 38.6,22.9 39.0,23.8 39.4,22.8 39.9,23.4 40.3,24.3 40.7,24.9 41.2,25.1 41.6,24.5 42.0,25.1 42.4,23.9 42.9,22.1 43.3,22.2 43.7,22.3 44.2,22.5 44.6,22.9 45.0,22.1 45.5,22.3 45.9,22.6 46.3,23.4 46.7,23.0 47.2,22.8 47.6,22.0 48.0,21.5 48.5,21.0 48.9,20.8 49.3,21.4 49.8,22.7 50.2,22.6 50.6,22.2 51.1,22.9 51.5,22.1 51.9,23.1 52.3,23.0 52.8,23.3 53.2,23.6 53.6,23.4 54.1,23.3 54.5,24.1 54.9,24.3 55.4,25.2 55.8,24.4 56.2,22.8 56.6,23.7 57.1,23.7 57.5,23.0 57.9,23.1 58.4,21.9 58.8,21.3 59.2,20.3 59.7,20.0 60.1,19.8 60.5,19.5 60.9,19.1 61.4,19.0 61.8,19.3 62.2,19.8 62.7,19.8 63.1,20.4 63.5,21.7 64.0,21.7 64.4,20.8 64.8,20.7 65.3,20.6 65.7,20.8 66.1,20.6 66.5,20.7 67.0,20.1 67.4,19.9 67.8,19.1 68.3,20.5 68.7,22.4 69.1,22.5 69.6,22.7 70.0,22.8 70.4,23.1 70.8,22.5 71.3,21.8 71.7,21.3 72.1,21.6 72.6,21.5 73.0,21.6 73.4,21.0 73.9,19.4 74.3,18.9 74.7,17.2 75.1,16.1 75.6,12.0 76.0,13.0 76.4,12.2 76.9,12.3 77.3,12.4 77.7,12.6 78.2,12.2 78.6,12.1 79.0,12.4 79.5,11.4 79.9,12.5 80.3,12.4 80.7,11.8 81.2,12.8 81.6,12.4 82.0,11.6 82.5,10.0 82.9,7.1 83.3,9.6 83.8,7.6 84.2,8.4 84.6,7.7 85.0,7.2 85.5,4.8 85.9,6.0 86.3,6.3 86.8,8.0 87.2,6.8 87.6,5.9 88.1,7.2 88.5,6.9 88.9,7.2 89.3,6.8 89.8,6.7 90.2,4.5 90.6,4.3 91.1,2.0 91.5,2.8 91.9,6.8 92.4,10.4 92.8,13.7 93.2,15.1 93.6,16.5 94.1,15.2 94.5,14.1 94.9,13.4 95.4,13.0 95.8,13.7 96.2,13.1 96.7,13.4 97.1,12.5 97.5,13.0 98.0,12.2 98.4,12.0 98.8,12.4 99.2,12.2 99.7,12.2 100.1,12.7 100.5,12.2 101.0,12.1 101.4,12.5 101.8,12.6 102.3,13.2 102.7,13.6 103.1,13.3 103.5,13.1 104.0,12.3 104.4,12.9 104.8,14.3 105.3,14.5 105.7,14.2 106.1,15.4 106.6,15.3 107.0,16.0 107.4,14.7 107.8,15.3 108.3,14.3 108.7,13.2 109.1,14.4 109.6,14.2 110.0,14.9", "ret_12_1": 154.0, "ret_6_1": 66.3, "ret_3_1": -14.0, "volatility": 59.8, "traded_daily_cr": 71.0, "watch": "Nothing flagged", "from_12m_high": -31.4, "signal_rank": 11, "data_quality": "Green"}, {"rank": 5, "symbol": "RRKABEL", "isin": "INE777K01022", "qty": 6, "last_close": 2459.8, "amount": 14759.0, "spark_12m": "2.0,31.3 2.4,31.1 2.9,30.7 3.3,31.2 3.7,31.2 4.2,32.0 4.6,31.8 5.0,31.2 5.4,31.1 5.9,31.4 6.3,31.1 6.7,31.1 7.2,31.3 7.6,31.4 8.0,31.0 8.5,31.2 8.9,31.3 9.3,31.3 9.7,31.0 10.2,31.2 10.6,31.4 11.0,31.2 11.5,31.4 11.9,31.5 12.3,30.1 12.8,28.7 13.2,28.4 13.6,28.6 14.0,28.6 14.5,29.0 14.9,28.4 15.3,28.8 15.8,29.2 16.2,29.8 16.6,29.6 17.1,28.8 17.5,29.3 17.9,29.3 18.4,29.1 18.8,29.7 19.2,29.5 19.6,29.4 20.1,29.7 20.5,29.7 20.9,29.5 21.4,29.0 21.8,29.1 22.2,28.8 22.7,28.8 23.1,28.8 23.5,29.0 23.9,28.9 24.4,29.4 24.8,29.5 25.2,29.1 25.7,28.6 26.1,28.7 26.5,28.4 27.0,27.8 27.4,28.1 27.8,28.3 28.2,28.3 28.7,27.3 29.1,26.5 29.5,26.6 30.0,27.1 30.4,27.5 30.8,28.1 31.3,28.2 31.7,27.9 32.1,27.6 32.5,26.9 33.0,26.4 33.4,26.3 33.8,26.4 34.3,26.7 34.7,26.9 35.1,27.3 35.6,27.0 36.0,27.1 36.4,27.5 36.9,28.0 37.3,28.6 37.7,28.6 38.1,28.4 38.6,29.7 39.0,30.0 39.4,29.7 39.9,30.3 40.3,29.3 40.7,29.6 41.2,28.4 41.6,27.8 42.0,27.5 42.4,27.7 42.9,27.6 43.3,28.5 43.7,28.2 44.2,28.3 44.6,28.7 45.0,28.7 45.5,28.4 45.9,28.5 46.3,28.4 46.7,28.1 47.2,27.9 47.6,27.0 48.0,26.9 48.5,26.7 48.9,26.0 49.3,26.5 49.8,27.3 50.2,27.1 50.6,26.6 51.1,27.2 51.5,27.8 51.9,28.4 52.3,28.2 52.8,29.8 53.2,29.3 53.6,28.9 54.1,28.1 54.5,28.9 54.9,29.0 55.4,30.3 55.8,29.7 56.2,29.7 56.6,30.3 57.1,30.7 57.5,30.0 57.9,30.0 58.4,30.0 58.8,30.2 59.2,28.8 59.7,29.1 60.1,28.9 60.5,29.3 60.9,29.0 61.4,27.8 61.8,27.5 62.2,27.6 62.7,27.8 63.1,27.7 63.5,28.3 64.0,28.1 64.4,26.9 64.8,25.1 65.3,24.8 65.7,25.8 66.1,22.2 66.5,22.1 67.0,21.8 67.4,19.6 67.8,19.3 68.3,19.7 68.7,19.4 69.1,19.0 69.6,17.6 70.0,19.1 70.4,19.2 70.8,19.7 71.3,18.9 71.7,19.2 72.1,19.2 72.6,18.5 73.0,18.7 73.4,19.1 73.9,17.3 74.3,17.8 74.7,17.9 75.1,15.6 75.6,14.4 76.0,14.4 76.4,15.6 76.9,15.2 77.3,15.3 77.7,16.0 78.2,15.3 78.6,15.0 79.0,14.8 79.5,14.6 79.9,13.1 80.3,12.7 80.7,12.1 81.2,11.8 81.6,10.6 82.0,9.7 82.5,9.5 82.9,11.4 83.3,11.6 83.8,11.4 84.2,12.3 84.6,13.1 85.0,14.9 85.5,15.0 85.9,14.7 86.3,14.3 86.8,11.7 87.2,12.2 87.6,13.2 88.1,11.2 88.5,13.1 88.9,12.4 89.3,12.2 89.8,10.7 90.2,11.7 90.6,9.6 91.1,9.1 91.5,8.2 91.9,8.5 92.4,8.4 92.8,7.7 93.2,7.2 93.6,7.0 94.1,4.4 94.5,4.9 94.9,5.0 95.4,5.0 95.8,4.0 96.2,4.4 96.7,3.7 97.1,4.5 97.5,5.2 98.0,4.5 98.4,2.5 98.8,2.6 99.2,2.2 99.7,3.0 100.1,4.2 100.5,4.1 101.0,3.7 101.4,2.4 101.8,2.0 102.3,3.0 102.7,7.2 103.1,7.5 103.5,10.3 104.0,11.5 104.4,10.4 104.8,10.9 105.3,10.6 105.7,10.8 106.1,11.6 106.6,11.3 107.0,11.4 107.4,10.4 107.8,11.1 108.3,10.0 108.7,9.9 109.1,9.0 109.6,9.0 110.0,10.2", "ret_12_1": 126.0, "ret_6_1": 110.0, "ret_3_1": 18.2, "volatility": 44.0, "traded_daily_cr": 93.0, "watch": "Nothing flagged", "from_12m_high": -16.0, "signal_rank": 15, "data_quality": "Green"}, {"rank": 6, "symbol": "ACUTAAS", "isin": "INE00FF01025", "qty": 4, "last_close": 3214.4, "amount": 12858.0, "spark_12m": "2.0,30.2 2.4,30.2 2.9,30.3 3.3,30.3 3.7,30.8 4.2,31.5 4.6,31.6 5.0,32.0 5.4,31.2 5.9,31.1 6.3,30.9 6.7,30.9 7.2,30.9 7.6,30.7 8.0,30.1 8.5,29.7 8.9,29.7 9.3,29.1 9.7,29.0 10.2,27.8 10.6,26.4 11.0,26.1 11.5,26.7 11.9,27.4 12.3,26.8 12.8,27.0 13.2,27.3 13.6,27.1 14.0,26.8 14.5,25.8 14.9,25.5 15.3,26.3 15.8,26.4 16.2,26.4 16.6,26.5 17.1,27.1 17.5,27.4 17.9,27.0 18.4,27.1 18.8,27.0 19.2,26.9 19.6,26.8 20.1,27.2 20.5,25.0 20.9,26.1 21.4,26.0 21.8,26.1 22.2,25.4 22.7,26.2 23.1,26.6 23.5,26.7 23.9,27.1 24.4,27.1 24.8,27.8 25.2,27.6 25.7,27.4 26.1,27.7 26.5,27.6 27.0,28.1 27.4,27.2 27.8,27.7 28.2,28.0 28.7,27.8 29.1,27.4 29.5,27.2 30.0,27.8 30.4,27.8 30.8,27.8 31.3,27.7 31.7,27.1 32.1,26.5 32.5,26.6 33.0,26.3 33.4,26.4 33.8,26.4 34.3,26.7 34.7,27.4 35.1,27.5 35.6,27.4 36.0,27.1 36.4,27.2 36.9,27.4 37.3,28.1 37.7,28.4 38.1,27.9 38.6,27.8 39.0,26.8 39.4,25.1 39.9,24.2 40.3,24.5 40.7,24.2 41.2,23.8 41.6,23.5 42.0,23.6 42.4,23.6 42.9,23.4 43.3,22.8 43.7,23.0 44.2,22.2 44.6,23.2 45.0,22.9 45.5,22.4 45.9,21.6 46.3,22.1 46.7,22.0 47.2,21.5 47.6,21.5 48.0,21.3 48.5,21.1 48.9,21.4 49.3,21.0 49.8,22.1 50.2,20.4 50.6,20.2 51.1,21.4 51.5,20.5 51.9,21.0 52.3,21.0 52.8,22.3 53.2,21.3 53.6,19.6 54.1,20.1 54.5,20.3 54.9,18.3 55.4,20.0 55.8,17.9 56.2,16.7 56.6,16.5 57.1,16.3 57.5,19.2 57.9,22.0 58.4,20.7 58.8,20.7 59.2,19.2 59.7,19.3 60.1,18.8 60.5,18.4 60.9,19.7 61.4,19.1 61.8,18.8 62.2,18.2 62.7,18.7 63.1,18.0 63.5,18.5 64.0,18.4 64.4,17.1 64.8,17.5 65.3,17.0 65.7,15.9 66.1,14.9 66.5,15.1 67.0,14.7 67.4,14.2 67.8,14.1 68.3,13.2 68.7,14.0 69.1,12.9 69.6,14.2 70.0,14.2 70.4,13.3 70.8,12.2 71.3,12.3 71.7,10.8 72.1,11.4 72.6,11.7 73.0,10.3 73.4,10.8 73.9,9.1 74.3,10.5 74.7,10.3 75.1,9.1 75.6,8.7 76.0,6.6 76.4,6.8 76.9,8.3 77.3,8.2 77.7,9.2 78.2,8.9 78.6,9.5 79.0,10.8 79.5,10.8 79.9,9.0 80.3,7.7 80.7,7.6 81.2,7.3 81.6,7.4 82.0,7.0 82.5,3.6 82.9,4.1 83.3,3.6 83.8,2.0 84.2,2.0 84.6,4.3 85.0,5.8 85.5,5.0 85.9,5.0 86.3,5.7 86.8,4.5 87.2,5.0 87.6,3.9 88.1,3.4 88.5,3.0 88.9,2.5 89.3,2.2 89.8,2.4 90.2,5.0 90.6,7.5 91.1,6.1 91.5,7.0 91.9,6.9 92.4,7.8 92.8,9.4 93.2,9.3 93.6,7.9 94.1,7.2 94.5,7.5 94.9,7.0 95.4,7.2 95.8,7.7 96.2,8.8 96.7,9.4 97.1,7.8 97.5,8.3 98.0,5.8 98.4,7.9 98.8,8.1 99.2,8.6 99.7,8.6 100.1,6.8 100.5,7.5 101.0,6.6 101.4,7.2 101.8,8.7 102.3,8.6 102.7,9.1 103.1,8.2 103.5,8.6 104.0,8.5 104.4,8.5 104.8,7.7 105.3,5.1 105.7,5.9 106.1,7.4 106.6,6.4 107.0,6.8 107.4,5.2 107.8,5.4 108.3,8.1 108.7,7.4 109.1,7.2 109.6,7.3 110.0,8.1", "ret_12_1": 126.0, "ret_6_1": 36.7, "ret_3_1": -5.6, "volatility": 46.7, "traded_daily_cr": 101.0, "watch": "Nothing flagged", "from_12m_high": -13.0, "signal_rank": 16, "data_quality": "Green"}, {"rank": 7, "symbol": "DIACABS", "isin": "INE989C01038", "qty": 44, "last_close": 339.25, "amount": 14927.0, "spark_12m": "2.0,27.2 2.4,27.3 2.9,27.2 3.3,27.4 3.7,28.0 4.2,28.4 4.6,28.2 5.0,28.6 5.4,28.5 5.9,28.3 6.3,28.7 6.7,29.2 7.2,29.3 7.6,29.4 8.0,29.4 8.5,29.6 8.9,29.5 9.3,29.2 9.7,29.3 10.2,29.4 10.6,29.2 11.0,29.1 11.5,29.1 11.9,29.3 12.3,28.1 12.8,28.5 13.2,28.1 13.6,28.2 14.0,28.2 14.5,28.1 14.9,27.9 15.3,28.6 15.8,28.3 16.2,28.8 16.6,28.9 17.1,28.8 17.5,28.4 17.9,28.4 18.4,28.4 18.8,28.7 19.2,28.3 19.6,28.7 20.1,29.1 20.5,29.5 20.9,29.6 21.4,29.4 21.8,29.4 22.2,28.5 22.7,28.6 23.1,28.9 23.5,29.2 23.9,29.3 24.4,29.1 24.8,29.4 25.2,29.4 25.7,29.7 26.1,29.7 26.5,29.5 27.0,29.4 27.4,29.6 27.8,29.6 28.2,29.5 28.7,29.5 29.1,29.2 29.5,29.3 30.0,29.5 30.4,29.6 30.8,29.8 31.3,29.8 31.7,29.8 32.1,29.8 32.5,29.9 33.0,29.3 33.4,29.3 33.8,29.1 34.3,29.7 34.7,30.2 35.1,30.1 35.6,30.5 36.0,30.7 36.4,30.6 36.9,30.4 37.3,31.0 37.7,30.9 38.1,30.8 38.6,31.4 39.0,31.4 39.4,31.1 39.9,31.4 40.3,31.5 40.7,31.7 41.2,31.2 41.6,30.8 42.0,31.3 42.4,31.3 42.9,30.9 43.3,30.4 43.7,30.2 44.2,30.3 44.6,30.5 45.0,29.5 45.5,29.8 45.9,29.8 46.3,30.2 46.7,30.1 47.2,30.2 47.6,30.4 48.0,30.0 48.5,29.6 48.9,29.9 49.3,29.9 49.8,30.4 50.2,29.9 50.6,30.1 51.1,30.2 51.5,29.7 51.9,29.9 52.3,30.0 52.8,30.8 53.2,31.0 53.6,31.2 54.1,30.7 54.5,31.4 54.9,31.0 55.4,32.0 55.8,31.7 56.2,30.9 56.6,31.5 57.1,31.9 57.5,31.2 57.9,31.2 58.4,30.8 58.8,30.9 59.2,30.3 59.7,30.4 60.1,29.9 60.5,29.8 60.9,29.5 61.4,28.7 61.8,28.6 62.2,27.4 62.7,27.2 63.1,27.5 63.5,27.5 64.0,27.3 64.4,26.8 64.8,27.1 65.3,27.3 65.7,27.7 66.1,26.8 66.5,26.6 67.0,25.6 67.4,26.4 67.8,26.0 68.3,25.8 68.7,26.4 69.1,25.9 69.6,24.0 70.0,23.5 70.4,24.0 70.8,24.2 71.3,23.6 71.7,23.8 72.1,23.8 72.6,23.5 73.0,22.4 73.4,23.3 73.9,23.7 74.3,25.0 74.7,23.7 75.1,24.3 75.6,23.9 76.0,22.7 76.4,23.3 76.9,22.8 77.3,23.4 77.7,23.8 78.2,22.9 78.6,21.4 79.0,22.4 79.5,22.6 79.9,22.9 80.3,22.1 80.7,22.3 81.2,22.9 81.6,22.6 82.0,22.4 82.5,22.2 82.9,22.1 83.3,22.2 83.8,22.0 84.2,23.2 84.6,21.1 85.0,20.4 85.5,19.7 85.9,18.9 86.3,20.0 86.8,20.1 87.2,20.4 87.6,20.2 88.1,20.4 88.5,20.7 88.9,18.3 89.3,15.6 89.8,15.6 90.2,15.1 90.6,12.8 91.1,11.5 91.5,10.0 91.9,8.2 92.4,9.2 92.8,9.7 93.2,9.8 93.6,10.5 94.1,8.8 94.5,7.0 94.9,5.3 95.4,5.7 95.8,5.5 96.2,4.9 96.7,5.0 97.1,4.8 97.5,5.8 98.0,4.9 98.4,5.8 98.8,6.4 99.2,6.2 99.7,6.5 100.1,8.0 100.5,8.1 101.0,8.1 101.4,6.9 101.8,7.1 102.3,7.9 102.7,8.9 103.1,9.8 103.5,8.8 104.0,8.7 104.4,8.3 104.8,8.5 105.3,6.7 105.7,4.8 106.1,2.8 106.6,2.0 107.0,4.0 107.4,5.0 107.8,4.0 108.3,4.6 108.7,3.8 109.1,5.7 109.6,6.4 110.0,8.0", "ret_12_1": 124.0, "ret_6_1": 180.0, "ret_3_1": 61.7, "volatility": 53.6, "traded_daily_cr": 51.0, "watch": "Nothing flagged", "from_12m_high": -14.1, "signal_rank": 17, "data_quality": "Green"}, {"rank": 8, "symbol": "KIRLOSENG", "isin": "INE146L01010", "qty": 7, "last_close": 2141.2, "amount": 14988.0, "spark_12m": "2.0,30.3 2.4,30.3 2.9,30.5 3.3,30.2 3.7,30.7 4.2,31.2 4.6,31.1 5.0,31.1 5.4,31.0 5.9,31.4 6.3,31.6 6.7,31.8 7.2,31.8 7.6,31.8 8.0,31.6 8.5,31.7 8.9,32.0 9.3,31.9 9.7,31.8 10.2,31.6 10.6,31.8 11.0,31.6 11.5,31.5 11.9,31.5 12.3,30.7 12.8,29.6 13.2,29.4 13.6,29.4 14.0,29.7 14.5,29.4 14.9,29.4 15.3,29.9 15.8,30.3 16.2,30.5 16.6,30.7 17.1,28.7 17.5,28.2 17.9,28.1 18.4,27.7 18.8,27.2 19.2,26.6 19.6,26.5 20.1,26.8 20.5,27.4 20.9,26.9 21.4,27.1 21.8,27.2 22.2,27.5 22.7,27.6 23.1,27.7 23.5,28.2 23.9,26.8 24.4,27.4 24.8,28.0 25.2,27.5 25.7,27.7 26.1,27.6 26.5,27.1 27.0,27.3 27.4,25.7 27.8,24.7 28.2,24.6 28.7,25.4 29.1,24.2 29.5,24.4 30.0,25.0 30.4,24.9 30.8,25.8 31.3,25.7 31.7,25.8 32.1,25.6 32.5,25.1 33.0,25.2 33.4,25.3 33.8,25.8 34.3,26.5 34.7,26.9 35.1,27.5 35.6,27.0 36.0,26.7 36.4,26.7 36.9,27.4 37.3,27.9 37.7,27.9 38.1,27.7 38.6,28.0 39.0,28.0 39.4,27.7 39.9,27.6 40.3,26.6 40.7,27.0 41.2,26.5 41.6,25.6 42.0,26.2 42.4,26.7 42.9,25.8 43.3,25.0 43.7,23.9 44.2,23.7 44.6,23.0 45.0,22.4 45.5,22.1 45.9,22.3 46.3,22.2 46.7,22.3 47.2,22.6 47.6,22.7 48.0,22.5 48.5,22.7 48.9,22.7 49.3,22.5 49.8,22.3 50.2,21.4 50.6,20.6 51.1,21.6 51.5,21.9 51.9,21.7 52.3,21.4 52.8,21.7 53.2,21.4 53.6,21.9 54.1,22.0 54.5,22.2 54.9,23.0 55.4,24.6 55.8,23.9 56.2,22.7 56.6,23.5 57.1,23.9 57.5,23.2 57.9,22.9 58.4,22.3 58.8,22.6 59.2,21.4 59.7,21.6 60.1,21.3 60.5,21.1 60.9,19.1 61.4,18.8 61.8,18.7 62.2,18.4 62.7,17.9 63.1,18.4 63.5,18.9 64.0,19.2 64.4,17.6 64.8,16.9 65.3,17.3 65.7,17.3 66.1,16.9 66.5,16.6 67.0,17.1 67.4,16.8 67.8,16.8 68.3,18.0 68.7,19.8 69.1,19.1 69.6,19.1 70.0,16.6 70.4,17.3 70.8,18.0 71.3,17.9 71.7,17.7 72.1,17.8 72.6,17.2 73.0,16.4 73.4,15.0 73.9,13.3 74.3,13.4 74.7,14.5 75.1,13.9 75.6,12.9 76.0,13.5 76.4,14.6 76.9,14.6 77.3,15.2 77.7,15.6 78.2,13.9 78.6,13.2 79.0,13.4 79.5,12.2 79.9,12.3 80.3,12.1 80.7,5.1 81.2,3.0 81.6,2.0 82.0,3.4 82.5,4.2 82.9,5.5 83.3,5.9 83.8,6.3 84.2,7.9 84.6,7.3 85.0,7.2 85.5,7.1 85.9,4.5 86.3,3.3 86.8,4.3 87.2,5.6 87.6,4.6 88.1,5.0 88.5,7.5 88.9,8.1 89.3,8.1 89.8,8.7 90.2,8.8 90.6,8.7 91.1,7.0 91.5,8.6 91.9,8.8 92.4,9.6 92.8,8.6 93.2,8.0 93.6,7.1 94.1,7.7 94.5,7.6 94.9,9.1 95.4,9.7 95.8,10.2 96.2,11.0 96.7,10.9 97.1,10.2 97.5,10.2 98.0,9.8 98.4,10.6 98.8,9.3 99.2,10.2 99.7,10.8 100.1,11.5 100.5,11.3 101.0,10.2 101.4,9.8 101.8,10.2 102.3,9.5 102.7,9.1 103.1,7.2 103.5,8.4 104.0,8.9 104.4,7.1 104.8,8.1 105.3,8.3 105.7,9.0 106.1,11.2 106.6,11.3 107.0,9.8 107.4,9.1 107.8,9.6 108.3,9.1 108.7,8.1 109.1,9.1 109.6,9.6 110.0,9.5", "ret_12_1": 123.0, "ret_6_1": 58.2, "ret_3_1": -11.2, "volatility": 49.9, "traded_daily_cr": 87.0, "watch": "Nothing flagged", "from_12m_high": -16.5, "signal_rank": 18, "data_quality": "Green"}, {"rank": 9, "symbol": "E2E", "isin": "INE255Z01027", "qty": 23, "last_close": 625.9, "amount": 14396.0, "spark_12m": "2.0,25.4 2.4,24.4 2.9,23.5 3.3,24.3 3.7,23.7 4.2,22.9 4.6,23.7 5.0,24.4 5.4,23.4 5.9,22.4 6.3,21.3 6.7,21.1 7.2,21.2 7.6,22.8 8.0,23.1 8.5,23.8 8.9,24.4 9.3,24.4 9.7,24.3 10.2,24.1 10.6,24.5 11.0,24.4 11.5,24.3 11.9,25.2 12.3,24.5 12.8,24.9 13.2,25.1 13.6,24.9 14.0,25.0 14.5,25.3 14.9,24.9 15.3,25.3 15.8,25.1 16.2,25.3 16.6,26.1 17.1,26.1 17.5,26.8 17.9,27.8 18.4,28.0 18.8,28.1 19.2,28.0 19.6,28.1 20.1,28.8 20.5,29.7 20.9,29.7 21.4,29.6 21.8,29.8 22.2,30.1 22.7,30.0 23.1,30.5 23.5,30.9 23.9,30.5 24.4,31.0 24.8,31.6 25.2,30.8 25.7,31.2 26.1,31.1 26.5,31.1 27.0,31.1 27.4,31.5 27.8,31.6 28.2,31.7 28.7,31.3 29.1,31.2 29.5,31.1 30.0,31.2 30.4,31.4 30.8,32.0 31.3,31.9 31.7,31.8 32.1,31.7 32.5,31.6 33.0,31.2 33.4,31.5 33.8,31.6 34.3,31.5 34.7,31.5 35.1,31.6 35.6,31.8 36.0,31.6 36.4,30.3 36.9,30.2 37.3,30.8 37.7,31.3 38.1,31.2 38.6,31.5 39.0,31.5 39.4,31.3 39.9,31.5 40.3,31.0 40.7,29.0 41.2,28.0 41.6,29.0 42.0,29.5 42.4,28.7 42.9,27.8 43.3,28.2 43.7,27.9 44.2,28.4 44.6,28.8 45.0,28.2 45.5,28.3 45.9,26.5 46.3,25.8 46.7,26.4 47.2,28.2 47.6,29.0 48.0,28.3 48.5,28.0 48.9,28.2 49.3,28.9 49.8,29.7 50.2,29.7 50.6,29.8 51.1,29.9 51.5,29.1 51.9,29.4 52.3,29.6 52.8,29.9 53.2,30.4 53.6,30.5 54.1,30.1 54.5,30.0 54.9,30.1 55.4,30.7 55.8,30.7 56.2,30.2 56.6,30.9 57.1,31.4 57.5,30.8 57.9,30.2 58.4,29.9 58.8,29.6 59.2,28.9 59.7,29.1 60.1,29.0 60.5,28.9 60.9,28.1 61.4,27.4 61.8,26.8 62.2,27.4 62.7,26.6 63.1,26.0 63.5,26.2 64.0,26.2 64.4,25.3 64.8,25.7 65.3,26.0 65.7,26.3 66.1,26.6 66.5,25.8 67.0,24.9 67.4,23.9 67.8,23.0 68.3,21.9 68.7,23.0 69.1,24.1 69.6,24.0 70.0,24.9 70.4,25.5 70.8,24.5 71.3,23.6 71.7,23.1 72.1,22.1 72.6,21.3 73.0,20.2 73.4,19.8 73.9,20.0 74.3,18.8 74.7,17.5 75.1,18.8 75.6,17.6 76.0,16.3 76.4,17.6 76.9,19.0 77.3,20.2 77.7,21.4 78.2,20.3 78.6,21.1 79.0,20.6 79.5,20.3 79.9,19.1 80.3,17.9 80.7,16.6 81.2,17.5 81.6,18.4 82.0,18.7 82.5,19.8 82.9,19.7 83.3,19.3 83.8,20.2 84.2,20.6 84.6,20.6 85.0,21.3 85.5,20.8 85.9,19.6 86.3,19.6 86.8,20.3 87.2,19.8 87.6,18.8 88.1,18.1 88.5,19.2 88.9,18.0 89.3,16.7 89.8,15.3 90.2,13.9 90.6,12.4 91.1,10.8 91.5,12.4 91.9,13.9 92.4,13.8 92.8,12.3 93.2,10.8 93.6,9.1 94.1,7.4 94.5,6.9 94.9,8.8 95.4,7.1 95.8,5.6 96.2,5.3 96.7,5.1 97.1,3.2 97.5,2.0 98.0,3.3 98.4,5.4 98.8,5.8 99.2,5.9 99.7,6.5 100.1,7.5 100.5,6.5 101.0,6.2 101.4,6.3 101.8,6.1 102.3,6.0 102.7,6.8 103.1,7.7 103.5,7.2 104.0,5.4 104.4,6.2 104.8,7.0 105.3,6.9 105.7,6.6 106.1,8.5 106.6,7.3 107.0,7.0 107.4,6.8 107.8,7.7 108.3,7.0 108.7,5.1 109.1,4.4 109.6,4.1 110.0,5.7", "ret_12_1": 109.0, "ret_6_1": 186.0, "ret_3_1": 56.0, "volatility": 56.2, "traded_daily_cr": 49.0, "watch": "Nothing flagged", "from_12m_high": -8.8, "signal_rank": 20, "data_quality": "Green"}, {"rank": 10, "symbol": "LAURUSLABS", "isin": "INE947Q01028", "qty": 7, "last_close": 2010.7, "amount": 14075.0, "spark_12m": "2.0,29.5 2.4,30.2 2.9,30.1 3.3,30.1 3.7,30.4 4.2,32.0 4.6,31.8 5.0,31.8 5.4,31.0 5.9,31.2 6.3,31.2 6.7,31.2 7.2,31.5 7.6,31.2 8.0,30.9 8.5,31.0 8.9,30.9 9.3,30.9 9.7,31.0 10.2,30.3 10.6,29.8 11.0,29.7 11.5,29.5 11.9,29.7 12.3,29.3 12.8,28.8 13.2,28.8 13.6,28.6 14.0,29.0 14.5,28.4 14.9,28.2 15.3,28.3 15.8,28.3 16.2,27.8 16.6,28.2 17.1,28.1 17.5,27.9 17.9,27.8 18.4,27.3 18.8,27.6 19.2,28.1 19.6,28.1 20.1,28.4 20.5,28.3 20.9,28.4 21.4,28.1 21.8,27.7 22.2,27.0 22.7,27.1 23.1,27.3 23.5,27.4 23.9,27.5 24.4,27.2 24.8,27.7 25.2,27.3 25.7,27.4 26.1,27.3 26.5,27.5 27.0,27.7 27.4,27.8 27.8,27.6 28.2,27.4 28.7,26.7 29.1,26.2 29.5,26.1 30.0,25.7 30.4,25.7 30.8,25.8 31.3,25.5 31.7,25.1 32.1,25.1 32.5,25.2 33.0,25.2 33.4,24.9 33.8,24.6 34.3,25.3 34.7,25.7 35.1,26.7 35.6,26.4 36.0,25.6 36.4,25.9 36.9,26.2 37.3,26.9 37.7,28.1 38.1,27.7 38.6,27.4 39.0,27.8 39.4,27.8 39.9,28.5 40.3,28.7 40.7,29.0 41.2,28.4 41.6,28.3 42.0,28.7 42.4,29.0 42.9,28.2 43.3,28.7 43.7,27.5 44.2,27.3 44.6,27.5 45.0,27.5 45.5,27.5 45.9,26.9 46.3,27.3 46.7,27.3 47.2,27.4 47.6,27.1 48.0,25.9 48.5,25.5 48.9,25.9 49.3,26.2 49.8,27.0 50.2,26.7 50.6,27.2 51.1,27.3 51.5,26.9 51.9,26.8 52.3,26.6 52.8,27.7 53.2,28.8 53.6,28.6 54.1,28.2 54.5,29.2 54.9,28.1 55.4,28.8 55.8,28.0 56.2,27.2 56.6,27.6 57.1,28.0 57.5,26.8 57.9,26.7 58.4,26.4 58.8,26.4 59.2,25.8 59.7,25.7 60.1,25.4 60.5,25.6 60.9,24.9 61.4,24.6 61.8,24.4 62.2,24.6 62.7,25.0 63.1,25.4 63.5,24.6 64.0,25.0 64.4,24.7 64.8,25.6 65.3,25.2 65.7,25.3 66.1,23.7 66.5,23.7 67.0,23.4 67.4,22.7 67.8,22.1 68.3,21.2 68.7,21.1 69.1,20.8 69.6,19.9 70.0,19.7 70.4,19.6 70.8,19.2 71.3,18.8 71.7,19.1 72.1,19.2 72.6,18.9 73.0,18.5 73.4,18.3 73.9,18.8 74.3,18.1 74.7,18.3 75.1,18.0 75.6,17.1 76.0,16.7 76.4,17.7 76.9,17.2 77.3,18.2 77.7,18.1 78.2,18.0 78.6,18.1 79.0,18.4 79.5,18.6 79.9,18.6 80.3,17.5 80.7,16.9 81.2,15.8 81.6,16.5 82.0,16.6 82.5,15.3 82.9,14.9 83.3,15.5 83.8,14.6 84.2,14.3 84.6,14.6 85.0,15.9 85.5,16.1 85.9,15.1 86.3,14.4 86.8,13.9 87.2,13.8 87.6,14.0 88.1,13.9 88.5,14.6 88.9,13.9 89.3,13.0 89.8,13.4 90.2,13.6 90.6,12.8 91.1,10.0 91.5,8.9 91.9,8.3 92.4,8.3 92.8,7.4 93.2,7.6 93.6,6.6 94.1,7.0 94.5,7.1 94.9,6.7 95.4,6.5 95.8,6.4 96.2,6.6 96.7,6.6 97.1,8.2 97.5,7.6 98.0,7.5 98.4,7.8 98.8,7.2 99.2,7.8 99.7,7.8 100.1,6.2 100.5,5.7 101.0,4.6 101.4,4.4 101.8,5.0 102.3,6.3 102.7,6.2 103.1,6.1 103.5,6.8 104.0,5.9 104.4,4.2 104.8,4.4 105.3,4.2 105.7,3.6 106.1,4.7 106.6,5.2 107.0,4.1 107.4,4.0 107.8,2.4 108.3,2.7 108.7,2.0 109.1,2.2 109.6,2.7 110.0,2.6", "ret_12_1": 109.0, "ret_6_1": 94.4, "ret_3_1": 27.2, "volatility": 28.1, "traded_daily_cr": 300.0, "watch": "Nothing flagged", "from_12m_high": -1.1, "signal_rank": 21, "data_quality": "Green"}]}, "prices": {"TDPOWERSYS": {"2026-09-28": {"open": 730.05, "close": 722.0, "src": "yahoo"}, "2026-09-29": {"open": 719.0, "close": 777.35, "src": "bhavcopy"}, "2026-09-30": {"open": 783.0, "close": 786.05, "src": "bhavcopy"}, "2026-10-01": {"open": 779.9, "close": 792.15, "src": "bhavcopy"}, "2026-10-05": {"open": 801.0, "close": 812.9, "src": "bhavcopy"}, "2026-10-02": {"open": 792.15, "close": 792.15, "src": "yahoo"}, "2026-10-06": {"open": 810.0, "close": 816.0, "src": "bhavcopy"}, "2026-10-07": {"open": 818.0, "close": 821.1, "src": "bhavcopy"}, "2026-10-08": {"open": 835.0, "close": 793.5, "src": "bhavcopy"}, "2026-10-09": {"open": 795.0, "close": 793.75, "src": "bhavcopy"}, "2026-10-12": {"open": 800.0, "close": 825.65, "src": "bhavcopy"}, "2026-10-13": {"open": 830.0, "close": 797.85, "src": "bhavcopy"}, "2026-10-
A2: 14": {"open": 796.0, "close": 783.7, "src": "bhavcopy"}, "2026-10-15": {"open": 769.7, "close": 734.75, "src": "bhavcopy"}, "2026-10-16": {"open": 737.8, "close": 735.15, "src": "bhavcopy"}, "2026-10-19": {"open": 735.15, "close": 737.0, "src": "bhavcopy"}, "2026-10-21": {"open": 737.0, "close": 689.35, "src": "bhavcopy"}, "2026-10-22": {"open": 688.0, "close": 673.4, "src": "bhavcopy"}, "2026-10-23": {"open": 659.9, "close": 639.55, "src": "bhavcopy"}}, "AEROFLEX": {"2026-09-28": {"open": 524.25, "close": 513.4, "src": "yahoo"}, "2026-09-29": {"open": 511.3, "close": 539.6, "src": "bhavcopy"}, "2026-09-30": {"open": 539.6, "close": 536.6, "src": "bhavcopy"}, "2026-10-01": {"open": 540.0, "close": 521.35, "src": "bhavcopy"}, "2026-10-05": {"open": 524.0, "close": 544.35, "src": "bhavcopy"}, "2026-10-02": {"open": 521.35, "close": 521.35, "src": "yahoo"}, "2026-10-06": {"open": 549.7, "close": 560.75, "src": "bhavcopy"}, "2026-10-07": {"open": 566.4, "close": 563.85, "src": "bhavcopy"}, "2026-10-08": {"open": 572.05, "close": 529.0, "src": "bhavcopy"}, "2026-10-09": {"open": 535.0, "close": 520.5, "src": "bhavcopy"}, "2026-10-12": {"open": 530.0, "close": 567.9, "src": "bhavcopy"}, "2026-10-13": {"open": 571.0, "close": 557.6, "src": "bhavcopy"}, "2026-10-14": {"open": 559.0, "close": 568.7, "src": "bhavcopy"}, "2026-10-15": {"open": 560.1, "close": 510.95, "src": "bhavcopy"}, "2026-10-16": {"open": 516.4, "close": 525.8, "src": "bhavcopy"}, "2026-10-19": {"open": 526.05, "close": 505.2, "src": "bhavcopy"}, "2026-10-21": {"open": 509.95, "close": 488.95, "src": "bhavcopy"}, "2026-10-22": {"open": 487.0, "close": 479.45, "src": "bhavcopy"}, "2026-10-23": {"open": 470.0, "close": 451.3, "src": "bhavcopy"}}, "E2E": {"2026-09-28": {"open": 650.0, "close": 625.9, "src": "yahoo"}, "2026-09-29": {"open": 619.55, "close": 651.8, "src": "bhavcopy"}, "2026-09-30": {"open": 655.05, "close": 650.5, "src": "bhavcopy"}, "2026-10-01": {"open": 647.0, "close": 648.0, "src": "bhavcopy"}, "2026-10-05": {"open": 659.9, "close": 656.1, "src": "bhavcopy"}, "2026-10-06": {"open": 665.0, "close": 688.9, "src": "bhavcopy"}, "2026-10-07": {"open": 678.9, "close": 723.3, "src": "bhavcopy"}, "2026-10-08": {"open": 744.0, "close": 714.15, "src": "bhavcopy"}, "2026-10-09": {"open": 705.0, "close": 704.6, "src": "bhavcopy"}, "2026-10-12": {"open": 700.0, "close": 735.55, "src": "bhavcopy"}, "2026-10-13": {"open": 735.0, "close": 735.75, "src": "bhavcopy"}, "2026-10-14": {"open": 732.0, "close": 748.3, "src": "bhavcopy"}, "2026-10-15": {"open": 710.9, "close": 710.9, "src": "bhavcopy"}, "2026-10-16": {"open": 699.95, "close": 694.85, "src": "bhavcopy"}, "2026-10-19": {"open": 668.0, "close": 660.15, "src": "bhavcopy"}, "2026-10-21": {"open": 627.15, "close": 627.15, "src": "bhavcopy"}, "2026-10-22": {"open": 595.8, "close": 595.8, "src": "bhavcopy"}, "2026-10-23": {"open": 566.05, "close": 566.05, "src": "bhavcopy"}}, "LAURUSLABS": {"2026-09-28": {"open": 2000.0, "close": 2010.7, "src": "yahoo"}, "2026-09-29": {"open": 2020.7, "close": 1979.0, "src": "bhavcopy"}, "2026-09-30": {"open": 1993.0, "close": 1980.0, "src": "bhavcopy"}, "2026-10-01": {"open": 1973.6, "close": 1984.0, "src": "bhavcopy"}, "2026-10-05": {"open": 1994.0, "close": 1971.4, "src": "bhavcopy"}, "2026-10-02": {"open": 1984.0, "close": 1984.0, "src": "yahoo"}, "2026-10-06": {"open": 1968.9, "close": 2050.0, "src": "bhavcopy"}, "2026-10-07": {"open": 2052.0, "close": 2052.8, "src": "bhavcopy"}, "2026-10-08": {"open": 2055.0, "close": 1997.9, "src": "bhavcopy"}, "2026-10-09": {"open": 1997.9, "close": 2036.6, "src": "bhavcopy"}, "2026-10-12": {"open": 2044.1, "close": 2069.2, "src": "bhavcopy"}, "2026-10-13": {"open": 2047.1, "close": 2059.4, "src": "bhavcopy"}, "2026-10-14": {"open": 2049.0, "close": 2036.9, "src": "bhavcopy"}, "2026-10-15": {"open": 2025.0, "close": 2018.5, "src": "bhavcopy"}, "2026-10-16": {"open": 2030.4, "close": 2060.1, "src": "bhavcopy"}, "2026-10-19": {"open": 2060.1, "close": 2069.0, "src": "bhavcopy"}, "2026-10-21": {"open": 2052.9, "close": 2012.5, "src": "bhavcopy"}, "2026-10-22": {"open": 1993.5, "close": 2002.5, "src": "bhavcopy"}, "2026-10-23": {"open": 1987.5, "close": 1970.0, "src": "bhavcopy"}}, "NIFTY50": {"2026-09-28": {"open": 23064.9, "close": 22780.25, "src": "yahoo"}, "2026-09-29": {"open": 22732.45, "close": 22716.2, "src": "bhavcopy"}, "2026-09-30": {"open": 22665.0, "close": 22620.45, "src": "bhavcopy"}, "2026-10-01": {"open": 22543.7, "close": 22421.95, "src": "bhavcopy"}, "2026-10-05": {"open": 22532.4, "close": 22555.75, "src": "bhavcopy"}, "2026-10-06": {"open": 22603.25, "close": 22776.1, "src": "bhavcopy"}, "2026-10-07": {"open": 22690.45, "close": 22603.05, "src": "bhavcopy"}, "2026-10-08": {"open": 22599.05, "close": 22231.8, "src": "bhavcopy"}, "2026-10-09": {"open": 22314.95, "close": 22520.45, "src": "bhavcopy"}, "2026-10-12": {"open": 22593.2, "close": 22363.35, "src": "yahoo"}, "2026-10-13": {"open": 22364.15, "close": 22721.95, "src": "bhavcopy"}, "2026-10-14": {"open": 22715.75, "close": 22622.7, "src": "yahoo"}, "2026-10-15": {"open": 22671.3, "close": 22997.35, "src": "bhavcopy"}, "2026-10-16": {"open": 23065.1, "close": 23146.15, "src": "bhavcopy"}, "2026-10-19": {"open": 23150.85, "close": 22888.95, "src": "bhavcopy"}, "2026-10-21": {"open": 23016.0, "close": 22811.35, "src": "bhavcopy"}, "2026-10-22": {"open": 22687.75, "close": 22687.65, "src": "bhavcopy"}, "2026-10-23": {"open": 22742.2, "close": 22600.0, "src": "bhavcopy"}}, "ATHERENERG": {"2026-09-28": {"open": 1495.0, "close": 1454.9, "src": "yahoo"}, "2026-09-29": {"open": 1460.2, "close": 1407.0, "src": "bhavcopy"}, "2026-09-30": {"open": 1416.5, "close": 1425.0, "src": "bhavcopy"}, "2026-10-01": {"open": 1422.0, "close": 1406.1, "src": "bhavcopy"}, "2026-10-05": {"open": 1411.1, "close": 1409.9, "src": "bhavcopy"}, "2026-10-02": {"open": 1406.1, "close": 1406.1, "src": "yahoo"}, "2026-10-06": {"open": 1408.7, "close": 1446.0, "src": "bhavcopy"}, "2026-10-07": {"open": 1436.0, "close": 1455.0, "src": "bhavcopy"}, "2026-10-08": {"open": 1454.5, "close": 1406.0, "src": "bhavcopy"}, "2026-10-09": {"open": 1406.0, "close": 1434.4, "src": "bhavcopy"}, "2026-10-12": {"open": 1435.0, "close": 1511.0, "src": "bhavcopy"}, "2026-10-13": {"open": 1480.0, "close": 1494.9, "src": "bhavcopy"}, "2026-10-14": {"open": 1491.0, "close": 1467.0, "src": "bhavcopy"}, "2026-10-15": {"open": 1470.7, "close": 1470.0, "src": "bhavcopy"}, "2026-10-16": {"open": 1474.4, "close": 1470.0, "src": "bhavcopy"}, "2026-10-19": {"open": 1470.0, "close": 1459.0, "src": "bhavcopy"}, "2026-10-21": {"open": 1467.2, "close": 1447.2, "src": "bhavcopy"}, "2026-10-22": {"open": 1438.0, "close": 1425.3, "src": "bhavcopy"}, "2026-10-23": {"open": 1431.0, "close": 1380.0, "src": "bhavcopy"}}, "THANGAMAYL": {"2026-09-28": {"open": 5100.0, "close": 5011.5, "src": "yahoo"}, "2026-09-29": {"open": 5010.0, "close": 5204.5, "src": "bhavcopy"}, "2026-09-30": {"open": 5210.5, "close": 5062.0, "src": "bhavcopy"}, "2026-10-01": {"open": 5087.5, "close": 4861.0, "src": "bhavcopy"}, "2026-10-05": {"open": 4870.0, "close": 4747.0, "src": "bhavcopy"}, "2026-10-06": {"open": 4794.0, "close": 4758.5, "src": "bhavcopy"}, "2026-10-07": {"open": 4758.5, "close": 4803.0, "src": "bhavcopy"}, "2026-10-08": {"open": 4840.0, "close": 4810.5, "src": "bhavcopy"}, "2026-10-09": {"open": 4800.5, "close": 4889.5, "src": "bhavcopy"}, "2026-10-12": {"open": 4949.5, "close": 4890.5, "src": "bhavcopy"}, "2026-10-13": {"open": 4860.0, "close": 4900.5, "src": "bhavcopy"}, "2026-10-14": {"open": 4940.0, "close": 4849.5, "src": "bhavcopy"}, "2026-10-15": {"open": 4849.5, "close": 4791.0, "src": "bhavcopy"}, "2026-10-16": {"open": 4775.0, "close": 5098.0, "src": "bhavcopy"}, "2026-10-19": {"open": 5122.5, "close": 5017.5, "src": "bhavcopy"}, "2026-10-21": {"open": 5017.5, "close": 4860.5, "src": "bhavcopy"}, "2026-10-22": {"open": 4844.0, "close": 4782.5, "src": "bhavcopy"}, "2026-10-23": {"open": 4755.0, "close": 4690.5, "src": "bhavcopy"}}, "RRKABEL": {"2026-09-28": {"open": 2530.4, "close": 2459.8, "src": "yahoo"}, "2026-09-29": {"open": 2459.8, "close": 2523.2, "src": "bhavcopy"}, "2026-09-30": {"open": 2530.0, "close": 2518.6, "src": "bhavcopy"}, "2026-10-01": {"open": 2524.0, "close": 2518.2, "src": "bhavcopy"}, "2026-10-05": {"open": 2541.5, "close": 2648.0, "src": "bhavcopy"}, "2026-10-06": {"open": 2667.0, "close": 2789.7, "src": "bhavcopy"}, "2026-10-02": {"open": 2518.2, "close": 2518.2, "src": "yahoo"}, "2026-10-07": {"open": 2785.0, "close": 2722.5, "src": "bhavcopy"}, "2026-10-08": {"open": 2701.0, "close": 2696.4, "src": "bhavcopy"}, "2026-10-09": {"open": 2700.0, "close": 2705.6, "src": "bhavcopy"}, "2026-10-12": {"open": 2731.8, "close": 2721.5, "src": "bhavcopy"}, "2026-10-13": {"open": 2720.0, "close": 2614.2, "src": "bhavcopy"}, "2026-10-14": {"open": 2634.0, "close": 2664.1, "src": "bhavcopy"}, "2026-10-15": {"open": 2640.0, "close": 2603.9, "src": "bhavcopy"}, "2026-10-16": {"open": 2607.0, "close": 2388.0, "src": "bhavcopy"}, "2026-10-19": {"open": 2377.5, "close": 2387.8, "src": "bhavcopy"}, "2026-10-21": {"open": 2356.0, "close": 2327.8, "src": "bhavcopy"}, "2026-10-22": {"open": 2302.0, "close": 2263.1, "src": "bhavcopy"}, "2026-10-23": {"open": 2260.0, "close": 2140.0, "src": "bhavcopy"}}, "ACUTAAS": {"2026-09-28": {"open": 3272.5, "close": 3214.4, "src": "yahoo"}, "2026-09-29": {"open": 3290.0, "close": 3304.1, "src": "bhavcopy"}, "2026-09-30": {"open": 3334.1, "close": 3279.4, "src": "bhavcopy"}, "2026-10-01": {"open": 3249.0, "close": 3196.5, "src": "bhavcopy"}, "2026-10-05": {"open": 3204.1, "close": 3122.2, "src": "bhavcopy"}, "2026-10-02": {"open": 3196.5, "close": 3196.5, "src": "yahoo"}, "2026-10-06": {"open": 3140.0, "close": 3156.7, "src": "bhavcopy"}, "2026-10-07": {"open": 3160.0, "close": 3174.2, "src": "bhavcopy"}, "2026-10-08": {"open": 3174.6, "close": 3056.7, "src": "bhavcopy"}, "2026-10-09": {"open": 3059.0, "close": 3160.6, "src": "bhavcopy"}, "2026-10-12": {"open": 3160.0, "close": 3144.1, "src": "bhavcopy"}, "2026-10-13": {"open": 3160.0, "close": 3176.7, "src": "bhavcopy"}, "2026-10-14": {"open": 3176.9, "close": 3160.5, "src": "bhavcopy"}, "2026-10-15": {"open": 3179.0, "close": 3132.5, "src": "bhavcopy"}, "2026-10-16": {"open": 3132.5, "close": 3206.0, "src": "bhavcopy"}, "2026-10-19": {"open": 3275.0, "close": 3253.4, "src": "bhavcopy"}, "2026-10-21": {"open": 3262.9, "close": 3152.4, "src": "bhavcopy"}, "2026-10-22": {"open": 3152.1, "close": 3215.3, "src": "bhavcopy"}, "2026-10-23": {"open": 3219.4, "close": 3137.7, "src": "bhavcopy"}}, "DIACABS": {"2026-09-28": {"open": 353.0, "close": 339.25, "src": "yahoo"}, "2026-09-29": {"open": 336.9, "close": 352.05, "src": "bhavcopy"}, "2026-09-30": {"open": 349.5, "close": 354.2, "src": "bhavcopy"}, "2026-10-01": {"open": 355.0, "close": 345.0, "src": "bhavcopy"}, "2026-10-05": {"open": 350.0, "close": 350.8, "src": "bhavcopy"}, "2026-10-06": {"open": 350.0, "close": 368.3, "src": "bhavcopy"}, "2026-10-02": {"open": 345.0, "close": 345.0, "src": "yahoo"}, "2026-10-07": {"open": 367.0, "close": 369.15, "src": "bhavcopy"}, "2026-10-08": {"open": 374.9, "close": 371.9, "src": "bhavcopy"}, "2026-10-09": {"open": 370.0, "close": 380.95, "src": "bhavcopy"}, "2026-10-12": {"open": 380.95, "close": 379.7, "src": "bhavcopy"}, "2026-10-13": {"open": 376.7, "close": 377.55, "src": "bhavcopy"}, "2026-10-14": {"open": 377.55, "close": 378.75, "src": "bhavcopy"}, "2026-10-15": {"open": 377.75, "close": 373.75, "src": "bhavcopy"}, "2026-10-16": {"open": 367.3, "close": 362.4, "src": "bhavcopy"}, "2026-10-19": {"open": 359.0, "close": 345.85, "src": "bhavcopy"}, "2026-10-21": {"open": 345.85, "close": 337.85, "src": "bhavcopy"}, "2026-10-22": {"open": 337.0, "close": 326.65, "src": "bhavcopy"}, "2026-10-23": {"open": 320.0, "close": 315.05, "src": "bhavcopy"}}, "KIRLOSENG": {"2026-09-28": {"open": 2138.1, "close": 2141.2, "src": "yahoo"}, "2026-09-29": {"open": 2141.2, "close": 2402.0, "src": "bhavcopy"}, "2026-09-30": {"open": 2358.0, "close": 2304.2, "src": "bhavcopy"}, "2026-10-01": {"open": 2310.7, "close": 2242.7, "src": "bhavcopy"}, "2026-10-05": {"open": 2265.0, "close": 2243.7, "src": "bhavcopy"}, "2026-10-06": {"open": 2258.8, "close": 2266.1, "src": "bhavcopy"}, "2026-10-02": {"open": 2242.7, "close": 2242.7, "src": "yahoo"}, "2026-10-07": {"open": 2270.0, "close": 2230.8, "src": "bhavcopy"}, "2026-10-08": {"open": 2230.0, "close": 2163.0, "src": "bhavcopy"}, "2026-10-09": {"open": 2171.4, "close": 2210.4, "src": "bhavcopy"}, "2026-10-12": {"open": 2235.0, "close": 2193.0, "src": "bhavcopy"}, "2026-10-13": {"open": 2195.0, "close": 2180.8, "src": "bhavcopy"}, "2026-10-14": {"open": 2214.5, "close": 2148.3, "src": "bhavcopy"}, "2026-10-15": {"open": 2158.0, "close": 2066.3, "src": "bhavcopy"}, "2026-10-16": {"open": 2075.0, "close": 2025.6, "src": "bhavcopy"}, "2026-10-19": {"open": 2019.0, "close": 1973.2, "src": "bhavcopy"}, "2026-10-21": {"open": 1970.0, "close": 1908.7, "src": "bhavcopy"}, "2026-10-22": {"open": 1908.7, "close": 1869.0, "src": "bhavcopy"}, "2026-10-23": {"open": 1859.4, "close": 1784.7, "src": "bhavcopy"}}}, "entry_override": {}, "news": {"fetched": "2026-10-23 17:22", "days": 7, "items": [{"symbol": "MARKET", "title": "Sensex, Nifty Extend Losing Streak to Fourth Session as Crude Surges above $114", "link": "https://news.google.com/rss/articles/CBMiqAFBVV95cUxOYzMybHpFSFdNMElLU0ZZZDd6cFlGbk5INDhsaUFRYkZta2gyYnNLYVRRV18zcTBHSXlyczRYd2VEcjliQXZoN3Y1Yk9GVkFGbDJwV1VZU1VHRFFaS0t3aUdvd3NZZElDMkdaV2xJcGhMQ1Y2anRvTW0zbG0ya0E1RWd3UlJBUHFKY19yYWoxR25sdDR0NjFhaTUxUm8zaGNZMzZya2VaZ24?oc=5", "source": "The Indian Awaaz", "published": "2026-10-23 16:48", "score": 0.077, "label": "Neutral"}, {"symbol": "MARKET", "title": "Sensex, Nifty Fall for Fourth Consecutive Session as Geopolitical Tensions Rattle Indian Markets", "link": "https://news.google.com/rss/articles/CBMiwgFBVV95cUxPQnIwOFFjZ0FXd3hPQzNZZjRGalJkb1BNUmF6QkszZG9KeC1pN2N6VTBmeW0wOWtPYW94STFRZEtGbk4xbHpwNjYtNnREaGtlcjg3blBQQmNPcGdQX1ZmMWRuR0VGZ0puRVNfanc0R3J4UFA3aFlxcUFOc3ZjRnNuaW9fZWU0MnY3NmdYdWdxcjF5eVpZN2pROUdKRHFCaGRkbkswVVU4SFFRN2sxaEF0NVNzeHZuQmpXZGxDUjFUMkl6UQ?oc=5", "source": "INDIA New England News", "published": "2026-10-23 15:07", "score": -0.34, "label": "Negative"}, {"symbol": "AEROFLEX", "title": "Aeroflex Enterprises NSE:AEROENTER Stilonn Acquisition", "link": "https://news.google.com/rss/articles/CBMiwgFBVV95cUxNVVVFQzlqUVNaMm8xRml0Mnc4NHlkQjFrbFVwZ1FtanZPa21CSldPNi1IRUUyc18zQ1FIQUJ5M3prMEVab0hlLXBXSmtFU3EyZ1ZKbzZyNms4S1JnS0Z2cV9hNEp3X0ZCWDZXaVg1RFY4U0xRVWljQ1hpYTJpSTFFTFdpdnlLM1RzcUlyMFpJYlpHYzg5VG5QTW9raUVGTlFiQmttcGo0REJUQ3pKbURVYmlSSDluRTczQk81dnFUMWlXZw?oc=5", "source": "Kalkine India", "published": "2026-10-23 14:26", "score": 0.0, "label": "Neutral"}, {"symbol": "MARKET", "title": "Stock Market Weekly Wrap: Rs 16 lakh crore mcap wiped out as Sensex sheds 1,605 points \u2014 what lies ahead?", "link": "https://news.google.com/rss/articles/CBMi4AFBVV95cUxNQjZyWl9nQ19wVmduaW02NS1MVFBCM1dyeExicTVkRVRTYVAwejlXTERkQkRYRm1HWW50YjJkVWxmR0NlNmo4V0NpbXo2eVFmcEJjWVgtM2tiQXZDQUo3NG9oRlBsbG8tcHZIU2ZLMnhTQ05ocGNqc0RWcmtsVVpjRFBOcnUwNGZMQUwzWXdRUUtNSThobWdLakdCclhjcDRIQ1p1ei03bzRFZGx4ZmRybVhtTHZha0F4c0xJWnZKcm9oRVpQQWlCdER2QzkydlRzczR5ZWVpbGRkb2xzQ2dnMA?oc=5", "source": "Zee Business", "published": "2026-10-23 13:04", "score": -0.66, "label": "Negative"}, {"symbol": "MARKET", "title": "Indian Renewable Energy Stocks Decline as Inox Wind Falls 5.45% on October 23", "link": "https://news.google.com/rss/articles/CBMiswFBVV95cUxNUUEyRkU5Tmk2WllPUDNDVGp6b3dkVTI4SGVfd3B0ZS1lMXF1OEVNNG1jckgtVE9yUTg5VTFVM2xCQmFjeXRkd0pSY2lOSW9NR3psZzJGeXNjbkpYdFFHUGZ0VjU0VGhHMUp4dW85d1MyMHJrSzlHOXhRbUltWXQ3NVB0czhweHBLdWEyRFZMcDg3Qm5XN0RVOWd5M2lVZnJRS1ZEcFBPN0hDQTdUczdzcWdSZw?oc=5", "source": "SolarQuarter", "published": "2026-10-23 12:56", "score": -0.477, "label": "Negative"}, {"symbol": "MARKET", "title": "Market wrap: Eternal, Apollo Hospital, Shriram Finance, Adani Enterprises among top gainers and losers on", "link": "https://news.google.com/rss/articles/CBMiqgJBVV95cUxPMFNuVzhBMFJfY3VMdW5SSFhEcndpR3Z2M2lGd1A0ckgtNWhIcThFa3VrNV8xSnpic3B5bEVLaG5vZExHcnFickJ3Y05sV1czbXFvWUdxeFRXandBdWZkS0s0N1V6aXo3UXIxbURBZXZ0T3MzMmxOYm1UTkxrVWFSZmVxRkZIMndwdmVmcl96enNkdXZHNVNhS0JraXFqM3JlRjBWOS1XOGh5R0M4X1dSTmVjQTJVOEFIY0hueFRDU1ZveHQzTHcwS2JwaVB5YUZQRTZ6bUFha1p1TzZ2MG45Q1RZYXNyeGtZM0owRWNYNEhWZE1ELUI3VVN6Rll2UHQzLWFwelNVNUhsSkVkblN1T0VyVlZManpBam04NlRrbHZGRkc3VmpuMXVR0gGvAkFVX3lxTE9VUkk4NHNwdHA0V1hSMWdtWkJfdEhvLWt6YUdRRTJDTzd5Ym9wRFdJX0hnbWxURzNTVWlnckNqWnhmMWxVUnFRa2lpNG5Td3J6dEJDQlFDUktJNkJQNGozSmM1SzZiVnl6eUotczhYYU1zYW55MU5RMWRJU2sxdjNqUTZqcFFMSE0yS20wX1RDeHVFSGNQNFZ2LXlYX2dvRTh0Tl9Pb3lDbmp0M2FhR1hleWZJWENBbVZ1Mk9CN1JhdGhpZU5LM002MG85M0RocVg5Y0JMa2RyNEN4UGdKNFlfc0tSdWx4Zk5rNGhaTTRBVEp1c3dacnU1dEY0T2V4WFJ2ZWFFUjZzTFdlQnNDMU9DZE42N0RlVURjcUlrczZPemI0V19meVc5WTNoMDVrQQ?oc=5", "source": "The Economic Times", "published": "2026-10-23 12:00", "score": -0.382, "label": "Negative"}, {"symbol": "MARKET", "title": "Sensex Fall Today: Sensex Drops 1,279 Points, Nifty Near 22,400", "link": "https://news.google.com/rss/articles/CBMifEFVX3lxTE5Gd3lWUVc4RURIc3hYYkFVeVNDa3BOcHMydVBxX3Z1TUJEUmRrYk9zMDEzX1Y2RDJHN2NCQ0JPSGd2MmVBWDRSRzR1ZU5BRzN5UVA3R204elgtTGRNLTlTWlhXQ2dSLVNVMmFXR2NKQ2hzYXh3akVmSWZuRDA?oc=5", "source": "Business Outreach Magazine", "published": "2026-10-23 11:34", "score": 0.077, "label": "Neutral"}, {"symbol": "MARKET", "title": "Share Market Today: Nifty 50, Bank Nifty | Oct 23, 2026", "link": "https://news.google.com/rss/articles/CBMi4AFBVV95cUxOdC1raFlJNDlHakZlX3RsbnlzalQ2Sy1qQmJYVXpISmVRUjJWTXIxcVVCLU52enFtdWM5bVdQenczZ2FuVVZTbGNFYW1FVk9OMFVwTFY5QV9zNjVYbWFkVlhrMGJwQXJBMUp2TVBwMXVmQ0NCUmdrMjZ5LURaYnZhYnJxdXVWV2NpOWdoVmVmdlp6YmI1ekhCOGI5TVhheDJfNzgybmpyTWhscS14Q1YzeUpvcU1zVUlfMF92VWIxN0pOMlZTYlZHNlFrcGlHbENDOTExLVJjUjlTY2lHbDZpTA?oc=5", "source": "Liquide Blog", "published": "2026-10-23 11:22", "score": 0.66, "label": "Positive"}, {"symbol": "MARKET", "title": "Indian Equities Fall for Fourth Day as West Asia Tensions Drive Oil Prices Higher", "link": "https://news.google.com/rss/articles/CBMi4wFBVV95cUxQaXBZQnNaMjB2VC1wWDJkeG1PZHlVSjRhVkM3bTNpSmhxZWhmOWcyV0VTTVgyWUpaQ1p5c1ZObU51QmllYkM5TkZsVDlRWlItMS01c3hHblVTZ2VzeUJTNjBVdzZVTUZKbUNFLUZjSDA3eE42ZEFZdTJuQUlfYVFVcE94VjZ3WklqdnZ4VUZCSmNtZ0hfSU0tVzk3aDlaaHJIRUt0Ulg4SEs0ejFXR3lCSmZwZ2lOWUEwVndUb3Y3TjItOTFXanoyZUdLcEZjeGU3M1NoX1RfS0liNFFRVEU1Z0dYa9IB5gFBVV95cUxQWllvblBMU0tiYzRlZ3F6ekNTeGZhYXVvd29XRDl0QVRmaEltMm1PZ3FOYXg2bUI2VzRxWnlwN0VpdVdjYi05T1Z0REZjVGM2cTdLT2ZGODZQZzA5MURmOU9YSGF2ZUZoX3hVZ2FoYWNvdnB5cFBNWjRjdDRXUENsa0hUdVdvd2JqVFBTQmdXQmREaWttNlk4TlZvY19BYkdBbS0wQnpXWGttdlh2dHIzS1lmWWQtaTVVQ0xpeGplelFaZE9QYWdCek80UFBvM0tZSnd1QlJjb251cXVJSGpTQmluOFVsZw?oc=5", "source": "Rediff", "published": "2026-10-23 11:20", "score": -0.625, "label": "Negative"}, {"symbol": "MARKET", "title": "Markets extend losses for 4th day amid selling pressure, oil price surge", "link": "https://news.google.com/rss/articles/CBMiqwFBVV95cUxORmEzQjFiR2tJQmJBSXFpR2kyVFJMeEZWUnBZYVhhR2dlUEg1Y2xfRWZDekFuNVN3UWxiMmtQQ25xRUdVd2M0aUI2ZUx1MnYzajFGdlFrLXJlRk9jSFRNZ1Y2MnV5RXI2cm84X1NmUlFfdlFBWWlWcVVnRF9fbkk5WUk3R0JPZ2M4bnRQbmVndGVFYXVlRnNQQllWWGt3V3A2M1RCVTc5MjZ3aUk?oc=5", "source": "DT Next", "published": "2026-10-23 11:19", "score": -0.026, "label": "Neutral"}, {"symbol": "MARKET", "title": "Markets Fall for 4th Day as Crude Nears $114; Nifty Ends at 22,600", "link": "https://news.google.com/rss/articles/CBMirgFBVV95cUxOcW5MSjcwWkJSamFDMl9hNUpSdG9Bd0lwWkJyQ2RrVy1ReVJJNzlVa0Q4TklPRUdKNFBqV1pQSHgxbVo4aVhBSUlZa3I2VUJWMlRSQ2gxUXV5QjNISl83LXFlVklqc2dOdXJVV2M1YzlGV3JidjFYQkVfaU01djVpdS1pLThxZ2pNTlRua2VjT1l3MkF6U3VxcW96S1NmQ3JPa0pyYkEycTlzS1ZBZVE?oc=5", "source": "HDFC Sky", "published": "2026-10-23 10:54", "score": -0.527, "label": "Negative"}, {"symbol": "MARKET", "title": "Sensex Today Ends 126 Points lower | Nifty Below 22,650 | Tata Steel Drown 3%", "link": "https://news.google.com/rss/articles/CBMizAJBVV95cUxPbWlwSjh6U0oxZ2hNUG5ZblRyNGlDZzQ4RWpPcTQzWUdTVGVyc0FxNW9Vdm9CV09WSUdMejBwdGpPbUlvMjZBcVc5SndQVEV2TVFjcnU3NmdCdUpzUjl2Rk1lRVZvMUdlS1B0RUFMbEptbE8wQjZQZmpNeHdEVzRrR2prMDlmc1F6UXJka1JQRDZZZHRrMDJ0V2dwM2JxT0FwQmVnNDFIT0FxaGJOZG1ZOEJKV0hhX0paQVNad2oyX0VCLW5EV0JqX21XNmVlMl9fUnBMLWZBSGxMWlV2Mll2QmxPY1RJUlJjc09NSEdOQ2pYc2tNWFVKaTN4d1NxZHF3dWxiY2d4U18zbkYtZ3VjQkt0aFR4aWlnSms1VTlxZjJicXFlNHhYWFRMc2Zab0g5SHpjTHo5bXQ5YUVwbTFuaEthVkhvT3N5N1kwUg?oc=5", "source": "Equitymaster", "published": "2026-10-23 10:46", "score": -0.421, "label": "Negative"}, {"symbol": "MARKET", "title": "Taking Stock: Markets recover from day's lows, but sell-off extends to 4th day; Nifty at 22,600", "link": "https://news.google.com/rss/articles/CBMi7gFBVV95cUxNYW5sZ3RaSVR2VDdOejhPbVFQLWpkaWQxWG94Qk9MNVhoelNIWjJtSm8xazh2NUtTSHhPX0hkNlZXcU1nRVRqdDF6T1J2cFpOd3JjTm15TEdUSkNCb0ZGNUR0eHBLN2JsaURxN3FPdDVreG1sdUtzUjlGRTVXeUo5V202Rlo2SkJKT2U2Mnhkc2JHak83TG5YenNKVnNFdnJHc1hpRmZ2TUsxSjBpOGVIc0ZGMnhWYWw5ZmZ3R0pxRXIweUZmcjF2VE9HdlhzRU9iWV9LRTlwWFJsZ1FWMFFlTGpzUWs5TUY0eU80OVdR0gHzAUFVX3lxTE5CaEdTMDBTbEFBa0tRaF9kbllVem9uUklwZXNqUGZGWFBaQTdKcndrSk1UR0Raak5NV091MlFFYkdoNjhibkNocERJMWctSzg4M0xrdFp6U1lEb0RuM2FfN0hDckh0bzg5aEVZXzdvR1dnNFBBb2ZleXMyOGxVODl0NGdfUV9na1M0WTF5ZEY2S3BlUWtVcEJkVUF6S0ZNYlVLUGxhUUJVOExELXIxRHg0d1FpaTZDNUJMZFZKcllhSEVLR1Rsb3ZLemVlZzlQMWI1Rl9Da25ZY0l6R2xBSmdGcUZfTUtoYjdGN3dPa2lYTm5Zcw?oc=5", "source": "Moneycontrol.com", "published": "2026-10-23 10:39", "score": 0.599, "label": "Positive"}, {"symbol": "MARKET", "title": "Sensex, Nifty extend losses as crude surges to USD 114, all sectors close in red", "link": "https://news.google.com/rss/articles/CBMiyAFBVV95cUxQc1JaVTd3SURLaTBsd1BBOE5VLXdMV2dzMEtzcy1TLXlpN0Fzclg3Y21KTVdxejFRcVZvQUlUOHB1em1Oa2k4VEN1VDJ1VGZ2STZfRVNGUmwwWUxzQkJRdGRyZnROOW5Ob0NleDk5R0tVVXJPSE1COU9IaEJjS3JLZU5IWXV2X25TMG1QRjZBREhraGI0dTIwSU5yUVdIRFNWLUJiTXdFdGpxWWREaHBlMUpSRzdpaHY3QXZWNWFSWkpHYzZvNXNGQw?oc=5", "source": "ANI News", "published": "2026-10-23 10:30", "score": 0.026, "label": "Neutral"}, {"symbol": "MARKET", "title": "Closing Bell: Sensex, Nifty Fall for 4th Session as Brent Crude Nears $114; Smallcap Stocks Tumble", "link": "https://news.google.com/rss/articles/CBMi2wFBVV95cUxNZWRLUVZCZWZCTzhPRmRIOFZmWGFWajR1ZmRSOXc5VlpydTdOQTM1S0dvRWV5Q0tsdUh0RkJmWmxldFRkejNPbllGdi1jUEw2ZE8wdzExbHNJa2FSbHoxRl9vSDV2VmtlVWZXTEZ3QThVT3VnNzhycWRVdEFzYVB3NlRZcklUMGhCWnNZMnVwX285RFpacnlCeDE2b1E5Q3UyRHFhZkRIYWFhRWR0cTc1a1lYUE1tRXdCM2txQXRVWEIyVEdEeEcwTXY5c1NJR09KLXdSZjQ5anR4Wk0?oc=5", "source": "Dalal Street Investment Journal", "published": "2026-10-23 10:30", "score": -0.527, "label": "Negative"}, {"symbol": "MARKET", "title": "Market Today: Sensex Falls 126 Points, Nifty Ends Below 22,650; Smallcap Stocks Crash Nearly 3%", "link": "https://news.google.com/rss/articles/CBMi3AFBVV95cUxQVjBkcXFZQng1RGg4cTRCVzZ3cDNpdlNpZmNwY3hBT2lRcEdQTDhzZzNSMzVnU21BYTJYek1INGMzTzFwZV82dzZsbEpwWThNbHZYbU1ZdHJQT19qVWVndEdrZjJDVFZkM1VWOThtalpEUWFvYUljdWRNbXZ5UW10TWNhRDZCTXo1UndTRkxtODdGeDdCTFNRZ0JxV200VWRQWnRiQ0NaaUVsUlZIWkkwazZKS1huemJGTGZXNVNVTzdBRzNyQWRQTl9nNUFGRWVsaVMxZ0ZTeUVEeU5H0gHiAUFVX3lxTFBram12dlViVDhYS1U4a0ZxaDQ0empDUGR2R2EyYWtiQ25rbEtkNHJBMXNlNEYzZlZGRnZfa3VoOTVQcUxLUl9uRmF6QlVScndHeUNEMGlBbGhQYzRXYXR4ZGEwczE1c3l6cTNXbXFzenE2WElVZFhKa2wya282V19SUFY0eDRCSE5fUHZKWXJwcTV4dWo2S0FKT280akp0YW41bTR4MjdPMzlTUmVHaHNPUFhmMVh5VkVjUWZPdk13S256eDE0bXNQclRvSHNLektuZUtmUDVuQXl5dXhJLXAxdnc?oc=5", "source": "News18", "published": "2026-10-23 10:22", "score": -0.572, "label": "Negative"}, {"symbol": "MARKET", "title": "Sensex, Nifty end lower as Midcaps tumble; Swiggy suffers biggest single-day fall", "link": "https://news.google.com/rss/articles/CBMiwgFBVV95cUxNWU9YZDFKQmpIeVlVTndmSHZISmdIOTZ1X3c2elpYaWlIWTNQTE1OVUxZaWhLR0dISllmeW93dVFzdzk2STFFNFdtaF91VU9qdFlaSUJMTjdNaldFRkVUQlczTFZXWmtQU3VjaDBrTmM0TGxTS3BtazFOSXBUWXUzeWp6RENIRmpzeGY4RGJ5YzFSZEx4SUppVm41U3p1SmVMVzItSDA3OWRSX3V6VTRTSjNPamYyNVlBaW1IWERpSWlrd9IBxwFBVV95cUxPdDhWcVBjWDkxenRBTjVZSVVqX25ncUxqdl9jZzRpRWo4VzBNN1lvX0JRb1laWHRQRUxsVkpLZWludldnMGNJN3VYSlFOQVI5ck5tVjB1dFk2cmpNWkZtcVlvT05SY3FFSzJnOHA0YWp5VnhyU2lORHYzN0ZwTWtMcHFOOXkxYXNrXzM1M3B4cGxwRnQyOW00TTZ6Y29NMmNmV2ZJOG9Td1RZWEM2OXFydFQ1SVpSQUYxcEtLc0VrWnE3c0JwSVAw?oc=5", "source": "CNBC TV18", "published": "2026-10-23 10:12", "score": -0.557, "label": "Negative"}, {"symbol": "MARKET", "title": "Closing Bell: Sensex falls 126 points, Nifty below 22,600 as oil prices spike; Metal, Realty stocks lead losses", "link": "https://news.google.com/rss/articles/CBMi6AFBVV95cUxObWFadjlUem5OeW1WM0ZnWmF3NlpnSkQyd053NHNvanJ6VzFOZUNIdzhleVNJLTc1V3VWWnFrVWowMXlQd2U4YkxSSmRVVERjRFVTc1g2M1hGWGI0OE1tYW84S3VUWWlPdGsxWFFWa1dqUVB3dlFZUkl1ajlyYU9iY210YzBncHoyUENrY0F2ek8zSUtfYkZMd1Jra0RBUm5ybEtBdm1lZTFja3NiYVVsYndIMk9GNWR2eU9hVlB4R1pxUU5Oc0FqRzhZQ3hGa29MVVU4RXNQaF81TkFnempwTGxtWUJRekNF?oc=5", "source": "Zee Business", "published": "2026-10-23 10:05", "score": -0.402, "label": "Negative"}, {"symbol": "MARKET", "title": "Global Market: Eurozone bond markets stabilise after volatile week", "link": "https://news.google.com/rss/articles/CBMiV0FVX3lxTFBvU1A3YXdwdkdEeEhvQ1lLLVhhUk9sWUdXUFdDb1F4NjUxRDlnVDFkOUNjdFVjbTBBc09kNmNkRl9UbzkyOFVvbjIxYjFoMVQ3MUNJNGFmOA?oc=5", "source": "The Economic Times", "published": "2026-10-23 09:59", "score": 0.0, "label": "Neutral"}, {"symbol": "E2E", "title": "E2E Networks shares hit lower circuit for 4th straight session; Netweb, Black Box fall up to 9% amid...", "link": "https://news.google.com/rss/articles/CBMiiAJBVV95cUxQcFBFTjQtVDNpM255Z3czRXdHbno4UThYdVNRdnUzNlNOMnQyYmZ1eWRwSkhIb1FrT1Y0OTB5QlBsNTdaa2t2Q2Ribm12SDJ4ckEyYmZZamZQbEhFWktPeFQ3TmcwV2lrLTlSQmtRYjZsZU1nbjZqYkNRRHFpcVFtR1BIU0dZTUhoTjNDWHpMdmYwdmZPVC1POURWb1U0SXAyOTFtaFhkVFJpaHpfam01UFQ2X1VoYUF0RzV6MVQyNC1MUDdmQnFSV2M5SHBsb1ZZRldzWUdDT2tmV2szVkVJWWg1VjJWTDJ6cy1KdUs0WEVveGhqWE1YTTN0N1Y2RGFaUVhCVk0xcG3SAY4CQVVfeXFMTklrZEZlazREcHF4Zmw0X3dsSUFvWFFEektRZ1oxN082dWdWYmxyN21XVlNyLVd4UlVnTWs3dnQ5OERsQk45UG9JLVJ4NzQxQ3U0ZmVXSFR2M2FYOTM1STV5VzkyN1h0RzJPQ19GS3E0aExLTmFNSWZSMWg0S0NQQ1IxSENyUWQ0ejB3a05kbE1HdGlzRC1XZ0puS0ZyM1ZxMHAtT25zdTQyUXVUQ2tqUFhvNWVyVnNHbzNFMGkxVTRfN0VmWDVBbVZBWlRYcGtDQ3M2U0pVTFc4SUgtM3dCZEplUVZQdWlqVjRRNVlObVVoZmZxVFBsOG1vT3YzdktNbjEzazAxeEZMTnVZbzNR?oc=5", "source": "Moneycontrol.com", "published": "2026-10-23 09:50", "score": -0.44, "label": "Negative"}, {"symbol": "MARKET", "title": "Westlife Foodworld soars 20%; rebounds 24% from days' low post Q2 results", "link": "https://news.google.com/rss/articles/CBMi0gFBVV95cUxPWmx2T3pmclloM0dPOE1zRmlMU3d1STU5aTNVRVJ2Qy1INzRoU1drUW45eUE4dUpXNlZGRXllYUdhUEZxT0hFcmRneTBwU21KSHdDUHhOYl9tZWNqbFFBVDhZX1RfSzQwa1lfQ1NtZ0hINERWaGdIazBXV1FnX0hsLW9iUXkwUEYyaUM4OWl6X1l4MXpHOXZlRC1ReWJpRUNLQmM2Wmw2cEtkaWYzZWV4bG50Qkl6Q0FfLUNNSzRidk5hV1dpZk9UTFduSkVfVklMWXfSAdcBQVVfeXFMUDJxX2htblVLczJOY25aS3dpZGxqd193OE5EX042R2ZaX0M2bVg2VDdrYkZEbV90SWFzMDBmU2p4MlUzQWg3UjBqSjBIZHdXRGtUWDNVRll0V0JLYzJJRF9lMmhudUtmNlRkSnNxbF9LRXhxcUNCNnRNc01fRTZoOWxjQ1Z0cTNUanRKRlVNLWg5T0M4ZnRhLU1UOG1yYkxYODRTNmcxb242NzAzS1k5b1Z1SlFQaVAxUzdBVmk4cnVEbnpjd3RFdHVJY3hjSU1zTlJmX2l4RW8?oc=5", "source": "Business Standard", "published": "2026-10-23 09:30", "score": 0.318, "label": "Positive"}, {"symbol": "ATHERENERG", "title": "Ather Energy Share Price Today, Ather Energy Stock Price Live NSE/BSE Updates", "link": "https://news.google.com/rss/articles/CBMiigFBVV95cUxNMmpPVXcxeVFIRHF1aHV6dFRLVnhXV3djOWRQN2tuMmxVTnhDeVNJSnFoV2ZscmFoaEtaWXhCT0tabGNHdVhlOV8zcG45eTJrYS04ek9hSlNlMEZPYlpyeS1pbXNqbjlVVklKeEFrX1R6OUEzXzhRdjNneFZzbEFFMjc4MmZ4T3dSMnc?oc=5", "source": "The Economic Times", "published": "2026-10-23 09:00", "score": 0.494, "label": "Positive"}, {"symbol": "MARKET", "title": "Sensex Recovers 408 Points from Intraday Levels as IT Stocks Advance; Nifty 50 Trades at 22,500", "link": "https://news.google.com/rss/articles/CBMi2gFBVV95cUxPYm1hVGg0RlZqTG5DbXRHX2syNGJsc29fajJzQWh5N1lVb1dCOFVMOVlRczhQeV9MTFJCOG55S0MwMGw1RGk4dFBpNWQ0MDYtS2hxdnJWMTRkTHBldzgzUGNIQ3hvQXFaNTlKWnVGRWFNc3dJVml6Y05wNTZSVjRMREY2M1kyZUZITkM5Vi1hWkRRZ1V3aWFlU3lmUG5hRmJ4RG1KTUdMbkZoMUwxeEdOTG13eXNLQlFXb1VZUDJRdUxmcE91QmhSSmwtejlROXhBU3pJOWZDTzVZUQ?oc=5", "source": "Dalal Street Investment Journal", "published": "2026-10-23 08:53", "score": 0.402, "label": "Positive"}, {"symbol": "MARKET", "title": "D-Street bleeds! Market value of all BSE-listed firms falls below Rs 450 lakh crore for first time since A", "link": "https://news.google.com/rss/articles/CBMipgJBVV95cUxNZXh6eXI2Q3Z3dV92VDJ3NjBuZ3hvMUlrZzBnTlNaNUZyOWFTV25zbDBKdGEzMnJhMlNqQzBhZ3UyR2U5Tjc4ZXdCcFAyVjZTZ2hrTzB0UXFyRUtJQXU5QWVKTDA0bjU0dVU2VWo1UkMtZlRjM1Y1dnphNmMySWRBS1lhc0Z3OWl3OFdabDREaVV5TklGdFRaYnE2eGpCRjlxWENuS3hWbklCNG1pRWhlLTBzYk9Oai1XcDBMYkt4RkVLRF9uZGI2ODYwV1FyZzg2ZW91bFNPTWw3TGRFeTg4NTdva1pEWHczZzBHMUhPeE9nY0swdVNudzd6MmdZbjkwYThsY3hYQjhrQ0FFV0cyUUxaQVNtRXdFb0ZUZFNEUHhNSDAxV2fSAasCQVVfeXFMTjZLRFV5cWhFaldYazl1ZmItVTg3WmtJWFdQZzVmeV9kOXNncElIOTZWLUVTcVU2T2loVUxSRVF5d3BhcGNJaXJOcjdyN1lCQ3lnQlhuLWVsRU1vVGVoZzlGY1R6bDBVX1J4THRDM0JvNXdNVzd2VnBOYkVmR2o3cjFfVFdiWk5wbUxYTUhjSFhXQ0syNGdQWGx6eGxDZmI3dmc1OS1jb1VXQ2ZGeDJLR3kyZ3hHdllUYXFCQ1hWTWl5dWdkbkdtdFBoWWFncFBpSXVienJzaFhpUE5oY2dCVUV5RFMzTUp3Ynp4cnJYdWZxUXB5RXBKUkw4cEFhQ1otLXY2WkNkQ1R4OXZ1YmF5NlpTX0lLZFJYTXN4bEtIR3hJcW1Zc24yNWxkNjQ?oc=5", "source": "The Economic Times", "published": "2026-10-23 08:29", "score": -0.126, "label": "Neutral"}, {"symbol": "MARKET", "title": "Sensex and Nifty Slip Amid Broad Market Weakness; Utilities Sector Leads Declines", "link": "https://news.google.com/rss/articles/CBMi1gFBVV95cUxNSW9vYTRDMkNRLS04emdkd0E0WFBkbWJkNFpZbm1OV1F1ZFI5MGFPT3FkZzhlSGZucHFJOU5oTWtJcS1vZ2xHT1l0VmFuLTV1R19kc1pEVlFvRmRyNV91NTZUZ2pYSmhiOXVJNFprNDV3OUdTSkdVenRuXzZXWlJ5X1BoSTJlY0dsZnQ2Q3J1b3lGazA1R0tuRzYtV0hvX0VqZ0pGMDRJdi1icmFfdWNzSEZmZ0JiTVY1Nk5aUHN6NnRCOTJ6bUhrSmE1MXRQM08xVXViTHBn?oc=5", "source": "MarketsMojo", "published": "2026-10-23 08:17", "score": -0.625, "label": "Negative"}, {"symbol": "MARKET", "title"
A3: : "Steel Strips zooms 19%, hits record high on heavy volume post Q2 results", "link": "https://news.google.com/rss/articles/CBMi0wFBVV95cUxPel9aNDh6UXVaS2pWWUlzNlNWa0RERDZRWlpncG5pcDRqbk14ZzdfTDllSEVJVGhlVC1FcXVZbjNKMDBIbTRZVnpWb2dZbk9SUzEzaHlrZ1VTVDVMeFZEcW5xYmp3RWhJX0R0RGFwclQ4LUxwelRPazF3N3BTcElQdE9OZjMxWThIM0paNWFUWDIyNTVleFVqS0JNV0kzX05MMlFSdFg0a2VMM09uTG9uY3dab0c0c3I3aFJ3cWVjM1lmUXByRENVOTJiYjlrbDVZUF800gHYAUFVX3lxTE1rdk92bmZRSzdQcUlRdEdNSzNQeEFZbjJsdk5tbHpsM29xa1J3Z0EwbVJnbXU3dlVvV1lYbVp6NlN6dGo3NkJxRHFxa08ta2tmY29kNVB5M3J6SXcxZ3ZGV2l3eU1QUHM5cllNcW1NUTM5UHZOSDlQd2Z2ekZqNi1MTGZPcU1UOUVRYnF1eDItRXZKUzVTaDhrQTAwdVlzMlhhY1Z2d2pjeElNaWhtSll5a09lVENaZ1RFOWEwdkhfd1pOaTRGYU8wYllVZWRjX3hDMXdPQVhuaw?oc=5", "source": "Business Standard", "published": "2026-10-23 08:12", "score": 0.402, "label": "Positive"}, {"symbol": "MARKET", "title": "Stock Market Crash: Rs 24.8 lakh crore wiped off this week; Sensex sheds 1,000 pts from day's high, Nifty nears 24,400", "link": "https://news.google.com/rss/articles/CBMi4wFBVV95cUxPQ2MyTEhfRW1jclh3d1E0dmNmcUg5a0ZvbkRLVE5ROUM0RWVLeGxObWRiQXFsbFF1bVRCWDQ2WVFKbzkzWjZGZk1UdDV2UTBIRGhpLWUxWUFUZWlyNlprUnp5bDJLTU1BUWpLMHJzaDR0dHE5QTNKbVRXVy1KbE1IanNFTTI1bDFvckg2T2F2TUhRTFlraE1CSklVTlNtZlJ2b0RGTmQ3dExFSjJURkdJWXJ2WVNESmZNMU9kLXJESmpEMDdnWlZDa0huOHJ6VW4yREFGWmFFeU1qVkUtR3QyTzl3TQ?oc=5", "source": "Zee Business", "published": "2026-10-23 07:59", "score": -0.44, "label": "Negative"}, {"symbol": "MARKET", "title": "Market crash: Sensex sinks 1,279 pts from day's high; Nifty tests 22,400", "link": "https://news.google.com/rss/articles/CBMipgFBVV95cUxQN2pCLThGUk9vOU44QzRrMGloVTF1TzlUSkpROWxZOFgwdm1sRGVlWFR5WFM5a3NBd1hGMkFpUjkyQW01bFZLSEpBTFR5aGplR3hPRkFUbU0wM0NBaXpJLUJ3NTZDQjhJUnhpeVlJUGp4bjhNMU9jTlRVcEI5RzYxLWswaVhJN1JSV3VyZG1UUVlLVWoyYXVIM2tsYloxQWpmZ0o5OFdn?oc=5", "source": "India IPO", "published": "2026-10-23 07:23", "score": -0.511, "label": "Negative"}, {"symbol": "RRKABEL", "title": "Buy R R Kabel; target of Rs 2960: Motilal Oswal", "link": "https://news.google.com/rss/articles/CBMiswFBVV95cUxOTGQtcjc2NUVXTW5pUXpzOTlyQnVxSEotM0JoS1hzUm5mb1Y4UUI1NjljMllhVy1CeTVkdVZHdUZkbHFaWjk4ajc2WVdCQldabWxLQk03T2NTYW0yWmFxSzlMQTktZ0l4Z3lodVRuS0Rjc3RHM3FlWDlOU2FTVE9VZWZWR253bkFnVHZqdDlQMzk2c1U4UThlZWdBbUNXbEphMlVDa05yTVdhNTUxZ0RORGw0RdIBuAFBVV95cUxOaGlIdTF2eHp3dTRjdG9pTDBkdUYxTDd4bDBhYlF6a21QYUVBMmo4ZklLdk9JVEFDLU84TnF2a2FBVkE4QjVCd2tyRmhoWWJiV1JWUnZraWRtVUhDd1NtbUNvZjF3S3YtSjZfRHZEdjBCckhQZDB4Smducm5mQjlIbVdNMDlXZWt1NTNYNG9Ja3h6Z1ZxeUJiQzg5eUo5UHFhMHh1N2hYc0ZZemR2Qm5WMGl1V0EyRElp?oc=5", "source": "Moneycontrol.com", "published": "2026-10-23 07:22", "score": 0.421, "label": "Positive"}, {"symbol": "MARKET", "title": "Why Stock Market Is Falling Today? Sensex Drops Over 700 Points, Nifty 50 Slips Below 22,400; Key Reasons", "link": "https://news.google.com/rss/articles/CBMi3wFBVV95cUxPY2czY09uX1B3ZTlpQTN6VTJPNTJ6Uk15eDhNYWNwNHpfdnFHbFJiaWxmZDJOSmc5VTM1N2ZKWHhVYnVyeTNxbzMtMVdzYUFCSVV4NEJ5MDJiWUVUTDBOU3VHNVd0OUpmajh5WEV3S0JTWVdiUEx5bVlCalN4dWxEcFVoYjNRSl9mUmxqZnNINkhIQnlPd0QxUUI0d0tydjI1NXZNR050cDFsYU1oTkptSWpHTFVSR1hSYklmVFZtN2pxM3VFWTVJU21fMTJEd3g4WXFjWmdQamJKU3Vrd2dR0gHnAUFVX3lxTE5aal8xOTYxeTF5cWZ2VE9vWmpBTHlNUEZZZFdJTGgtZEpPS25DTEFPZEFGWEstdlh4SUZ1MVZkemk0WDVBOTNQeGVRR2dvSVNMdV95Sy1LT296bERheUozbFN4dEpsV09WTVVHbjl1dWVZOEZmZ1dLREtaaFZGZTVCWFJTUU5zdjNJcW1ESzNhc0FoVDBkOXkwcXRDMW82YnNldHVYQlJjT3hHbGNFWGt4anZNSDMzcFhIRGNHN1RhU3M2N21feG54OVJleE83M1haR2hUN1UxX0NfUEg0SC0zRGZWYlNvcw?oc=5", "source": "NDTV Profit", "published": "2026-10-23 07:16", "score": -0.077, "label": "Neutral"}, {"symbol": "MARKET", "title": "TCS share price surges 28% in October, hits over 7-month high; here's why", "link": "https://news.google.com/rss/articles/CBMi0wFBVV95cUxQRHJkNU5lNUtYWnBHY1lnQ25VMjJCUEhfZ2NRLXNEdERZTFRpaFFURGZLYWw2NTduZEtGYnNRRmJxc3RUYklWVFRkdmhobndHNTlGb09Bd0lOMURPTnB3VUNXVXVlWGpWaWE2WjNfZFZzWlY5TWlsRnBJWXdKQ2tCdFhZbWZrXzJFZ0V2cXM4ZG5pZHYwVzdTOFBnUUNBeVlENjVZSW4tR1lEX1JIMzFNZFg1TGdPVlJCOVpmcmhfRkhheWltVGdHRUJXSlVSZnpUUGU00gHYAUFVX3lxTE1IcEJrS2MxQkpDandGS2FvQ3RaZVE3ZVE3X3lmVVpYeDVSd0FzWHVycmhBbGg2VHQza3E1VmZjMldJRXNqMFdYc1ZPRFhlWERCeVZpS0FGckNSTW9XbWMwekhQYVM2NmdJWVZHMXFmNXU3Y2xtQzUwZ1ZNeXRFZEZrMEMyN1E1NzIyNGpya2pRRjNpR3NSX3NxTURwbmdYRzk2WldQVFlGQnhYZ2lnNzdVZTNoQXBKMElQSGU1amU2a1BmcUN2R2txR2g1RUNDM2NpdXRxSUFDVw?oc=5", "source": "Business Standard", "published": "2026-10-23 07:05", "score": 0.527, "label": "Positive"}, {"symbol": "MARKET", "title": "Sensex falls 600 points: Why is stock market down today?", "link": "https://news.google.com/rss/articles/CBMi3wFBVV95cUxQTlVFTFhuM0lRR3lNS2I4OHBtWWxBZU1iNm9EaFNHT2M4Mk94LWI4ajBDWlcwbS1GODhQRWxSY3NQMEhWV3QtZzB0YW1HaVJNZGF2aWJmSVdNTmRXdUhpTXZrSWxfM3VJVWNQU1M1R05wcnI0ZFNBSzNlVzVzWjhrYi1ycWM1all5VzUtVUQ1bzNtWUI4QmoySTFZSkxWVmJmX1k1aEtZR01rd2dubUg0M01tS3lVQm1XcVBqZnYtemZvVGs4QmtZdjlOUkhlVzU0MzVNSnFpNVV1S0NqNkFR0gHkAUFVX3lxTE9pQU16WXh6eHlLdVpDaUJvdDVVeGxyWXM5ZHBlZzNOUkV1T0lGcUFndlVOQkZqcHB6OU5FVFprVnJPNnZTc2ZoNTVxV0R4N0JPYTBTY19yWU54Skp3UF82cmVXWDNBOU9YNHc0TkcyZGYwcnJfZXJaUGoyMmUzSkh6OFFvTDV0MnhwRGhjSHcyVEhRcnB2SmlMZzR2RTlaY0JtMjg4bHNyR2l6Q21KOUFjcXR0bGNaX0pRcGIzbkEyczlrMHptVF9PVEI0Mld0R0dqMF93WFJaaDhkTTN0RDFLd0xrUQ?oc=5", "source": "India Today", "published": "2026-10-23 06:50", "score": -0.382, "label": "Negative"}, {"symbol": "MARKET", "title": "Sensex Falls 669 Points, Nifty 50 Drops to 22,420 as Oil Prices Surge on West Asia Tensions", "link": "https://news.google.com/rss/articles/CBMi1AFBVV95cUxQMGhtM3RXOEpCaENVaE1ldTZqLTBPWThQVWVaNlVMN3hfN0NROVdHc1RYRE9QRmtabHlpaldxU0pldWh5UzdwX2QySEJLODVCX2o5aTdMNmI4TW43NzlVMmN5cWFiaGs1N1VubXh0TUdmLW5MMEJQMVpqWXYxazJvYy0zWnZ1NUxBbEZ2N0FZRTBvWVBMM2paS3JnVGdkQV94LUk3Ui1aOUp3Z28zeV8wR0I4cjRnMkVYUEhRREF4SnUyU1g2QktwaGhiZ2JhUXBWcHFiNw?oc=5", "source": "Dalal Street Investment Journal", "published": "2026-10-23 06:48", "score": 0.153, "label": "Neutral"}, {"symbol": "MARKET", "title": "Sensex, Nifty rebound after 3-day fall on IT stocks buying", "link": "https://news.google.com/rss/articles/CBMiowFBVV95cUxQSlJoQ3Y4b1BtVE83ZDN5amthN0o5SXJZQlBwdzlkTXBwSUFGQmdwczNzenQ1aHQxdWMtQ1liaWdDV3hELUdMRXdfQXRwcXZoUG8zMmxwRUU5WHIzaVlBb3lROVRDOGJJWEsweTBvbkVPNWJvZl85Q3huaVJtZ2JtY1hHcV85N2UzTnlHZk03dEU2NjlFaHN1TU11TEVpTE5RV2Rn0gGqAUFVX3lxTE5kRGFuTUhWbFJHOVZuVlBlMXJkZzNsd0RUQXY2VlNoYl9nUlZZX1Q4ZmtpcUxmS0trMm5uZGlLd0RPT1hlWVBfTVhIdjJtZk9kVTF2ZkxNdWJ2SlhsV29TVEkxVTFIaWlxNXFCTnY0clVLeExrWWliWlMtcWRiVWFlMUQwZ09XdnVndHpWOUZ2aXJHTTJhbGpSRVV6c01OSkVOa2tCTVNHdzNB?oc=5", "source": "The Hindu", "published": "2026-10-23 06:21", "score": 0.077, "label": "Neutral"}, {"symbol": "MARKET", "title": "Freaky Friday in stock market today: Sensex, Nifty reverse morning gains and crash for 3rd session \u2014 what led to blood?", "link": "https://news.google.com/rss/articles/CBMikAJBVV95cUxQbXBZSnR4TUhRaHlTNXd6RXB3VmJfQzBkc3hKdlhDVWFPSVY4NzZicHlfeUprLWlieDFfZjl3SjFjQkgxM0lEZnF4V21Bd0ZEaWExeWl5OHF3bnFQZjRQVTVwYkZWcUU0NjJVLWFGdV9GSDZWSUhzTXhwZlNqXzhvQTJqSklNSzhRNFFhYk5BTkx4NjFQODB6TzlzRFFZb2VjS3RPYXZNLW15UTJCWGphTFBoazNiSUVVblVjbUwzbG1IbE1EdGJYOG5IMEJXMFhEdWNyLW5zZUVaRnIwV25YZEQ0UjV6VUtKcHc0Y0JMX083cTJpaDN4T1lKQjNvUEJlaXU4U25BbVZqSFQwdkVBT9IBlgJBVV95cUxNVXRBT3ZFOHlHVDI2cXNOM2ZfQTZnVTVXWF9tT0lTbEtVMmJYbmpkcXlCVVFEeFgwaWpIU2U3QjR3dEFyR05EMTJWX0FMUEp0Q09BaWQ0bVpuVFNqdDNlYUdoMTM5SFhvLWVGczByUGJ4emdPWXdyeXB3RHFnTklhbW1hWlh2a3hHOFE2LVFPNktRbmFYYk5oQ3RkdG1MMXppeW1hVDhYTmJ2SlZyVld0SkdtSl9UNnpCYlJsUjdlaGtoNTlQa2s5dlg1dGtjbG9vekZNVXBnSUZwUldUYkJBejhEREN2SzJmUWctZHA2ZHpIazlQSlYtYWZoeWUyNnI0ZlpqNTM1LVhmakw1V3VsejBoZXFVZw?oc=5", "source": "Livemint", "published": "2026-10-23 06:17", "score": -0.25, "label": "Negative"}, {"symbol": "MARKET", "title": "BSE Capital Goods index tanks nearly 4%; Hitachi Energy, ABB India slip 6%", "link": "https://news.google.com/rss/articles/CBMi0wFBVV95cUxOUkptTXgxekd1dmlzcmxmSDVFUjRnNUN0em5YSnNILTF5Vjl4MUcxRk1JOE1iMzRvajVHMDhvX0hWY1ZLNDJtam0xeC1HdElVcWlRZzMtbVMyZnQ1NWhmN3RhU1ZacnI5QXhoeGg1YmlOcTdJMm5QUFU5c3dsTDhxV3VqNlBRcFBtaFUtUVhUMS1HMGhpaWpSeDlNQVhIN1E4SUpSVWJLN0pVekVPaGViREtyMHBwNTUtVXQ3b1pUSm13c01nOVd5akYwc0ZpS3ZWQ3Jv0gHYAUFVX3lxTE93OEFlY0hVdG5NeGdNSk5UOHBGS1F4eTB0QXp6SmNtN1FTRGl0MV94U00tdWwwcUVBLWJqY00xc0Q5ZEJIS3BHVjhjbDUxVDREQ0dIekRhZUJjRG1jUDFhZ0lOMXhydkZjemtXSEpkTjVxaWZTcUdQNmM1ZF91c1BiYTdhcV9WTjdhNEJoUDBjbFBQNkFhb1lCQWVmNmVyY1pjdFFrVHpEdFl6V3I0akw2TXhxNmtVQk1qaWR4a0RJbTNrUDJrc3VmQmdXOS1rNjFnNW8wTEhycg?oc=5", "source": "Business Standard", "published": "2026-10-23 05:54", "score": -0.542, "label": "Negative"}, {"symbol": "MARKET", "title": "Silver ETFs fall up to 5% as oil surge, inflation fears hit bullion markets", "link": "https://news.google.com/rss/articles/CBMi1wFBVV95cUxNa1JlREhRMlM0NlhPM2V2MDJ1Q0N5S1l5b3U2VThGS0o3elNmaDZjNm9Ja0F1cUJNUG5rOGd2V0Zkd21zSTU1SkxHeTRDSmZZZnEzb2lpYWNTeDcxR2dsYUxFQkZEQzJBcjBNazRiX1VpT2dfMUNuUlBGb09DNTBpcFA3X1hGUWNrRldNREFyT3lfU3pmcWtMR3NqUFo2U1hSLVFaUHZGV3ItQjBvMUk5ZlNRajZkUEgyZHNUNGNlajcxdm5qSkJIMUpuaWMySjN5TlZKbmlhMNIB3AFBVV95cUxNRklJU18zdUFyZTdWaE9veFhYelJ6dWlnZk0wZjBkNklfTjFxeEw5QUVtVG1wWEltQTlCQWotQzNKa1ZGQzdVWklkRzZsUWotNXVqcG9Xdlc0V2RmVTlJSl9zc1ZydE9uRVhZVzVnQWo0aDRVektuLV9WWnFoY0FRbk5pZjRUWkdrcS1LMVViVm1pUWJMMHhSMFpMUHp4MXBYR3otaXk3Q1F1TEN6bFNkYzJvMVlUX3Rzb3gyOGZhYnEzX3BPSU9yQWJMMXJYMl9DU256TWtVQ2Z0ZVBw?oc=5", "source": "Business Standard", "published": "2026-10-23 05:43", "score": -0.382, "label": "Negative"}, {"symbol": "MARKET", "title": "Why did market fall today? Sensex, Nifty end the week in deep red. 4 key factors behind sharp selloff", "link": "https://news.google.com/rss/articles/CBMinwJBVV95cUxPcnV1Zi0yYVRuMi1CZkFTdi1BZWFKaGJMZ3VHb1NxM1U1cGs3R240RkIyMXBUcVE5ODBsNVVZTFAtOXpRdlV6TlY4V3pNd3hVVTdaU1g4QlFBaHNHc3hoelltMTczcC1NUUpEWDJBUUpvaWJtc3FvRkNXQWE4VXZyMnBaVzBQNTZRenNuTy1Qay1lVVNHMGhyTGhsLVJhdjFWOXRDR2tGbm85WDBiODJaWmRCcmh4M3k2bDJacnRKdUtjYnh3OGY0M1VaSHhPRFYyNWJDTmQ3amdqREhidDAxdkx3aXE2SVNSUjBxeDdlT3UxbEk5UWtSSVJISTRKZ3hnZ2dHSjhXWUh3OVhVQVVZb0lXWTgyQS1rSE9vRDN2ONIBpAJBVV95cUxQLUZaRUNndmw0c1k3WHFBYlNwWFBDMXNxWDB5UEZWRWtfbUZ4R1VTaktxSlFaVnoyakx5cXc2dTlWNDVvdTNFMGNJWGN3SV84OW1fSzNZMGNrcTllZnRLZHdvOU5rbTNTaHptMUN6blkwQmNMT3JlM0d0NHRoZ0xxVTI1OUVmdkNxLXBqakpLZFJvOW9hemw1Zy1TNjJZc2lyY08xcmZ1UkdIdHRwMHEteVdDbnhRUmRyekRtNDZhZHktNXJvUVVhM3NLQ20yV21IUmMwT2QzMlN1Z0FlX1R1RnJFTE9Yb2JtY0FxNjdLNjVrVnpiMlpGbTh5QmpNX1BfRHJGZlB6Y284cUt2ZFNWVDhCcHRJNlBxNGM4QTM5M3hqU1RV?oc=5", "source": "The Economic Times", "published": "2026-10-23 05:40", "score": 0.077, "label": "Neutral"}, {"symbol": "MARKET", "title": "Why Is Share Market Falling Today? Know 5 Key Reasons Behind Sensex, Nifty Crash on October 23", "link": "https://news.google.com/rss/articles/CBMi5gFBVV95cUxPek1kTGNfc2lTSFpmdURYNHdzX0pKQjZSS1dseGJIZWRDbFV5T21SdG5aN1FYRlNjQ2l3cENqVDh1UnMwVGYwMHpOcmlvbmVHb3VQLTVxWDU5SEs2Vnlld0tzMjVZeVBoUzVzdkNJazBnVmNSeU1Pb3NHUXBrYTF4ZW1pckwwNkhQNGZwLWo0QXBZQUh2Wl9FYVd4dkd0TWRHQWIxd0VUV3I3RjBlMVVmQXFOR1l0VnhWZVEwaWhCM3ZwOTVOQWRhVUZidGxmRGt4a3lLcTZvaUN4LUhCR1hCUzhQc0FBQdIB6wFBVV95cUxPZ3c5ZkNOMEdQaWVTaTRvSXJiN2NHZnRZdkUzY3hGbEFmenEyNmE3MlNiYms5a0tSMlhhYnZFOUNhNjU2cUtWRlVCUDMtQm9jeVhjMmh5WTNiV3kzdHZ2cmtBM2hvTmVweVFSMG1tdWJoTDlYWnRuLXpMdGlPbDU2T3h5RWdlQXB4bXNNNTE1TkVQMGRvOGhLeEM2N09ib2hxQVBQclhiMEVURG5BM19INFRteFNpZTl3U3M5LWpmb3BQbGNVb2NndVZjYlVUdnZWSWo4ZkxEU3l3WjVjc3J0WDBwVXZOOFFPLUZr?oc=5", "source": "News18", "published": "2026-10-23 05:36", "score": -0.402, "label": "Negative"}, {"symbol": "MARKET", "title": "Market crash: Sensex sinks 1,314 pts from day's high; Nifty tests 22,400", "link": "https://news.google.com/rss/articles/CBMi0wFBVV95cUxORHE2eXQySVVQU2tHU3hBYXNRaDlKZ2VDN0MzLTRNYkhjSXhZUXN3M1k2aHJvbGpfU21KTHc0dlh1LXN5WktJdDZERXpZcEs3a0FMVEx2TldTWmdHLUhvZWRMa2J3aUpfaENNNGV4S3VzZVBBSFBiU2dITTRUNVkxOGtHcXNMMHVOX2dHU2JJSGRiZ0I0dFpOMk94TEM4ZTdQdGlvYmhEdzNPTC1JclUwSmJNWGQ4Y0w2a1pBUldzVmlZQ0VzRGhKN2J4SEVNMnd5R0k00gHYAUFVX3lxTE0xQ1pqOHZHWlJNc3h0c2ZtanRqMU9xU09wYm9lenZCQ2tpelhKb0NKSFVwNTVzeG5ycFFEazJaM1pBR1BBMEY2Z2NvamJZWW8wcDJub3BHVDBwWERYbDl3WkxnaHExclJGb1A2cVFiQjJ2WF9sb044OVY4VzVJeTdrdkhLZUM1VC1SekVQOWtwR0pfME53YjFydk9pTTlQbVA3ZXdBdUw2cGpaSFJaMEktUjBuLXNuNjR2REt4dURWTm10OV9VX04yS2JWeFdHY3FiTFJuVTk3VA?oc=5", "source": "Business Standard", "published": "2026-10-23 05:27", "score": -0.511, "label": "Negative"}, {"symbol": "MARKET", "title": "Sensex falls 450 points, Nifty slips below 22,500 as oil tops $113; Jio IPO in focus", "link": "https://news.google.com/rss/articles/CBMimwFBVV95cUxQRHB1V0V0REszTFp6bmJZdENuVHRoMmN3MzBlcTNjRXhmNDlPZnBUWlhKRmpuTjhrMEx0ZzlVSHp6NVRRSjBSc19EZC13VW83M0wwNFlxcF9pWUVKZ0lwa1BLNXRvREZUbWNDcEJZWWFwSXF1bnllRG5GWERNWHhfaUlEcWVCS0dSbEFNVG1QZGxQRGZlenY2T1gyQdIBoAFBVV95cUxOMG9jdzdVT0NKQkJNLXhsRVpIb3BYNkZRRHJsckxabnJueWN4X1E1dG83b0N2UTBZX3pEeGwwdnlIc3JfeTlNd05WN2tqYlV6cUdEaEEzWk5vU1JnZkg3Y292OENyWjFaekI5Y2JWQ2F4eDd6MG1mYlFCdDVLSW1CLXlRTUoxcDV5bFk2TTZYX2szSWRtWUVwMmhfRVpueU9r?oc=5", "source": "Firstpost", "published": "2026-10-23 05:19", "score": 0.25, "label": "Positive"}, {"symbol": "MARKET", "title": "Sensex, Nifty Open Higher as IT Stocks Lead Gains Despite Weak Global Cues", "link": "https://news.google.com/rss/articles/CBMipwFBVV95cUxPNFFQSk9iUFdMLVBOcmk1RnRmY1pLYk9mS0FCNF9XUi1iU3dYYkNsV0ktUzFhTVhtYjdVT2dsWDFLeElsb1F2dDU1UG5HQW9DWE1GLXhpSFRyV1lWZVk0d0FTQjV5U09MYm9YZkxvNWJoQ1k5OG1tUjR6QjdGQS1RYU5GXzFMMlY3ZzZfNGJRb3ZsM2lUUlk3NzlwQ2FGVTdXRGp0ajQ2Zw?oc=5", "source": "DD India", "published": "2026-10-23 05:04", "score": 0.757, "label": "Positive"}, {"symbol": "AEROFLEX", "title": "Microcap 250 index slips 2%; Aeroflex, Rallis, Bluestone slide up to 8%", "link": "https://news.google.com/rss/articles/CBMizgFBVV95cUxQSVhXc3E2UEFfWXdoODIwS29pdEFsWF9BUjJQajQzaG83bTk3cTF5RjZNR2hzQUdZVmNfcklZVmxjeXZneXlVdkwxTFgyZENGeV91NElhd2VFckNjWm9xR19aTmpCWXp6b2FmR2N1eGgwYTRYeHBMX2ZFeFQzNXVMaURRd2JuYlcycUVseWtBLXQ4VVg3d2JGanJ2T1pDYzN4SVBjdFNlWVBTYXFOMWlVZndvcHFVTE1xTnJvcVU5bVpNNlMxa0lnalRGY2EtZ9IB0wFBVV95cUxQXzh2VGo0Mko3NkM1V3lGbEVIRkpldTc4a3c2ZWRlcUQyenpnaHVmM3RNMTkzZHBLNjJiRk44bjRMUjFnV25mNWVvRUFONnZadWR1N0tOem42T2NKSlM4bUd2ZXdoelNSbkJKM0I5V1lPZVRnMVZGNlpPTHB6cDBRYU5JRUV2ZEt3V0xyZXRMSGRHdWVVSXFRdHg0OG11MGFxRHpWeUJlYXN6cDl2MjhLeUVCcVY1RVU3cmkwZVdLU00wR2d2N053TGRvOVdVc25NV2o0?oc=5", "source": "Business Standard", "published": "2026-10-23 05:01", "score": -0.34, "label": "Negative"}, {"symbol": "MARKET", "title": "Microcap 250 index slips 2%; Aeroflex, Rallis, Bluestone slide up to 8%", "link": "https://news.google.com/rss/articles/CBMizgFBVV95cUxQSVhXc3E2UEFfWXdoODIwS29pdEFsWF9BUjJQajQzaG83bTk3cTF5RjZNR2hzQUdZVmNfcklZVmxjeXZneXlVdkwxTFgyZENGeV91NElhd2VFckNjWm9xR19aTmpCWXp6b2FmR2N1eGgwYTRYeHBMX2ZFeFQzNXVMaURRd2JuYlcycUVseWtBLXQ4VVg3d2JGanJ2T1pDYzN4SVBjdFNlWVBTYXFOMWlVZndvcHFVTE1xTnJvcVU5bVpNNlMxa0lnalRGY2EtZ9IB0wFBVV95cUxQXzh2VGo0Mko3NkM1V3lGbEVIRkpldTc4a3c2ZWRlcUQyenpnaHVmM3RNMTkzZHBLNjJiRk44bjRMUjFnV25mNWVvRUFONnZadWR1N0tOem42T2NKSlM4bUd2ZXdoelNSbkJKM0I5V1lPZVRnMVZGNlpPTHB6cDBRYU5JRUV2ZEt3V0xyZXRMSGRHdWVVSXFRdHg0OG11MGFxRHpWeUJlYXN6cDl2MjhLeUVCcVY1RVU3cmkwZVdLU00wR2d2N053TGRvOVdVc25NV2o0?oc=5", "source": "Business Standard", "published": "2026-10-23 05:01", "score": -0.34, "label": "Negative"}, {"symbol": "MARKET", "title": "India VIX Jumps 5% as Crude Nears $115; Nifty, Sensex Open Higher", "link": "https://news.google.com/rss/articles/CBMiuAFBVV95cUxPQ0xWVE1oc2JTOGdCUHZYbFpLNGVaYTg4QTBEMFFVNEd4Qko1a3M1VjFfY0NTUVotd29Yb0RtQ0xiLURjbzhiWF92emtxT19iOTRXQ1VaMnVwWlFJTkd0YW1RYnVEdXZsbUdWMjI2eWdyOHA3Q1ROdnJRLU56enBwZVg1bGVQQWJ4UDhVRGJ5cEN1cjdud1RROTZPLVJVWkgyd3N3Y1Nub0Z6TW9jWnZDaWtlUFRBTWdh?oc=5", "source": "HDFC Sky", "published": "2026-10-23 04:59", "score": 0.25, "label": "Positive"}, {"symbol": "MARKET", "title": "Opening Bell: Sensex Rises 339 Points, Nifty 50 Gains 36 Points; Q2 Results and IPO Subscriptions in Focus", "link": "https://news.google.com/rss/articles/CBMi5wFBVV95cUxPM2JJVm5iOXhFZ2ZhUjNQcDNOZk1kMmdFR0tTZTRzUUZ3SEpkVGl4Znl1OHZfQVcwVGR6VDhzUG8yZWl6Z3dDV2RBRlNrYlM0azBYd2ZVZk1EYmpqWkdIeUpockF4YWZFV29SNWZJc043SXlQRGxzS0RybFJfVk5mdjVfdm4yMTN2dUp4bVpSMFlDQUdDSmpTSWN1b2doNExkQTlqcUFyblVWa3BSZXJ5Z0c0UHBRV2RSOHNqQlNrREZMYm1EY1cza1RhQkpvQXBoc1Z0THhOcXZuaXIwRmxMY19Pemc1Rk0?oc=5", "source": "Dalal Street Investment Journal", "published": "2026-10-23 04:55", "score": 0.649, "label": "Positive"}, {"symbol": "MARKET", "title": "Bonfiglioli Transmissions shares list flat at IPO price of Rs 586 on BSE, NSE \u2014 should you buy, sell or...", "link": "https://news.google.com/rss/articles/CBMi-AFBVV95cUxPVVFWdXlMMnNDdkdKZ3ZGX0xoNHBSQzNnbnB4OXQxZldKVVUtRm9yaEJjckw0ZW1ocDdXSDd1UDJpb3hYczRnQUZHSzF3MWFpNWEtTVFyd2h5YnNPNTdLaVNZRlBrY21QdVBfblNyQVhpX3IwWEVYUVpZSXJjVEtRSUZ5QS0tVjBRRkdxY2pGMHZLMmFBdWxnR25Ibi1uNnVDS21mTzVLTXBXN1YtVjVuX2xkWl93OVpxeXVqZU1idnVndmZreU5RUTBBeW0xZ19zYkw0cVVKUTVhTHR0QnNUdk4xZV9aTmVNck9sbDA5OFpBYnhZTlRLdtIB_gFBVV95cUxPWTI2SmE3LU9PbEJ3QllFNmI1SjhqY29oLUlSQWxpS0NsRG1UdkVFNmNkU3BsTHpoVDhkWmlzRFpJZ2g5d0p3dWdDME9Rd0RicjlCXzJCQ0xXYUNpOTdNeVA5SDZzTURZTXhpS19TMUY2YXg0XzZkWUlhQ2QyS2VHbEZwRDNJMl9QNk9zYmRRcHdrS0xtYWhsdUhjTXczektiNHJBLVdsMm5uZnhRcUJzTC1oTDF4ZkNISkxPcTROTzdOUzVId24xMVR4OHphQS1BcktWckVjS2dHazJ2VXlPOHdOVV8xazZqSDNHSTNHOWFJdERXZEJ6U0RtRU5NUQ?oc=5", "source": "Moneycontrol.com", "published": "2026-10-23 04:31", "score": -0.052, "label": "Neutral"}, {"symbol": "MARKET", "title": "Tonbo Imaging shares make strong debut, list at 66% premium over IPO price", "link": "https://news.google.com/rss/articles/CBMi1gFBVV95cUxQaHI5UktOeTNYcUdwZWFwd3lHUkZOX2NYMVZVTEpBVjI1SzNBVGUxR2t6NHFhWlJ0bG9wNlh4MC1HbFpWaWdrOENncFhiRFN4R0YtQ0laTmJUTUxZNVByRkpEWENDdUx4bjZlbDM4ZlUwbS15aXFhaVNQYlFyOWg0OXFINHZWTGJPOEVqUHZPRXM0eWo0SXZmX3lndTFJQUc0N3c3OURQQmZXMzJHQlBOcnhYeU5pS2N4LVI4a0hjdmtwaVpLLU5vSVdYMTZHVDVxdTF5ZXRR0gHbAUFVX3lxTE5rd3kzb3JPQ1JwdGpXS0Exdld4b3F6cjJ3eDQ2MzFFcTZVZXg3VTJUc2tmaVcxeG5rdEFlRTcxT2czLW1TYVlRb2lYbDNiSHdjS2dkUkpMMjVCYTF3TUt2T0Z0enRXRU5TNW05cnJqeDhzakFoeGFENXBCWDNYVWFKYXhMQUZXcTY1VVVJM1UyNW82MkNua0ZObVNwYkZLcUtMLUp0UF9rUTNvSEdDY005VS03bkRVcjlkaUtmRDh3NFJRcVRRQUtiRl9YaXFYdGkzWmtmc09weUNRdw?oc=5", "source": "Business Standard", "published": "2026-10-23 04:30", "score": 0.382, "label": "Positive"}, {"symbol": "MARKET", "title": "Sensex crashes 1,250 pts from day's high, Nifty below 22,400: Key reasons behind market decline", "link": "https://news.google.com/rss/articles/CBMi6gFBVV95cUxQR250SWE3RDBETXh2Unp3ZENZa1ZNX1k3QnVlaUk4cERpOVl1Zm5XT25FNVAtZnJXc1YwSnQxY3VIUjdRckM2Wm1DZjhUMXpIVW96eXdIb2IybkxlOGNETDFvR0xVYjZuazlaNkcwNWhSMzU1b2pqUnZwVHlPYUtULVphbmh0VUhSNjFSOGNCY0RiVGM3MEdibzZLa05FQUNCc2ZkRi1FY1F1dDR5MHZnSVBWamVQSzlvaTNxNVpmLW9hbUtqRFN2QzhGX3BLOGc0Qldqdlp5c01PMkVLOUZxdVRrTVZrOXd1OVHSAe8BQVVfeXFMTmpwTlpEb25yZXVFWHRXUzhuQ2RDYVVTX08xSWZSVGFTMHlTU2F2SDVJTkN5ZU9hWWdIb0tsUEdtdzE2M1kxcTRxTWt1ZDdRdVNSS0t0bWlFWTlkSXh2Vk9wQUstRldGT0JDbGNkX3Vab1FZQVZkcWtqNmM5QUZiRS1qOFNsR0pHRmdRUkNhY195TFBMN21HNEl5OTA3aVhVYkdHWXgyMmppN0JlY3dDRVRkZ1dMeWpReHZmaWJCc3ROMHFJWEY2dE0tSU83TXFXdEpvRm1leVBLVzhmQXlHMEhNZUFJQlZmR0xDOXp4V0U?oc=5", "source": "Moneycontrol.com", "published": "2026-10-23 04:27", "score": 0.226, "label": "Positive"}, {"symbol": "MARKET", "title": "Sensex jumps 373 points, Nifty rises 0.19 pc at open as IT stocks rally despite global tech sell-off", "link": "https://news.google.com/rss/articles/CBMi4wFBVV95cUxQeTRtUHZzWkxoV3hfVUFYN1dydlZxdkYxMV9RYXBMb1JNUW5CQWNLRzJ2dUFfbE9FVk9VV0JHWThQUHNwTG9FdmtUdXdkaDFIaEFhM0N2c2kya29OSHhEbk5icGZEbjBzZ1pYVlVUdkRWUTFvYU1ieWk5azhidmZlTlRvTUhKSUw2N3plOXZ0ZDNOclktNGFDN1BvYVRYU2Z6UUFIU19yZ2dhUjQ5QW00M0ZCQ09FdlktUGozQThrUElTUHo1ZkxLSHYxdWFlbDVzLVUxX1hkRWo1dXBIOG56RWVIUQ?oc=5", "source": "ANI News", "published": "2026-10-23 04:22", "score": 0.827, "label": "Positive"}, {"symbol": "MARKET", "title": "Tonbo Imaging shares list at 66% premium on BSE, NSE \u2014 should you buy, sell or hold?", "link": "https://news.google.com/rss/articles/CBMi1gFBVV95cUxOeWhIN2xrT2Fpams5WV9XMGZla25RQjE5ZlBCaHI0RDgzRWRwUi15TW5ISG1KS0ZjQjVKZ2VwZ3hCOUppdERRQk5SWjdVcFJLcWU0aFVHTzRTcThYSHlpdnRFR0htb2U0aHJudEVQdWVqOGRhWnNKSkNVVWtORW9JS0xGaElGRVh1MG5ZT0M3SHlISEkwR1hsUkFkUlRiRk5QcTVIaWdGQVZBcG9QMVV2QktMUFFsaG01YUxSaDdNVjhxaW5fZEpnTWgyLVY0N0RBLUZFRjBn0gHbAUFVX3lxTE8wY3lVNjlRU2VRZmZoaVd4Y3Y0WGV1eXpod3dtM010MHV4M0ljamd2MlVialFpZjE2T2RiaEpXei1NSWI4dW1mMmJkaDcxZjdIbXZHS2xQanljVVNoTlJRRzJZakFLZW40VjBWelluVngxYW1kSnd1V29MWkptQWJ0aHlvWVZpbkdUSmFuclpEZXNZSlYwQjl6WUw1bHhZcm9IZHdSNFFOYWNzMmdnamk4TXZXV3h5UEVZVDcxdFZBcmZjMS1fLTV6RFU0d21McVNCamJJMDhhaTFwRQ?oc=5", "source": "Moneycontrol.com", "published": "2026-10-23 04:20", "score": -0.052, "label": "Neutral"}, {"symbol": "MARKET", "title": "Sensex rises over 400 points as Nifty IT gains nearly 3 per cent", "link": "https://news.google.com/rss/articles/CBMilgFBVV95cUxQVVJ2aVlaQTJEU3haR3RsX2lmNHI3UGRXM0dicDdHcUc1X2lLV3lzT1RoOXlOdEVNZzdKMmJFTUJ0Rll6cm5LbGpJSG0xTE5BOXJ2bUMySGQzbXJ4d2ZoVkdleWtEUjFFR1NCekNDT1FnZXQzcDBHUGJjVlRVRzJmVl8wRkdiQkVfZUNqajN4bHJxb3l4dmc?oc=5", "source": "Telangana Today", "published": "2026-10-23 04:19", "score": 0.649, "label": "Positive"}, {"symbol": "MARKET", "title": "Sensex Today Trades Higher | Nifty Above 22,750 | L&T, TCS Top Gainer", "link": "https://news.google.com/rss/articles/CBMiwwFBVV95cUxObjJZRHBmTlFZUVJ0VmgyZzhzdDJ0SEhCdTRvaXpjZnpIWnZTZ3JSS1ZhM2p2Q3FyR0dkeGhNbGZFaFJfZTRzb1JnTDR0ODhONzBxUjY3M1VoRzJBWVp2Rmg1aURiZnRCalhiYmsxT1dZeWRPbTJDLVBaVTNOd1ZXb2RJdURERXdLNVk5Rl9MellOSGU2SEVjdDhBaFNldWZXbDc5TnRSN1FuOGlxNGdHQ2dNMnQyNHR1dHJBejV1NzhaMzQ?oc=5", "source": "Equitymaster", "published": "2026-10-23 04:16", "score": 0.542, "label": "Positive"}, {"symbol": "MARKET", "title": "Market Update: Sensex Crashes Over 1,200 Points, Nifty Near 22,450; Smallcap Stocks Plunge 3.6%", "link": "https://news.google.com/rss/articles/CBMi3gFBVV95cUxNRW1NOXcxQU14TU13N3VaeTJLV1VFblZTMThubS1kel9zaFZVWXc5b2tWZktrSUphOEk2eWVzbEpmdE1MSmxxTm9OQkFhajBPdEpaX0lqYWJVX2MzRHhOSEtfRGt0cFRnOXBTZG1ycEVmM2lsZzZBS2xiSHd3Q2xoaldIdE9hRC1HTlVaZ0Q3NlV3TjBRT1ltNjNCS0xXVV92UVRlcC1hX1BPUHZzNkdZQUFxWDI5MzBxWXBfcW5IOHM3WmZsZThyY013dzJkY0RJSER0YU1JS1BBM2dSUlHSAeMBQVVfeXFMTnFCaEhHbi1rSkhZZThKUjU5bnBnTGVxb2NIcHJqZWlLMmp0cnhwZ0JLY01WcndTR1VSbjVZam8tMW40ZlcxTXMwUk1Rak51V2JRLVE4Wm9OeU9icm9BLXEwUTRTVG9DOW5TUm5lQ0NKVUxVRW9sZEdGN29yems1N1J3b2J2WFhWaUdpRTMyQVR1N0RSbUV0blUtaUl4LV9TOXJnTTZzUjVXTXozd29FSWpwdTBYdjgySUZ4bktvMDlsSFBFdmttd29pQTBzU0FSbEEza2ZUbUFOeThpRFdxbGYwVlE?oc=5", "source": "News18", "published": "2026-10-23 03:57", "score": -0.202, "label": "Negative"}, {"symbol": "MARKET", "title": "Havells India gains nearly 2% after Q2 results; brokerages split on outlook", "link": "https://news.google.com/rss/articles/CBMi1gFBVV95cUxQaDZKTGJWNVVPb0VxaWZ1R2NSNGFTTENlYlJzZi1IZ1hBbm1yYjV1NlROZDhNMi1FcXF6UXhTOUJOd1dJbndIUDRmM28wMEpzYndDTlpoQk1acjB4Z0owbmtkTzJYeEg0dEFfSUptQk94d2I5S2ZBY2NuNHhQeEdCMHNwN0FKVFFDY1AzcnphUTBfcWwwTmdieUd4MFI3LXpSYkFWVGE3dmYtTXNmRHl6N2xTaVBZSmlWMHBBX0hqd0hURkYtdnVjNXZyeVAzMWtUcnU0eUVn0gHbAUFVX3lxTFBlSnV0bC01bmVXbXBNTHlJUEtCSTI0QzBtNUlZbGFDTUxNOGZ1NFdfUjQyd3NTNU85S2JhZi1NcVVaR2tCT0JkMnZZcElxVlU4RktuRk10VjRZVk1memNiYW9Zc2lPUmtBWmVPQld0eXRxeXp3X2RpOGVTVnZGUEdkbmJuY09GMkY1Q19WbjlrZVdTeFREendoQ2IwWUZsckNMXzc0Q2NuY1lMMmdXSkI3VDFsb1c5bmpNY1VCVl9fOExORnhaakFKblZiYWFKOU5wZjVqOWZoNTdvNA?oc=5", "source": "Business Standard", "published": "2026-10-23 03:53", "score": 0.382, "label": "Positive"}, {"symbol": "MARKET", "title": "Sensex 400+ points higher after 3 straight loss sessions; eMudhra among stocks in focus | Business News", "link": "https://news.google.com/rss/articles/CBMi8wFBVV95cUxNQU8wY2JvYVJwUDBPSnlWcG5Sb0Vvd25xQ3htbkFJZFBiU0x0ZHJTeW5tQXJ6YklhVWlDZmMwNXg0M0pSVDV3UUc2ekw3ZGVtaDJoNW96UFdXeU13LXk3NVdpbGVxUGZEX2hGbTdHT1JMdFB0YVA0RkpQdTB6c3U0eF9tVmZLb0NGdW5icmw3ak03NmNlbW5ibXpaaFZja3BMM25EOEFtcWlnOWlKWm1PeWo4ZmVia1NFMFp1Z0lkQl9SbmVsWkRrWFk1RC1zT3FiWk54a3ZLTlVTaVFTSFBMalozLUstS2d1WFp5TnkxNlA0VkXSAfgBQVVfeXFMUG1VTm4zeXNUcDZ3ajN3UFFxOFVWZFpPQ1pNeHVEMEgwQV9RbW42RUM3bHRYeTkxOHkxQjN0UGJ6UVJxQ0ZWNkpyTXM0Qlcxb0xYUlBvQTBhNG1NSlNibVRTR0d4RUJHV2MzbllPR3g0RmFJZ1BvaUhtTUFTMnozQ2VsamJwZGtVS3VaU2VOVmRnSkRudmR5RGJsZmgwc1VFcGN2Tm90WEM2NzlxSURaT25CcC1tRHVFbWxKS1k2NjF6TFozQ2dkMEp2d0NkUVViSkE5cHFfTzhTV0xTR1RwQjhveXNfQ2ZmN1JoTmpqV042RlhnUDQ0WHM?oc=5", "source": "Hindustan Times", "published": "2026-10-23 03:49", "score": -0.226, "label": "Negative"}, {"symbol": "MARKET", "title": "Stock Market: Sensex rebounds over 300 points, Nifty above 22,700 after three-day losing streak", "link": "https://news.google.com/rss/articles/CBMi2gFBVV95cUxNSjBDSWdBVjlmU1NWMU5sQjhvY1V5aUt1QlQzQU56aGY0aEJwZEZvaVUzekdaSDNaYi1ZNkNGM0U0S3YtQVJ6TVJDZVUybjVVLWFXQkVobXc1N0JiWW9iTmJ0cEZiZVZOTjdmaERhbllzNTJQV2Z6Y2hPU29HdF84MFVEbHc3RGN6bi04bXozcmEwbjNwSGFmMVk3SW1WRkZMSHdSRGMxSWpxbGxsaUo3S0VsSEtDbzBFQVphZDRKcHZ2djR4ZzBSemJ0aTlKRzRvZ3k0eHpxNlBFUQ?oc=5", "source": "Zee Business", "published": "2026-10-23 03:49", "score": 0.026, "label": "Neutral"}, {"symbol": "MARKET", "title": "23 October, 2026 Stock Market Updates: Sensex jumps 416 points, Nifty near 22,750, IT stocks rally", "link": "https://news.google.com/rss/articles/CBMioAJBVV95cUxPODZaMVVEaXNXM2lsYVVaOC01U1pLV1FmNUFOWmZsVzJ2eWZJQ1dIRkpSV2oxVDFVWUlKU21JRTZ4Rk1OUElsdGlVUlJWTFhMVHdWQy0yS2NYN3hLWGJnWFRzbzgyMUdwekZrMDVqd2FvOXByaU94Q2tOX3JWX0tkTHU3RF9qMkdoMXZDZWFxSXdFUkNyeDVJcFNoQUVOU21UWllGUXdld2hJVGRJa1BYMmZYNUkwUG1XZ2xvOXJCV0JNOHhmRmdMa2hScUFmMGJoLVVUcXJtRDI0SEZVWmdHMG1WRzZwZmFhdHdqckxUWk9zZERuai1MTVgzWkFWQnZvWEZKbUZMdUJ1M3l1UHVpdHBRM09PV2JRVkc5UTNsVHXSAaYCQVVfeXFMTk9GeXcxbnRSbVdzdlFYbEdQczJab1B3aE5takdKa3VhOC10d2xuQXMwbUxGR3hfWXh0TE9DU254NDVLd2kwU2VUQTd0Q0hzYXc1dVdCd200T05PbkNfNGJFY0tLMGxYeHBsakZ4RjlYaEhQZFllaWJmakZMVHhwaEVGakZXaVdZZzAzVjRoak90R0h5c0lSa3F0VWVoWW9pOUdvNWJUcmM2d3FKQjFnX3FJdVFjWUNHY1hiZ19GTExLblhXNjRETm1xQjQtNWFnaVdpdS0wUmlIOXpqeWVfLXhFdzZlUUF2NlFpY0tjVE9KcXFyQTQ2VkJNV3hwRkRxSzFOYlpGLV9OeU1uZE5PNTdvaVBHLUxyc1NhWU02Zk82ZU16MmNR?oc=5", "source": "India TV News", "published": "2026-10-23 03:46", "score": 0.827, "label": "Positive"}, {"symbol": "MARKET", "title": "GIFT Nifty up 133 points; Infosys, Swiggy, BSE, Cyient, Zetwerk, Tonbo among top stocks in focus", "link": "https://news.google.com/rss/articles/CBMi-wFBVV95cUxQRF82QUVVOG40dldXVkJEWUJyeUM4cE85bF9vcUQzVzNfUFQwRklUSVM5U2RrbWI4RzdCMmlaVmdFTEhsNzVRQ3c4UVZVbDkzWVhYWm9QcHpmRHZibXJtd0NWZmVwMndiX3pvSzhXZWtVZU9GUjExQjdyVlJKWjBfNWRZckZidE1XYzd1SmlmcEMxcWdPUXRfTm5XLVdDT096eGpEZWxVY0EwdEpGTzlNSElUeC05YXhsaDVNMGZBYzNKWGczOWlCME43SGVBbHBYZ3JNcnhObHpLSEF5S0FkOWdJOTNOV2p2dV9oQUZVblhlSkE0aldPd1V3Z9IBgAJBVV95cUxOVkhkckZ1MWhEWGhzcXd3dlJaN0hKTDNXWFNacWV1SGhMblc4T0VQQ2lMR2JNSlVpTHdFOXdXZ1RUc2VRcS1Sd1JscGxSOFZ3Uk03a1FyNV9OVHRGTl9neUhEX3htM3pGSjhRLW1IZi0zV2szSmlMQXI0NXdTV2dvS0dOR0w1VEhSYm5JelN4b2JzY2NxcUNtMDM4RmVvaU91b2hQODNSZmRSZGxDLURDZ25CQzdUNW1ycEpIM0dPMHdJQnllZFlza2pzcEZpeDhyTzQ5M2FRZnM3UDNkeWVGaldYaklRVnI1QmVRQV85NzZTM19SVjlBeDBoZGt2clh0?oc=5", "source": "Business Today", "published": "2026-10-23 02:59", "score": 0.798, "label": "Positive"}, {"symbol": "MARKET", "title": "Surging oil prices drag Sensex, Nifty 50 even as Jio Platforms IPO shines", "link": "https://news.google.com/rss/articles/CBMiywFBVV95cUxNQjBIRnRoUFI3Z3VnU1NiMlF5Wm1BNG1FaU1QajNaWURVc3dvRUFSV1c1U3NMcE9CRktiNjlZU1N4S2RGQmRvTUlmcHotQnl3TTBCU05jUVJUMV9jRk15R3pieXlqTV9oQnRfN2d5NWo4U01YLXhuSmZJbm01Z2VFQTk4M0dNbFJzVVBQLUJqRldUSTRtVnF3NGlUb2tZUDJja1c4Q2RieGRGN3psYWhpZWtDRU0yVGh3enZPWEtGQVo1bGZoSWNnWkJRQdIB0AFBVV95cUxOYVQ2RU14VFllRzQ0M3ZNenF6bmJNUlQ4QXI5YkdEdmlNejUzMnp6bHNGUWYzVnFPbGJvUHRjOHU2QkZjd29mSzNISVNyU0duNXhVUld2d2tpQ1QxbzRnam1qbS15WlZnREF3RDgwWFpac1pTMjZ0c2MxUDFUX3k5NjJzOUpxUkhMaHM4dldUVFptalFDYVd2am9sRjF5a2tvSnRYZFJzdDN3bzQ0SXVGMmhFYmtvTm14NnBHMTFjN2g4NDJmazRZV21kc1FwZlNO?oc=5", "source": "Livemint", "published": "2026-10-23 02:30", "score": 0.202, "label": "Positive"}, {"symbol": "MARKET", "title": "Surging oil prices drag Indian shares to weekly losses", "link": "https://news.google.com/rss/articles/CBMixgFBVV95cUxOeVk5bXN2THRVWVBubnpudHpPQ2dreFhuVUxXSUFqZWJLa2psTU1rbjl3UktXTlVabEpvVEM0YUpuZVBUWkJQSjB4X1o1QlI5OEZYNE1fNE5QREZ1RjZqeURTcEFZSm5DbkFGYkFCLVNVYkpRNXRCQ3RMTDExMGVJdS1lUjUtdlBFVkJQY1VXdVBZTF9qVklpbU1YRXp6dHpXNWhqcHVFVFNsZUtQeXV6SGNBTnJYaHBzWlE5SF9EeFpiYllha3c?oc=5", "source": "Reuters", "published": "2026-10-23 02:17", "score": -0.572, "label": "Negative"}, {"symbol": "MARKET", "title": "GIFT Nifty Rises 102 Points, Signals Positive Start For Sensex, Nifty; Experts Say Concerns Remain", "link": "https://news.google.com/rss/articles/CBMi4wFBVV95cUxOeENlS1JEazdEdS1pY3hldkxqVUU2bGRicFpDTG9DNHZZMTE5YXdxTzVNTnJZV3ZxZktfaGViUURVM0llTDE4UFlZZGs0Z2N1c3VtOUNVbC1hRzJNZjVkamxHek9aWkZVam5zVWYwTWFLVHVPWTE2NWc1TlNtV24yZUJwUFpqZ01sVzBYSnVkbDZ6bEI2TkJzcEswMW52ZGpraDBtSnlQdHBhc2dYMVVOTnhfZjdGeDh1dkFOdDB5TDZ2UnpIaWFEd2s1NUdKMHA0M205YmJqWnJSNUhqVEkyN1JGd9IB6AFBVV95cUxPLXdlc210RWxmTzZTUU5zaFJYQzVfNHVmbkllRTI0UXZJbVpxblFDS0hTaHJXbm1NTjlOTG5MNnJiVG9nLVE1T1FOeGN2Z1VlUGpTT3NYbTdmQXRSbGFZSnJOOTVkcVRrV0RFXzFoVDQ3a2ItUVFGckVKZnduQXRKODZaa3JTZ0FXZnQxRDFyc0VMNVFsRC0wZ0FTdXF6c2tZdk84TlUtRTVzTjMydnVVZ1Q2S0swMUdYRXV0TEtuZ3hYbnBxaUZiOTNmeUstV09YVl9VNG5MZUs1TnZuSnYtV0d0ekV4dE1E?oc=5", "source": "News18", "published": "2026-10-23 02:17", "score": 0.912, "label": "Positive"}, {"symbol": "MARKET", "title": "Top stocks to watch today: Infosys, Tata Motors, Swiggy, Cyient shares in focus on Friday, 23 Oct | Full list", "link": "https://news.google.com/rss/articles/CBMiggJBVV95cUxNOVVCUXpYOFFvMHRiNUh0STZHZDJIU21Fc2pxaElwWHBlNjlCMzBNczUyMExydzNMNXp4NmhaVkdzRENneW9YU2htOGs0d2xYay1XLUNWLVVsNlZqOU1iSUFIb1Y0UFFEeUFkOF9KWGdaMjZPUFdfSjRBQW9YMUduZktUcUdGRGhSckZpRGotSDhDazBSX2tHRVE2cktYaW1acF9rQnItamVNVHFoRThQMmVCQ2VjZXF0Z29IS3VEWGtiOVZZWUc0djgwVUxuSVJsaFB0bU1wU09NeDZtQ1ZvR3A4cS1RWkJ5ZE0tOW4tWFc0eURSMXdpUEplaGN4Q0lnQVHSAYcCQVVfeXFMTUNzZWFUcDlaY1ViVHpuYmZheU9mWTZaYWlQcXdJRlVuczc2dS1vc3pjMVAzVkxUMnc5c3Y4YUdJbmdXYkRwRS0zSm9fSnNVdW5HSGE3ZVlTUmNOUU9Sd0hQbzNGMUw3Yi1oWFdlbXdGSzN1Sl9DbHg1M0l1SWZfb2V2QVB2VnRfV0dSbkpiQlRubVk5MklvREN1bG1lTkZ2a2RDSzVQSkZnSG5IUThlemxYUGlqc3MzQ3Fzc0NlMjg4ZU9QWkxlMFlCbFFEOXhzMWdldmU2aHRncDR1MlVmS2NJQ3M0djNBcVZBenFuZkRHNTZralp6aWY3cngtc3F4Rkx6aTdRcEU?oc=5", "source": "Livemint", "published": "2026-10-23 01:54", "score": 0.202, "label": "Positive"}, {"symbol": "MARKET", "title": "Sensex falls 1,000 points from intraday high, Nifty below 22,500; small and midcaps plunge 3%", "link": "https://news.google.com/rss/articles/CBMihAJBVV
A4: 95cUxONnJMM3BTT1ZsdmNEZ3hLQlJRa2hqMWtuVUdyVzl3UnVOZFlqeTNRbWZJQTZxcjNTNFRSanZUb2Jtdll0OGhkQ2MzSjFxdUxWRlZVendyOHoyOW1YNmhWSkdSNUpMdFJTRnRKWGd6MEx0aWM4QzhiNVQ1SThIWUtBOWpSd3NteW5hQU1qblNiTEpqMWZBSzVLRElpSVRwdF8xTDdqX004UUEwTTFIdDFpaUl3bFNOMnFxLTN5czVsdWVXb2lpTzJZd1lfZVJvbE5ZWDlYR3RFOEVBUjJyaXZ0MHc5YnlDSS1PLUpWTk43UXYtNjQzYkx4WWU5N2xnVkVqU0FDZtIBiwJBVV95cUxNeVJHamZ4anZFR05lQjB3YzQzYkVfTy00WUE3X0Q3ellsNjc0M05uUGxiWGdULXhPb25KVktfeldvcVdIY28yZnY3ZGR6N3MyS1FNcU5VYk9vT0xNUS04M09BdkVKaUJyMkdoQ19GVmZLZUs5Wm5mRzJEeFRTUmJqVnYyelMyQlN0WUpfVktxam9xUXp0V1ExZ3VTQTF5RmQwdXU0a0hSYlVUTVBhbEF5WkFpU3g0UzJGeDNiaTNfeVVUaGV5c2lCbXltb2VNdF96cUNQWVRBeF9tdDRQT3RUMzhJbzlEWHVJLXF3VGx5dl9FbWNYdVhmT2diZWZHd2YwbEVSbTkzZ2xVdm8?oc=5", "source": "The Financial Express", "published": "2026-10-23 01:36", "score": -0.382, "label": "Negative"}, {"symbol": "MARKET", "title": "Stock Market Today: Gift Nifty, US Tech Stocks Selloff To Oil Prices; Five Key Factors For Sensex, Nifty 50 On October 23", "link": "https://news.google.com/rss/articles/CBMi_gFBVV95cUxQQWdWRVpsUTNxQ1RxNHNyYk9CMlBJRk80WmcyZWloYWRoaUZrQlNybHZLYVFfZ1V5dkpEZGJTR2w4UF93MTBSWms0UkMyOU1BSS12bFZydHo3Zi1kcTVNZXZIM3N4MDUwRUxITG9NazI5M2FGRzdrN2Z0R3Atbk13cjB6SnRBVEdtaDVMcVU3OHJDREYydTJUTUZSWERLRVRTbjRuWkxoTGNZdzdQQnFzbTlOTFJETTVRUjl4M1VNeVg0ai1PV3VOUlNEWnRTcktKWVN2NWViOXY5cmRSeDd3SVd0NnVOck9IQVpBX2ZoYTFiQUpGQ3BNQWxrcG8zQdIBhgJBVV95cUxQUG9tU20wMjhNUjNkOTZYVXpic1RuYkhHcVZBdGZBMkpaSDRNRS1fMHdjYjFDY3JqZTczRWFFWXl3SE5pYmltRnpnZV92X2ktMFV1aGRiZTJ2T0tYa1FMNW9PRzhsLVk2S0JUTU5YRGdvY3Q1MUgwQlUweFJiU05wa2ZhUUUzNE1GR0MtbFFHSExJdGlJWWlBcWt4Ry1iRXkzVVlTM09pejk2SXdOUDFrYkxDdGM0dU00dkhvdE96V3dDQjVkcm5UcW5jY3czMmwzdFo5V0k0dDAweWZZdkx4LW1FTnkwYnc2WVhBbmhzWGZJV0NKR1NjTW8xZFBVdUVpY0lITHpR?oc=5", "source": "NDTV Profit", "published": "2026-10-23 01:31", "score": 0.807, "label": "Positive"}, {"symbol": "MARKET", "title": "Stock market outlook today, 23 Oct: Sensex, Nifty prediction - DJIA, S&P, NASDAQ, GIFT Nifty, Kospi, Nikkei, Taiwan cues", "link": "https://news.google.com/rss/articles/CBMihAJBVV95cUxPTWxKQmhIZi1qa3BFdEFrWVNkUDJnaEswcHk5bThXdGphTkNINUFXLUZhc2t0UkF1UVFTYlJaNnhQWEk5TUVNVVpNYWRwM2hBM0JNOFE2X2JWYkwyZlJ5Z3ZENFMtT2dtZWRCR0MtcWV5ekN0QUJuN1llRjVsNDZMU1hmNG9UTldJa3Rvd0pnckJzd1BMNDVTOGxLNkVBVmhwNTZXRWpVcGtvUzNHUUI1SUZ5TzU1MGQ0aDI4NFhLYUlxUjB3aFktQkE3a2pDTXR2V1BRTV9rMWt2RmduVHpFUU1GdnR2Ujk1aTZvMTg2Z0dSMGVJOWNPYWZRWnBHUjZVTnc4RtIBigJBVV95cUxOcFctNlFlTXNYZ29wZDFVWWwzeVRfT2hJekJ6cW1fU3V0bTVORlZVR3VTWXpDdldYcEdsNzFPd1VHcXk4WWRmemVsMFNQSmRHWE5mNEt5eWVMUmVvLURZUThCTTFETnd2WFRVM2VDU096LWl5WkRRWXZfMHZ4cUJPTWVaTU0tam16STVJUnlOOHJsdkg2dTkyb3hDVTA2N25TYjRSVWxCWDhKSmQzTzAxdVVlV1dvdTdkZC1CQllOXy1FR2VzalYtOEhQSEtDTnBrakVGa3E3cjV5b3U2blQxT0JjdGhId1FqUkVrX1dwbzFtUGV4NUdmUmI2amVadzQzN29leW1raWtUdw?oc=5", "source": "Livemint", "published": "2026-10-23 01:16", "score": 0.842, "label": "Positive"}, {"symbol": "MARKET", "title": "Oil price surge keeps Nifty in red, Sensex sheds 460 points on Thursday", "link": "https://news.google.com/rss/articles/CBMi0wFBVV95cUxPbnVBOFBMd2JkeEpUdWhNWWFuS3ZsQXJBbkpLVEgzQ3lOcVlxc1YyUTZlaHotRzhqZEFqRmtXd21YTFJrWlVhaVduTWVWckNjSHJLS2pLSUM4eHhlOXRzUVpUZWt3bWZiWTl4Q205eGV1akprWXBwTXUya0RmWjJhWUJMWnN5WndPZnJEcTNDdnZuUnVyX19fVGZremtpUWxzaXQ5VlowakM3UWNidG05Y1pnUzc5UmE3Njh6N1VsUkRlcW1lMVNOdTA1OHRQekI0d2w00gHYAUFVX3lxTE5iNml4WGQ1ZFpidzd3OGNzREdxZzZaUlhUSlRWMG1PY1Z5c2JKSUVYaEFsSFJzSVN5TktuM0trVEdNdDF3MlhrdWNGUl9Gd3JBWkhoNWctNVRjb2ROUnVxRXp6REJGamFNay1RYWZmVzdwRk9kWVN2alJibGRDa1dtWm9KU09ZN2RreVN2dHJrR2Y2ZVNfTktPdEhjQlhhMldsS1J1U3BoT29TZTF0UXhOc05GNEZjNG5iWERDaEl0LWQ2bnJBMU40Z3NVd1Nqd19MaVpSM0w2eA?oc=5", "source": "Business Standard", "published": "2026-10-22 15:03", "score": 0.511, "label": "Positive"}, {"symbol": "MARKET", "title": "FIIs sell \u20b93,459 crore of Indian stocks as market falls for third straight session", "link": "https://news.google.com/rss/articles/CBMixgFBVV95cUxPdE5KZVFyTDN1QUpURTlLNV8xUjZEY0Y4Q1AwZGUtajBKWmNZN3p6UklJU3hJeFhLT3lvUnBYZjdaTmtqOFVvSXpfNWc5bzBNSXdGVE1ia010X2FOR21COVN3aUJwYXB3YnhmVUc5UG1uVi01cXViNHF2cmNaZGNOckhqUXVHV3dKSXp6WEdEbTdnSlBaMGdTRnNzbDdUZEs0Nlh2U2h5ZmRuVWdsUkRVY3R4ejhOQkliNTFSbnllWWhMak5KNnfSAcsBQVVfeXFMUEJDdVdpWWtBczNQTmFRNHlwUW0tRlVyWnZjSlVQOGdrejBjRUFsdFJEVy13MUF0MXRzcWMwODBBMml6RDd0NDliYUtDd0tBdXhVQlRJc0s5UnlEVUJ0Y2lkXzFYRWRKRUhYcHhGWWFCRDk1LWJwSmViTG5KYzJHYi05eC0xRE9aVWRCVWtwWmN1TkxTNlBPNnV1MnVMRm9ranNBcXRpN3loN1FDUjlOd3NERXMtQWx6ZFNpOVZ0d3ZHU2I3Wl9QNTM4MUk?oc=5", "source": "CNBC TV18", "published": "2026-10-22 12:56", "score": -0.477, "label": "Negative"}, {"symbol": "MARKET", "title": "Share Market Today: Nifty 50, Bank Nifty | Oct 22, 2026", "link": "https://news.google.com/rss/articles/CBMi0AFBVV95cUxQeDVfMzZHd1BEcDJYUndvc240UUItdzNXZXRFanhTeWxYMTVIcmRXSVBaWDBBMzNkOGdKN19ZWUFhaFVyOTNIZDh1aDVhM29oYW9sdDB0RThJclc3X1YyZ3FYM2RMYkdoQmFRZjlKRDEzWGE0bHNZSzJhaU5Db3M3ODliLTdMSDJjcmZQdWFrZTRmdDVjZFljamVVcG5tTzJmTlhvN0daR3hUaTg0NjkxTnBKQUpBZXVyLTIxa29GdUJSRk5MbDNpbGROTHpBUDNP?oc=5", "source": "Liquide Blog", "published": "2026-10-22 11:47", "score": 0.66, "label": "Positive"}, {"symbol": "MARKET", "title": "Stock Market Today: Sensex Falls 460 Points, Nifty Closes Below 22,700; Media, FMCG and IT Stocks Drag", "link": "https://news.google.com/rss/articles/CBMi1wFBVV95cUxOVU9BekUyYlJlTFVRTG12cVpLTURpTC02WU9obzdOdEFyMGZlb09vSlc3ak9xVW9vbnZQU25ZTVY5bl9fLVNLY0c1WExWWmh1b0R4dVhST2RVdWtKQVFpU2psT2RlYkZIcElVY1hKZnRkaEM2aXY3ZjFvSnRNRFB6VklINTE5cnFiUUVld3VSNUJDdjk5d2ptVW5MVUgybEx4SXpOcDRSWDJnbHpKQ3l4SnR6TWY2cmFoLVloVEFQZDR3M2J4ak5tc2hQREtaRVBsWXJoc2l0VQ?oc=5", "source": "India Infoline", "published": "2026-10-22 11:03", "score": -0.202, "label": "Negative"}, {"symbol": "MARKET", "title": "Markets Extend Losses: Sensex Tanks 460 Pts Amid Surging Oil", "link": "https://news.google.com/rss/articles/CBMisAFBVV95cUxNb2FTRjNBRXZ0YjNCWkdScDFaUzk0WlVuSTRpcS1nZzhnMi1BUVJtNzNIZ2J6TFk2ZGgyVGZnV3MzYklyME5fZEJxOVdqaFlIdmJObmg2R3EyUVk2Yy1wTHhjN1dXOTZja0xzT2ZNSjJpS3VHRm1XcnZNRElTaWlTaFJZTG1lelVMdF82N2EwVDhOTy1FdXBIOHQ1YU9aWXFCUDljUkt4bV9oT0E0M2NVRtIBtgFBVV95cUxOVURVeF9ZTW9udWxPcE03Z0o1R0VzUmJrMGtmN0ZWcXp0Y3Q1RDMtUF9KQWJIMDdab0VXVHBZRkQ2bHZscm9rdjN0M0prcVlZNzE4R3pyUGlLSi1JX0MySGJlekN3cHp0SEZKeTJlODE3OWpzeF93MjhNMWR2eWxFTGN6OURsVzU0NjNTMFlGYlRYbUtCSEVGWV9JNF92bTBZYTNZMzk1d2ZITTAtQV96ZUprMjNxZw?oc=5", "source": "Rediff MoneyWiz", "published": "2026-10-22 11:03", "score": -0.649, "label": "Negative"}, {"symbol": "MARKET", "title": "Market Close Report Today: Nifty, Sensex Fall For Third Straight Session As Oil Tops $110", "link": "https://news.google.com/rss/articles/CBMisAFBVV95cUxPVWZ6SVVVcjFqY1V2c3B6dG5jbENlXzVxc2t2R0EtV1RZeWVLNmhEX3FQMl9lcDdTZ1JVdkpWYjhJelhSOTZyVEsyd2l5YTRNQ1hNckVrTzkzUWRGb3hHS0FCdXZKOGwzVWduQTBkcFYtelg0M3ZTYnk1N2RkXzhId0pZMi1McXM0ZmUtalZ6Y0FZRklxUmFUb1JRRE1HVEpMZ1doeUtSWDFTN3V4QjRiSQ?oc=5", "source": "HDFC Sky", "published": "2026-10-22 10:58", "score": 0.67, "label": "Positive"}, {"symbol": "MARKET", "title": "Sensex Today Ends 460 Points Lower | Nifty Below 22,700 | KEI Industries Down 8%", "link": "https://news.google.com/rss/articles/CBMi0wFBVV95cUxQWDRBeVdHWTA4d29oZWRYdV8yRVlGQmllUE5vR3haZHFHOGQ4bUc5amNnb0xER1Q5UmNIWTZVM3JVdXhyUGxTN1J3ZFdEc0dqbEs5b3ZDVXFpTFg1YWtyY1I4Qzdsd1VXaXZ3bjJhQkVnUGItaUlWa1JiTGZTbXUzVTRHdm40WWlYZnZIX0l5TEE0dTQxdUNiUWppNldaUkRZUGRpc2hBdXJPQ25xMzNGNzdnRnRObmtFU0UxM0JJY0FhdVotQ3c1UEVXYTVzRWZZVmdZ?oc=5", "source": "Equitymaster", "published": "2026-10-22 10:43", "score": 0.226, "label": "Positive"}, {"symbol": "MARKET", "title": "Sensex, Nifty end lower for third day: Elevated crude, weak market breadth weigh on D-Street", "link": "https://news.google.com/rss/articles/CBMiwwFBVV95cUxORmxJb0xkZmFUWWhzVGdmdWdQV3BibjZVSlV0QWFUMU96UjdEX25oNUpXNjYzNld6TGw4NFBxTzVPOXQ3YTJwNVFuc3R0QzB2QzJCWjJaM2FsNTZmcjFwR2Y3MXRORGRSeE5FdUl4V0VNV0hIV1dXWXY5YXo3R1lpU2wtZ1BaeVFkdkFpTS00LXBSS3VQR185MEQtRlgtSllmTUlZdVAyemsxMklYWUxrSU0weC1BcVpOMFBHNHpqWnJqelU?oc=5", "source": "India IPO", "published": "2026-10-22 10:33", "score": -0.66, "label": "Negative"}, {"symbol": "MARKET", "title": "Taking Stock: Bear attack continues for 3rd day; Nifty below 22,700, Sensex down 460 points", "link": "https://news.google.com/rss/articles/CBMi6AFBVV95cUxNaW9FTkNEcEFjRUY0cjNzOVZYV2RyRFc0dFFRc3QxekVFRFMxWFM3TERkZE9aOGloakc3REpsbUJlS05xWVhNTm5rM3RUeW9ZRkQwb0tUQ2ZrZTBSZzN5NVRNYnBvOW10c2Z1ZGtKakRfOV9mbWpHVUNWZWFUVFU1b0JfcDJCOU9jTTByRHVIckxOUExBcVdWSXhqclM1eE5vOGFxeDVwTS04Y3NSVF91SVhtN3d5RXZQclUyYkxOVF94ZUN1R2ItMWQwcGdYTmh3cmN3YWNZVHJ6MnFXQ3VOZURZa0UxZXhZ0gHuAUFVX3lxTFBXNm9sdkZLNkpxV2pETktJTVJoVFZfTEdrLUpTeVJJN2ZJZzdpSnFqNHQ3dzRvdmQ2ZnlYLUtVeEpaenNQaUZlZjR0T1IxS1Q2YW12X1RiamxJMnE2TnJGQnRRYUdXQWRwWWNoVU9jLU1vNS0wZEVqS0themlRemhVaVE1NWdid3lWYlZmcE5rTXhjSHliaWkwS0phVDNTOWkxSDc5d0tWaHY1dUJXcnRqUTFCVmJ6NTRaX3VDdGs3QURhZ2E4MFVzUk9zT20zRm82OXpxRGd1TWtfVkxWM3QzOGFlbnVuQkxCV0d6dHc?oc=5", "source": "Moneycontrol.com", "published": "2026-10-22 10:30", "score": -0.103, "label": "Neutral"}, {"symbol": "MARKET", "title": "Market Today: Sensex Falls 460 Points, Nifty Ends Below 22,700 As Crude Oil Tops $111", "link": "https://news.google.com/rss/articles/CBMi0AFBVV95cUxQbVVySHdvQ2xSVWZkaE45QnJFNXFOWU1WOVFwMlJsNVBCQ0NKZHk3NjI0Y3NHV05oMWNSOHZvanBhX20wd29Ia3lPRHM2b2p0VHNXc2tnT0lnazRKWU5NVkpjSHE1dUExazRkc0c1MzlxdWRzZ19BYnJEVnBjbnBlTS1MbkFMYVl6cVBtTU4xejI5Wl9ubmZfLUNGWG5aN1pzMWRSbFY4dTBQaXY3YnZhRk1uakFkLVdsUlRyRy1qb3c2NTdwZEkteURONGNUZ3Zl0gHWAUFVX3lxTE00ZEpnZ2dkSkZxcklVUk1xU21CaDlYakNDWmhzTGhkSk9WbFgxLUR2V0VETWRLRGxOcENsbmtrWDlCRnlfTzY2b3BHLXBGWmxWaEM0b21uc3lRTU9QMU9FVVF5M1JHVXhKRmIwX0I0T3JxQkU2YzhSWVVfZW94cEN2TzRHSVgtZVpWbHkydHB4bnBaOGd4RmNRS2d4OXBYZWRuUXhfMVhwbGdzd1dXQlNLWElvSmNiSmluM0VwYlZHaGV2WlNhNElUSUhfZzR6U2NfT3VaaHc?oc=5", "source": "News18", "published": "2026-10-22 10:24", "score": -0.077, "label": "Neutral"}, {"symbol": "MARKET", "title": "SENSEX, NIFTY50 fall for third straight session as crude tops $112 per barrel", "link": "https://news.google.com/rss/articles/CBMi0AFBVV95cUxNNHJwMHctX194YmgwOGt5TnY0bllIWkYxaDU3ZTZac3RXSnRxcFYya2FSZUI0a3I1YmYyak93Y195b3RhT0FuLTM3T29PT1REcmFjOWxBYzFxR2xibFgxcE43b2ZGcnBvR1Z4TWQ5ejNXaWpnSlVvaXpuLVltZEhZVVBaV2FtSGtJQ0w3WFJWZEdEY25GejFkcHExcDV4RU9kaEplOEhzU25zQlRqRWtKWHoxN085VERzREczUjJwd0FUc0ZqMFZzZ0wyd0tLa0lO?oc=5", "source": "Upstox", "published": "2026-10-22 10:22", "score": -0.226, "label": "Negative"}, {"symbol": "MARKET", "title": "Sensex, Nifty end in red as crude oil tops $111; markets decline for 3rd day", "link": "https://news.google.com/rss/articles/CBMi1gFBVV95cUxOTHlsMUkzOEkyOHJKY3BSNWdlX0dkR3JFRG90QS03UlBZN2M2M3RCVXc2RDJhNGR3SFFoUGJ6YkpQaFVLN0tVZDYwOWV4MWhVLXEzZkN5ZElEbmpHOU5fLWIyd3FwSmllUkxPLWhsTnBzWHlEdFNLdmlia3dQa2hPWDlzU0dkbFhYQWZSLS16R242SmZFam1iV1VtaFpXQ2kta29mWHI2ZWtfbHlMWGhsUUJ4dGdqeGk3S1JaaUhSTU5XRGRyX01US3htcnp0bGhPOHdYLWFn0gHbAUFVX3lxTE5ZRTRndFFQbk9PWVB5dUJGMXhsUHBFN0pBRWxzM2hubXdZZVJfM0tLRUZVRmJMRUR5cEU3ODZSTXZiWGFFYkE3OXZEazJyNWNUSEhIel9ENWNfU2VNQlZHTGd2VXdmVldZLTZEXy1xUU5KREZmOHUwQWNSYzFieVpKaU0tMFVRRC1WTVRCRFNab0F4Q0tHd2p0aE1mUEdmdDJLWk8yM1YtY2VXZXptR3Z5WmhMYVhDQkQ3ZU1TTnM0NHQ5b2JqTW9QbzExejkxTGdYcmlMTHM0WXczWQ?oc=5", "source": "India Today", "published": "2026-10-22 10:04", "score": -0.077, "label": "Neutral"}, {"symbol": "RRKABEL", "title": "RR Kabel Share Price Fall: Price Action and Fundamentals", "link": "https://news.google.com/rss/articles/CBMic0FVX3lxTFBfZUw0Z3FFMW5wMEh2Y3hDQWYzaXBDdjYwOTU0U0F5QUhQOUJrOVBwaklBamt2WlZRV3BpSVk2cllvR1h5OUZuZ1JIX0UzWVllUEJfRVhGM3dFZzdRenlJMXpwbVp6WmhsZ0ZfdVY5bEdyaVU?oc=5", "source": "Univest", "published": "2026-10-22 09:29", "score": -0.34, "label": "Negative"}, {"symbol": "MARKET", "title": "Crude oil above $100, US election uncertainty: Will global factors keep Sensex, Nifty 50 under pressure? Experts decode", "link": "https://news.google.com/rss/articles/CBMikgJBVV95cUxPTDdoNFRQRG45bzFHX1FuZnVxcHBiNTA1ZUVPR3haTU5GN2xZTFNMQXE4UmhGZ3JFVG9YaEZRMGZyLXdobnpJSEE4OWNJY0swZ2dPVWFjbHdYUjcxUlRfWTI0M0MyUXlSWVVxR2dzR2YzVDBaa0t1am5YWVE5a2U3NHN5Zm9NNWFGLXl1RXJfOER3T1ZuekN5M2pBZkN2M1p5OTRnc2dTUkNHS1dVUlYwVE1vZktQWkROOV9YRDJYQnpNUXpyWURlLXZTNWFhWmZhd1pZOFJkakxuQ05YcDZFME1NZHNaMDFHVjVubXVIZ1FDNTRlYjdoeS0xcVRFdTFkVzJ2d01XNHR4UXQzckhuRkdn0gGXAkFVX3lxTE45T05GdVJZTktqb2JFdHRUVDZmOGNOSnYtOWEyQkM1b0FZTzFITmNqblU2TUlWVjI0M1hYckF0alN4Qi1kSEM0dE9XdkFGaVpuS0FvclV5R1NmbEVwX2RFdEp4R2gteklFTnA5alJvMHRGaXRUcjgwMUx0QXJWTjNMZnNfLU93Zjk1RnpxS1lLa0tiUzlBU1d5Nm14WGZ6OWVENUNya3E0RmU5cFl1aDNpVmVjWnA2VjRRcWtFM21IcWs1SjlfUGRYSFR1ZS1SRG5MZ0VyVUtSeDJHc08yazlacGRPUHNsam1MSE9yaTVtZ0R0d3BzQnhxYTVDczRmZTltWnpPUk5BUS1rUW1kNUFBUTAyRDJkdw?oc=5", "source": "Livemint", "published": "2026-10-22 08:35", "score": -0.681, "label": "Negative"}, {"symbol": "MARKET", "title": "SENSEX falls over 500 pts, NIFTY below 22,700 in noon deals; IHCL, Tata Teleservices, Swiggy among buzzing stocks", "link": "https://news.google.com/rss/articles/CBMi_AFBVV95cUxNTFZiaXNROG1HUHRnVDc1b0VYamdpc1NRYWdCWFhJajQtNnRyVzI1WFFsZjYxdlhhdHRwWFNzNjZMUXBVcHBaS1FoV1RSZnY3Uk5xVzdPbDhBdmxZeE12dHoyc1BfdzFMUzNXRVBWX3hhaTgwOXRKNTZQV1ZUazBUZHYxdkpjbG00ZDVMQldRd2JjaDZhLUNiY0xCcmtQcnJWSHVKaFJSZF95d2F1ZUMzWnhNY3lXdU9MX0xqZVNLdllIVllTOWVrSk43cHBDQk1yR1VOZjFpT1NCZmYybXlBczhXREN4TTZpN19XdVVnX1JYamZmczM5UWlQTHQ?oc=5", "source": "Upstox", "published": "2026-10-22 08:20", "score": 0.21, "label": "Positive"}, {"symbol": "MARKET", "title": "Why is stock market down today? Sensex drops over 700 points, Nifty crashes 1% - Top 3 reasons explained", "link": "https://news.google.com/rss/articles/CBMi7AFBVV95cUxNM1ZMNFBXeDMtZE1Qb1QzMFQzLXJwdjRsSW1jMDhtVnlYWXFfVzNDdDNTLWhkRmozNm1Sa1lpSzAzSm9qYkZPNGpheHNEQXprelE2SElJbzRnM1Y2SUM1eV9mVHVyOTRKVENWRlVoaDMxR0k2SGM5bFBZTDJBX01SbDhhN0NPQklSTkpoT3dSZV9Id0oxM01CWUxEN3BxeFdpVEhmMzZfQXZiRmhSTXVsSC1iVlpGVVB3OGpKc3JWTVN0TTNyNHpiWXBVLWhaLWJSajdLalNXZWZjNVFBOGpEUm1lSUJHeDhwRURfZg?oc=5", "source": "TradingView", "published": "2026-10-22 07:33", "score": 0.542, "label": "Positive"}, {"symbol": "MARKET", "title": "Why is stock market falling today? 4 factors dragging Nifty, Sensex", "link": "https://news.google.com/rss/articles/CBMitwFBVV95cUxOU3FBa3VJY2NZSXZiaWRtZjY5LVljTEFrZFVhZ0dUbkRQSldpOFI5RzJqVXZPLS10UmJhM0gyRVVaN2VPQ0hIUmRnM21aNXI2VGx2d19NNGJ5OWFUVGFZQ3c1Z1RobXprUWE1M20zeU1DSVhRSTIzZllCY3NFX3l6MTJtNmRETGRQSWhhZzBLWTRyMjFxWVhmS0JpV2ZlUU5kckFIMkR5c1RVYWpEQ3NpeV9oUlExcGc?oc=5", "source": "Zee Business", "published": "2026-10-22 07:16", "score": 0.273, "label": "Positive"}, {"symbol": "LAURUSLABS", "title": "Laurus Labs Limited (LAURUSLABS.NS) Stock Price, News, Quote & History", "link": "https://news.google.com/rss/articles/CBMiXkFVX3lxTFBxLUpXOHh3Z1BMOHZRamlZR1BuVGdaOVZLUmJSdkNiQ2dBLVZIWnhMbi1WMUpzUktaQm5pazNKdGFKMjZHNUdGRHcwWWd3U1Rac1c5M1RjOF9qQjVxY1E?oc=5", "source": "Yahoo! Finance Canada", "published": "2026-10-22 06:20", "score": -0.226, "label": "Negative"}, {"symbol": "DIACABS", "title": "Diamond Power Infrastructure (NSE:DIACABS) to Invest Rs 25 Crore in New CCV Line for 132 kV XLPE Power Cables", "link": "https://news.google.com/rss/articles/CBMi6AFBVV95cUxNNmRtSWFacEJ2R0ZvTmRsN1lUQkVuVmJSQ1UwcTJWWEVPc0FJNkRCbEFxeDA1ZXh4QTY3UUd4SGlYLVg5MG5UVGl6ZHJQNV9kSjdmNVhGY1NMWUNIN0ZOeWZpYlk1VG9iZHh2U2swVHg2S0xsMGp2ZGFSdGhhRVJBUnVSUnpQamQ2c3Qxckt1b0ZjaDR2ZHJQUU94bnMyNEZWSS1RZ2xjNTZUVTlaRnFLNGxneWR4QV9NUDJETS0xWTJhNkQtWUlkdkZsczZoN3E4VzMya1RwLURIbUlDRlJhN3ZhbmJXRlRW?oc=5", "source": "Kalkine Media", "published": "2026-10-22 05:45", "score": 0.34, "label": "Positive"}, {"symbol": "MARKET", "title": "Sensex, Nifty decline in early trade as power, metal stocks drag markets lower", "link": "https://news.google.com/rss/articles/CBMisAFBVV95cUxPUlZ0QjZMREp1TW4yazZUR1RfY0d2U1VZNnhtUV94RVdCdlRyYjdFSEZSS3o2V3ZWVERYa2lFM3h3aENobWhqQmliTy0zSWFxU2x0SzNUMC15NGpUcXBrWnA0TlJYYTNkVk5Hb3VkSXRnekxwdnpvXzl3Y3RUZXZfUTU4OXF5aW9MRE1reWtXcEJFbnpaVXZrc3QtVGxaWjZ5a2x0Z2VaeGV1WHNQbnFIS9IBtwFBVV95cUxOdUdic2ZlMjNoenFodkJlS0gyN0RFdTk3UGI1UlZiY3N2V3Y5T2c5dVpKTHlMZlR1aTZUaWNtYmRwZkpfMVV3ZjIyQ1NOTnAwY2lYZWVBZWJEeFRpS2sxc0hjdGVYR3JMZWFaUFlfdmd2R0NodVktMVJoQzVrNGFsUGlaZm4tYmluWEdOdlQ0X2ZWZnRIaFZ5TzZsb2ZUcnFiVVBJc3A4dmVGTzc0VFdNUVZfaGoxQ0E?oc=5", "source": "The Hindu", "published": "2026-10-22 04:57", "score": -0.382, "label": "Negative"}, {"symbol": "MARKET", "title": "Sensex Falls 596 Points, Nifty Slips 250 as Crude Rises", "link": "https://news.google.com/rss/articles/CBMitgFBVV95cUxQSDFSanZvc3JzOHE4MkxZZ1BUSW9WdnFGZ2tVamJJX09jb0JOS2hheVU0NFN2QlFocmFycjNaMEFXU1hlcC1GcDF2V2M3VnM5d2hmYUx4cFNGb1oxWGZCckpGcjV1YkpCa1c2aU1RRVZCRk14VkdOSTF2bWNVMDExTEFHU19pR09XQVdwcWRzMTZfY3RkbkVsTlhORjZpSUFTZDg1QjZUYTVIcTN2MFFVRDh5U2JZUQ?oc=5", "source": "HDFC Sky", "published": "2026-10-22 04:47", "score": -0.718, "label": "Negative"}, {"symbol": "MARKET", "title": "Sensex down 500 points today: Why is stock market falling today?", "link": "https://news.google.com/rss/articles/CBMi4gFBVV95cUxOakZkb2RoVENITm90YXpKRXZSU05UWGVtV0Z2WGhGMG1fa2JkSDFfcVB4NTR3ZjVqa2hWUzRUUGQtY3lLS2lYbW9PNUhnZE9hZXBHUGtWUnZVTmVQLVlQRElTdFNqOXhyQzU3azV5UWdKR201ejFvQXlwN19DTXhaRmJuSk1sbDFUYXFKNUtBUzgwTjFlcGNZeWJpRGIxWFBGWE5rejh3LUtlYWdYQm03TjFSR09VSy1ib01zbnN1enV3aWE1TG9ZXzVLUVVmSGxsbHdOR0ZNSXZkQzA3NEZwNDdB0gHnAUFVX3lxTFB1OXduRG1wSThoRXdCLTFWS1VuSW0wbGRteks2cHUwemdDOG5JdUZEaDljUE9IeFFGQU9pMUR5aHhqQnlZbmZxbWhHNUlJLWtTVFpZWGxGaG1ybi1zRlRidXpCQ0lwRml4NV8wM3gzNTI3Y0tJOVZEZWpNUXZ4dkF6bUYwM2w2N2FmS1pUZWtEbWdia1NsRjlpeFdDTWFjYXB6Z1FtZUpIVnhiNzFrNERTckY2Vmd4b1FsdXlERGJJYXB6bXl1aGxybFpJUmc3R1FaenoyMTRfUWFETFJCSEVmbnJpc21NRQ?oc=5", "source": "India Today", "published": "2026-10-22 04:22", "score": -0.153, "label": "Neutral"}, {"symbol": "MARKET", "title": "Why is stock market down today? Sensex drops 460 points, Nifty ends at 22,688 - Top 3 reasons explained", "link": "https://news.google.com/rss/articles/CBMi0AFBVV95cUxPcV8ySzdzNTZxT0NaYzdxb0RlZ1d0SGd3aTRvSDdQRGFNNGZIeUxfOEl5cDZtN0xsOWtOZ2RDNTlSTjBtT0oyZjRXYUtNTHB0QnNMWXpCZlBEenlQSFlPRkVhb0djaTdMcDNMNTJMRkhIU2k3Tmp3MTMybjZTSk1OekdmNng3b2JpQlhiT2tQbDlETEZ0YkZEOFNrZEpqdTl4ZDRMZEw0R0FOUnFIa2puNVZyVWN5QmRWLVR6ZkFEcnlSdjQ1b09TZlR6aTFYX2lu0gHWAUFVX3lxTE43bURuemx2MzU3eXVBay0zY3otTkRfekRrdC14NU5fS0tWcnkxSjUyVWl1RFUwUUlfMHlOckEwbGJ5VHpjTHh2RTJ1Ykg2SlpTWEIzZmpLbzhBbDZsWEU5UERhcjhRTERvMTZsZHlCQUpOY185OEpJZ0hreWZpbkd6Q2dnMkdxYlJUaHhIbUJxd3N0M2VRdXpvY0syTEw2bmRYLWVHUVNmNWI4UXl3OTBYUElWX0R4UGJzYWFaVlhnWDYzUVVNWHh2eThmNUNVTlpCYVpsMFE?oc=5", "source": "Livemint", "published": "2026-10-22 04:02", "score": 0.542, "label": "Positive"}, {"symbol": "MARKET", "title": "Why did market fall today? Sensex drops 460 points, Nifty closes below 22,700. Key factors behind Rs 3 lak", "link": "https://news.google.com/rss/articles/CBMikwJBVV95cUxOUHZIckFUQk9qdl9idHVTNjBSSXREM0hWdS1RbGlqOWhQZThXemVJazlRZUh3Z2Q1UHNhbERqN0IwWGt4SkQyd3ZfZS1jbEY0WElCdzM4MzI4YldXY2tObFM3d3F6YjFHMlRjVWJrSDBxVXpsTkVteHVqRE5SZUU2TjJuZndKUXRRbTl3MG54ZFdra3B6SHNCMFpGYWRGck1SZHBBLTJIN2lPem1iY2UwQ0dPSlA5ZjRfQU82QUJUYnFQX2tGQ2ptcENySHV5eWFJNGVGcFB5anF2MDh4M2dHNEVyX0E2VVowX21aUnpJcmhITVZQMnB3SW5EaXluMXM2LVNoUjN5WGpWcEgwY3hNYkpvSdIBmAJBVV95cUxORlFTY0FKNU9DYmhXUElDQm5JSHdndjAtbWltR2NZcjZxUEJ2ZzFwQTdiMDRQMG9WaFlfOUdrOTA2eXo5SXJRdGY1OWZxMWZIc09YVGdRQWI4Q3BveHprZGZOM2U1NnlCZ0NiUDQ2eG9oeEFja1BkVW5oZWZ1U2ptUHlibV8ydkREdi1QVmtOb2taNXRYcm1mVjJNS2hybXFGdzBxN0hvM2I3UTBHRnFSRWVTb2RJMWtwX0xZaXE2cFYyczduNVFqRjgtVEZVN0JXcnJpSW80SUROa3E5Rzd2QVpBNlVYSVNnTlNMbEU5NWtrQkhyMlQzSDd3WGFpU2NzWlprdk1EcF9GWF9IOHpRQVR5VmI1ejdY?oc=5", "source": "The Economic Times", "published": "2026-10-22 04:02", "score": 0.077, "label": "Neutral"}, {"symbol": "MARKET", "title": "Sensex settles 450 pts lower, Nifty ends below 22,700: Higher crude prices among key factors behind market...", "link": "https://news.google.com/rss/articles/CBMi9wFBVV95cUxQRzVaOTNoRlFEVldUMWpzckdZN2FXSTJLM1lKczdkUm5xMTZhTnQwcUlEbkRpaVd6RU1TZGhwVmFaLVNmcWItZHZJX1BpLW1HTFpaLVZqdE1FbjQyZklDNVF0MDBudi02d21uckwzNkVfZ1A0dVJ2QkhnZlFTMFl4ODBldnIwSHhWSVl3QlNnd3lqR0xNTUpQbzVRc2lsdnBaMHJhT2xBb2dtYlFEY3dZWHZhY0NwSHdBcU5MVzlBd1RHLTl0RFZLdVhaYVNhdHVGNUVNZkRfcXBzOG9Rc01mZVNGVzJIVkFBeDJucnJwdlVGVzVkSFdz0gH8AUFVX3lxTFBhTnRRZ19nMjJ2ZTRnaENHY25FNjFRSnZxZFhiczFFRWlSNUEzV182Q25sMTU3M0NyVFhUOXF0QXJBSVVSSGoxM3lJNm1ZVUc0clJhRzFWQ0hnWTJ4aGRDTkVEREc4UUduRldFaW80Z0RWRmpMaTRaTmo2YzZBNDhDaE5RWVEteEM5eXhpMjdsUXVPUWkwZmZmZW1CRTl5UUFtRnRLUG00Ui1BSmNRbmVsRUNaajhMcEYxUHVWX3pLOUl5eFJ4RmwwLVh5ZWFnZ1FKREVFWTVTSVpKX3V0UFlkV2swbzJLWVZRVEpxY2lsQ0JwWVhrYktXSFd2eA?oc=5", "source": "Moneycontrol.com", "published": "2026-10-22 04:01", "score": -0.421, "label": "Negative"}, {"symbol": "MARKET", "title": "22 October, 2026 Stock Market Updates: Sensex down 366 points, Nifty below 22,700, Power Grid drops 2%", "link": "https://news.google.com/rss/articles/CBMikgJBVV95cUxQeVl3ZGJ0NXlLWlUxT2lZaHRSdXYtOFA0c0tFMTNockJDWC1CNTdqQTNGNlZZRDdYVS0tVE5UWUtzUXI5NkRzbjF5SkZfOUlPdUprR090Mml2VWE5QmhjcEZsb1ZzdEs5TEtVZXlpYUdxNUNUbWlGVXA2T1VBYUxidE00MUtkNzRLQmVNZ0pzT3JvVkJxNHp5RkdUNHExbEFBSktGQXJyWks1WmtQclI0azA3eXNUTUppb0s2eXN4TFgxWTlySkVGNEU4UjNDcGRaVHpNYmF3aFlRcU1SQUpsM2ZGclhoV1VVdjRpbUM2UVI5THRMN3R6U2tfbDBfa241T000VVVFVWlnZmFPQmUwNlN30gGXAkFVX3lxTE9yZU1lUWkwWnFESjgxaW9YaGNycGN5ek43aHQ5WTlIT1FveWc5SldjLVNKNEN2YXZ1VUpiTGhaZkttWXJ5QThSYzRYNWV6d1d0Q1hldU52LWx4MGRiSEswcXlWUldJX0JlRkVjTzlYS3piOGQ4VmpzVkRBVl9qQ3lUQ2M2c0tkV3BwcUNPeU02ZjNlNFZ6QTg3d0dUMEJ5d2dUeGw4dklNellWOUozS09CWmtScTdQeHNKdmtHR2VNWGFjU0wtblRSTjRLakJ6cy1IeFEtR3MtOTZwRklMYkRyV0hBUndMb0MyaW50dThWeWIxMW5Cc0xyb2t4djBqcFY2dkdQUTRkME0yYncwdWlDZWtKbmVVMA?oc=5", "source": "India TV News", "published": "2026-10-22 03:56", "score": 0.402, "label": "Positive"}, {"symbol": "MARKET", "title": "Sensex opens 500 points lower, Nifty tops 22,600; Maruti down 2%", "link": "https://news.google.com/rss/articles/CBMi8gFBVV95cUxQZ0xJb1pXZjZ1Sk81cEp5SWtCNFlLRXpEU0t1c1NTWFZUeW52ZGV3dDcxbEV1dWE3OFhvZExQZmhuMWpTRlZlUTJISElycFVBOW8xX0pYdDNsUTlNXzVNRW5XUklIZWR1LUphcEs4SXo1enE3a0JKU3FzdGtSdlFPcVJrS01LNG9odjVkZE5NOVQ3d0RjZFJTVUQ2b04ya25fckdXeHZSVVNLc1pSMWVMOTJQeHQ0Sk9ObFdJbFRYdUZ3VkFJQWN5WThSX0EtMlhzNHpuZ0ZjQWMzVHZteHBNc0NXMVJablBZX2szb3R3OVNOZw?oc=5", "source": "India Today", "published": "2026-10-22 03:48", "score": 0.637, "label": "Positive"}, {"symbol": "MARKET", "title": "Sensex, Nifty sell off in early trade; power, metals, auto under pressure", "link": "https://news.google.com/rss/articles/CBMihAJBVV95cUxQZWMwQmlPa1NmV2pYNWRhdU5tczhmN0VfQjFxUEFfLWd4Q1NUeHhaNmMwZkxVdFhNWllMd2lJcE5FYk5yNzNzTG5HcWpBSXVITTRJNEY1a0JQQ0pNQVhnREh0NHBNUTBTRlo1VGJwR2JOYlBUWUVPajFwYTBtOGhsNVo0MEtueGJvVFFpYU5HRkRad2RYcVlaX0dDcU5aNWw1VVhRNzVnb3FZMTNDYldTTzhXcjRDUl84ZDV1V25ISXBuZVhkWTB0MUNodV94TDM0MU1KZEM1YmxvTUpxY0V0cEZKXzlOZkpsb01BNjlqOWJQU3ppTzRmem5DZTI4My0wX2EzUtIBiwJBVV95cUxONndNNGpXU3pfVVBDYlpQSzlEVjlTU3lXN2JBY0NCNnl3ZWQ2b2hGTW5lQnpiSWpJUnlUdEVMV2pWWFJWbnFDRXZjYWxzT3NfSmpyQ05ET1ZCSkhtUngzNEFCRVNmNTVwWU80eTZFdGhEak9hODMwZDVWYXNUNnlQVjF3Q0RoMF9leThrcVhWc25uSGtyOExXLUZMNURBdVlRZ0FEcXRLcTNLTUxxZVdaUWFmbTVDUUNoaXNzTzR3YmFzUC1JMlhqSHFHWFVUQXVUN0dzVkp4dS1raG5kamtzWlFOX1EtRW9VQVFpczlVUk1CbjRTOWtWdk5fOHNLQ05CcnVMZXZFd0ZkWXM?oc=5", "source": "The Financial Express", "published": "2026-10-22 01:44", "score": -0.226, "label": "Negative"}, {"symbol": "MARKET", "title": "Stock market outlook today, 22 Oct: Sensex, Nifty prediction - DJIA, S&P, NASDAQ, GIFT Nifty, Kospi, Nikkei, Taiwan cues", "link": "https://news.google.com/rss/articles/CBMihAJBVV95cUxPTnNUNUxNMmRjUi1QcjJmVHMzWWNHSEZZLUM1b285cUVHMnJsOFdOamVkejBVa1JEbEwxWW5kczRaSUVsd0JNVDZxQmRjUjRQOWlNYVdRem0yajNIVWU1SkFueWZrVk41T2FMcVFyNjNIdTBTYU1nYTBlTUstZ1laTUNYZEVUeE5PRGpOWHprUGlxRkdqNjh1OUlobGVZdUprdGN1em1tNnlEWXFYak1BV1A1OHFCTlJ1d0dnaUowUjlVczVWY3BsSkpvcjlzYVRNbHlkUDJQUjQ0ZkhCOXlkZFlrVGxucmNWVUtzWVMzY0dkeFFJWnJGZ2w0T3dzbXY3NFdTONIBigJBVV95cUxNVFFrYkdJRkdQcTB3V3FxZERqd2t1c3JlM2ZzWkZlYXNBd0lROWF0TVJudUhCM3FseTVSOW05MWZSS3BYQW55aVJ6cklYTHh3TkFheGRxUmdPQ3dqS0Vyenp4b1hGdnJrbGxCNnpzTGJLcWs3ZVVIUmFQMWo5VGhRSUl5Ymh1VHFxVlQ3WHZaZWtUMlhLcnMzY3p4bDdlaHAwTHBkLWYzNmhJVVBhU19VZHVpbV9UcXR4N1pSWWpoclFHM2pnc1lqWFFfUEYwQjAwWU1LZHVOYk1ad3VNVE1kYjhiU2hEYTJWUnBoTDF5c0hGcGZKdWc1YnJoTlJLcnpyMFpYRHp5MmdVdw?oc=5", "source": "Livemint", "published": "2026-10-22 01:20", "score": 0.842, "label": "Positive"}, {"symbol": "ACUTAAS", "title": "Acutaas Chemicals posts 70% profit surge in Q1 FY27 on pharma demand", "link": "https://news.google.com/rss/articles/CBMitwFBVV95cUxQNmdxX3hPMzJrejF0R0pvaUNBbDFacW44MXRuLXZ1bF9yVnlwTXFwWGlOZUh0U19XOTJhYkZ1cHJ6VkJSMkk0QVAzcENpdkNJWVRWMDhkYXJ0NUdxRjVnaVhiS2VPWExCMWdaQlBmVzQ4a0lhNlNjNnV5Nk9xcV9zOWMyc24wTFdBY3lCbFdQdXlsaWFNdnVxblZYWVhBcm5wQW11NzdmV01JeVBsQV93eXJuU0ZaTmM?oc=5", "source": "scanx.trade", "published": "2026-10-21 22:41", "score": 0.625, "label": "Positive"}, {"symbol": "LAURUSLABS", "title": "Laurus Labs Share Price Today and Sector Valuation View", "link": "https://news.google.com/rss/articles/CBMid0FVX3lxTE50NlRLX0hNeXphMTFfZTRycEtybmUtbWJ0ZXEyU2dndDAtZVg2akpTZmtPbjZkTkhLY01DRVB1eURzQ0Y5SVpwTUJpRS1ScWxMekpGWjJqYnFUbldKZWVMRnBZSUpJU3BRc29VZlBKV1VHS2ljcHZF?oc=5", "source": "Univest", "published": "2026-10-21 21:32", "score": 0.0, "label": "Neutral"}, {"symbol": "E2E", "title": "1:10 Stock Split Alert! L&T Backed Small Cap Stock Fixes Stock Split Record Date | How To Get Eligible?", "link": "https://news.google.com/rss/articles/CBMiwgFBVV95cUxPWmhhOV9UbzdzUnl1d3d3UWJ0WHdUVTFnVy1CRDlOaEtJRURFeG9MdzYwemoxblZHVFEyU3ZsSUpfd2R1QUVmRFhDakRUbWJvYTg1MVByOEtJZzhuZndaRkdHaU1BdGQ5bWVIMzRudUxYU0lvRk82UkFqd2tId2JMSDNVT1oxUzVPRWRsamprWWo2a0QxRXdGUUxhME03RWNTMmwwSmMxUkNkQS1yRmI0WUJ4X09BZWlTY2JxNG00X0Mydw?oc=5", "source": "Goodreturns", "published": "2026-10-21 15:18", "score": 0.624, "label": "Positive"}, {"symbol": "TDPOWERSYS", "title": "TD Power Systems Share Price Falls 4.37% on Price Action", "link": "https://news.google.com/rss/articles/CBMifkFVX3lxTE9hRVNFbXVSdmlBQjU1SjVINm42NjRkZEdJeGJGdktVNC1wbVZEUGJ2ZUJQVU5rX0VHdFhZUHRPdEVfeVllWWpqZXk2WEF2dFdFblViVi1aY0xRLUZoSEprUHFFb01VdUxSX1ZheWQxaDBFVWlYc3ZnenZETjhJZw?oc=5", "source": "Univest", "published": "2026-10-21 14:44", "score": -0.382, "label": "Negative"}, {"symbol": "MARKET", "title": "Sensex Slumps Over 900 Points From Day High, Nifty Settles Near 22,800, Know What Triggered The Fall", "link": "https://news.google.com/rss/articles/CBMizgFBVV95cUxQVTlZOG81RTVnWjBYRHRQMDIwcGZBeFctckxfN2w0bVg1ZFpDTUFoSFltOVA4MGdqT3N3LWhRdm96WFQyNHZTRG5heVUtRU5naDFxZ25mMEFYR1Z3aC1INkJ4RFBRQ1Itci1OSWpHam5aMl9zZzNnUTRjVlFXYzREZmFYVGVZd1RpRXljZTMxNFdQckJCeDRaQUZTSTROQmdLTTBHUHNic0I2UURCNjN3ekNwN1JULTAyT2NWYWpIMjFCN2FqQ2hPcUU5YmxMQdIB2wFBVV95cUxNM0tMVE80aXdoc254clRDZXlWUXdIcnAyMkVmajg0WlEyR01TVEVEeHpBbnhLMkVJaWJaV1M3Wlg3M2lfRURXR3UwWGNGX2pPdEJHSnp4R2stZzI5b0hiN0xDT0lWRno5cVhFd1ozc2xWbTZoMGxaVDhPOWFiT2JiSDdFSmpvWjZYalIyZTJDdlItSURqNjM0TjJFSnFadVBXWGNwLWNuejhuSVBaaHVSYXRQNUFqcUJHQ2M0b2wzZnI1UHR4TDh1Z3NwV1JxcDdvZXRoaTdpbVVfbFk?oc=5", "source": "Outlook Money", "published": "2026-10-21 11:20", "score": -0.273, "label": "Negative"}, {"symbol": "MARKET", "title": "Share Market Today: Nifty 50, Bank Nifty | Oct 21, 2026", "link": "https://news.google.com/rss/articles/CBMizwFBVV95cUxQX0ptQm9rVUR3WmhXT1hsYVFkZ1FDeXFBQ21Ma0hFU3N5Uzg5V3A4WW9ydXFNNW1BMFNRalB2V0NZNUZrMTB6SmlvMnBfUzYtaUdSTUt3emRnTjdZakRpRERJMkdiZ2lYX3hEQ2RRZ0pMamRYWi1RUzh3T0VwdmhkSXowNUtmcDRaYXR0dVdySHlRWjRFblRMWlJoZnBQZ3B6d05RVnA5b3BxeHhNal9xeWF3Y2hUXzhlVEF2SkxPSHlVOXVwNU1RWHpfTzl2bHM?oc=5", "source": "Liquide Blog", "published": "2026-10-21 11:12", "score": 0.66, "label": "Positive"}, {"symbol": "MARKET", "title": "Indian stock market today: Sensex and Nifty fall for second straight session", "link": "https://news.google.com/rss/articles/CBMipAFBVV95cUxPWTNFMUJiZ1Yta3hDU09iRHk1MFNNNVpUS0pOYzdMc1ZGcjZyU3h6aW5faVlJYlpVa1d2UHdKVXhmaWtXNFBwWlNRaU1HOEJ5dzlGWnZzVGZkNndOc2J1SVo1N2NLTHhGcTlOeFg0M3pVRE1qenZONFRtRjNEVTNONVgtSHdhaXllMUk5TThCQkI2SmR0VzhNRDFmX21zTjE4TjMzYg?oc=5", "source": "Telangana Today", "published": "2026-10-21 10:43", "score": 0.296, "label": "Positive"}, {"symbol": "MARKET", "title": "Sensex, Nifty gives up gains to close lower; IT stocks shine", "link": "https://news.google.com/rss/articles/CBMi0AFBVV95cUxOaWFxVEdUZElGaEVTNF9VTVEwVFpXUlRXcUZ1S1FTMVpIMnZVdFVJbTlqRVpvN056WXdXOEtfaHFDV2tXb0lvR1hrZERSMGFsUGdGYmtyemdiZmdoTXRkWHV4WWFWaWpSdjFGclVuaERMQ0xsd2pldlNfZGJudk9EZDc0QlNSa3JneHY1MUpIbE1TbVRoOEozY3NJbFdNYTJLZ1Jyd0hPMWpMbmI4NG5kUWRUZ01VY3FSTjExQ3k5VVBwSDhFeW5TMjZiblhsYzNG0gHWAUFVX3lxTE1YUXhCVEZnOTJHbktEQzZ6OWxrMzBibktwWGs0RWp3aGE4LW9LSHRkYlByYUpfaEVoQUphenV0U3pPc1BOSFA3cV83ajkxSkstTWZoYkdEN2pVT01KcmgtMWdBbWNBd01UZG54SmVHcFNpSno1d0dfZW1Qak9PeW1wV3hnbk1VdUczeXhQanhTQVZBOWZ3cTFtSmR0eEN0d25OdFF6VHdnN1lLYkVTaUZUYmRfdmVaUWIxRExPYWxwYkwwc1JSdUgxUGRqajkwbmxzMmtPRHc?oc=5", "source": "India Today", "published": "2026-10-21 10:37", "score": 0.542, "label": "Positive"}, {"symbol": "MARKET", "title": "Indian Market Rally Fizzles: Banking Stocks Drag Sensex, Nifty", "link": "https://news.google.com/rss/articles/CBMisgFBVV95cUxNUHl3Ri14Q0tHMjdZRll3TFp2cWs5bmNNV1huQWdmcUtNZVJ0c2NsRW9KaF83VEJSZUIzSldyM0M1UWhlS1UwRlM1OWptdUNCZHl3c3VGSHRqR3I2Zm1mRzZIS3ZfcUZ3WXRZNmF1RXlHMWR1alBnZkdMeDVtNnEwQlJ4UUw5dEdQSWFxUTN2bDlrMjlQdmFnS01IWGl3TkVIQXlyUVc1Q01Db2tMQUJvZjBR0gG3AUFVX3lxTFByT3lubXlZTHJfcDNQUE1JdkJVdmFHbGZKUDFWczlWQnM0bEM4c2RRdUkwOWY1RUpNUTVlYkJEbUc0RHVnSzFpcExqQ3owU21NN3lacnZWR1FLTGVvaURrdHNXXzBnUkR0OWZ6MVNtOXRfWXNQeFRaUVd3OTVDX2V5bHBab2ZWQlpWMUVwejc5Y25DWjROSDV5TmxVVkVjT2NpTEUwNkwwV3BpRGc1ZTBzNEtFWlZHdw?oc=5", "source": "Rediff MoneyWiz", "published": "2026-10-21 08:45", "score": 0.586, "label": "Positive"}, {"symbol": "MARKET", "title": "SENSEX, NIFTY erase early gains, tumble nearly 1% in noon deals: RIL, LLTS, HFCL among buzzing stocks", "link": "https://news.google.com/rss/articles/CBMi6gFBVV95cUxNR3NxdHRtWnBVMU9TY3VqMXFkWldrVzFCUmJfNkg3ZmZOTHNVYzZMWGFEalgyZlcwVjYwcUhXaW96Z2FsQmtPX1dUUjR0aHg4YXNpeWUxM0RKcndCUkhta3hJRmVINDA3RG80MVR0N2lyUzNUTGZIb0FqanZZal9YNmFpa3RGYTBjUHBoa3o4bThNS0RBaVVXSXVhbVpqZFJzMTdoOVMyRjhnNGkyRGR3NTgyUGV3Yk1NTjhmMGd3dlhVV2JUXzhYNkdlUGI3SUtZVWlFUVpza19tSW5PMmxiV2RpT1lvV3F5VVE?oc=5", "source": "Upstox", "published": "2026-10-21 08:27", "score": 0.721, "label": "Positive"}, {"symbol": "E2E", "title": "E2E Networks shares extend decline for 4th day; Black Box, Netweb Tech, other AI stocks see rub-off effect", "link": "https://news.google.com/rss/artic
A5: les/CBMi_AFBVV95cUxOQ01EUk5uSmcwT2otWHpCcXNKUkwtQk1Sd0IzZ1M5NEloaTRfMUwtWHdTZXd5TTAtZEtwb3dRLVQ1dWgzcmY5REU5eDJhMEFpdVNMb3d1UHZjQWlOcVRYNjZKTjhIYW03bVVpRjZ2ZEZ1WmtUMnBQUWRQZ3pucmpwNzJpOW93eDVvUGQtZG1WWnJVNV9GUGFIeG9vbUxYSGtKdjZrUFlKVkY1aHpmNXlhVTNCakx1TVNIZHA5NXVFSUZlTmpGLWZ1a2lqcElkdTZXSkpXaUIxSnBMZ240TmFlSHFHOGREaFhhUEp5X0pEMUo2TkFwWEU5V1dhUGnSAYICQVVfeXFMUE1JaVNFclVONzVqZElTQUp6cGxDaUE4b0h3ZVpiNnJkVE91eWN0TWlheTAxaUZCdG8ybENYZ2V1cUd1a3JORXNBblpkSnRKQVYwd210ejFWbThnQ1pvek5mMml2YzVQWi03bm0tbUt4a05HYmFFOXdvak9YcGRBXy05ZElWcXpOUkRHb01aR1lxVU1rYXFqWVZIZHNJTUswblYxUC15Y1NRNjJlUTFSdjF6MVJfVEMzVmxWOXFZSmI3WV9xbnd6clU3X0IyVFVzWFhJRm1MQ0p3ZTFxRW5FYnBoOXFXR1J1ZWozMVhSWXoxd1FXLXE0NUxGTlpIME5RZFdR?oc=5", "source": "Moneycontrol.com", "published": "2026-10-21 07:23", "score": -0.226, "label": "Negative"}, {"symbol": "MARKET", "title": "NSE - National Stock Exchange of India Ltd: Live Share/Stock Market News & Updates, Quotes- Nseindia.com", "link": "https://news.google.com/rss/articles/CBMiPkFVX3lxTE15aFBDQy1lOHpHNnVLU3dRM1lsWmNDMVRQNWJPcXBDSklxT1VIUnVxVDMwRHJsRTJtdmNLcEd3?oc=5", "source": "NSE India", "published": "2026-10-21 07:00", "score": 0.0, "label": "Neutral"}, {"symbol": "MARKET", "title": "Sensex, Nifty rally up to 1% in early trade on IT stocks, firm global cues", "link": "https://news.google.com/rss/articles/CBMizgFBVV95cUxQR1h5dTg3cEs3Sm1JMkptS1p0OE45SVlfSWJnd2w4c0U4QS1TR3VxMmhPVW9lYmZLQTNhX0FzOE1ZSkM5b1RweDNMUzE3LWJldFFNNEphR0RQa3lvUkZJSENnRW1PNnk2MnRsNlNocnRRNG5YZmNfdXdGSVFOdVViemJKS1ZsRzZrcWVGS201SlVoQWNrc2FWX0JoVGFkbnFKNGdUbHEyMW8wLThTMmdVeUFoNDBaRFp1Zm90YkltYUFnNk9hbHdVaVJ0OVpWZ9IB1AFBVV95cUxQNUVZMGpnaUtWa195QW1MaUFiV0RjQjRXdVR2QWN2am40Y2VsREVYVU5Rcmhrd2NQQ1d6dzJrMi1QMUlTdlZlaGFGekJ1a3lVMUNYamFabWFwbUVKQldnU25vbHFsejMxam1TZjRiR0FBZjNCOGZBUkVQbllGYkhQU285WkpvYmFuYllkOXJGN21kUUV4a1VVME43dUtqT0pKRlZ0bFBrRzhsM19vdDdMaTNMbEppMUdXT1RqczlGaTJaREdEcVBxNEJPclBQMm9RS1FJZQ?oc=5", "source": "The Hindu", "published": "2026-10-21 06:26", "score": 0.691, "label": "Positive"}, {"symbol": "MARKET", "title": "Sensex, Nifty Jump at Open as Asia Gains; Jio IPO in Focus", "link": "https://news.google.com/rss/articles/CBMi0AFBVV95cUxQUUk0eU8tSElYNTBybC1oZkt6Z3ZUV0ZIOXJGOU9maTg0ZlM5b01ZcVJVOTlyNEtaZzk2YWJzZXlEa0JLdlpubS1BdlkyU1RmUnNuZHY4SF92T0lZbkRScUtEX2ZwdzMxNW5jeWQwd1ZFeEoxazRIdV9sWmVYNHhkNGdGMGFDS2h2eC1OYVIwVkxhRFoxQXJkQmhRRGgzT1BIUk5EY1gwQlM4Z0dPYzkzbm5EckV1MVM4NGZ1ZXc0V2pFY1k5bDhWai1OTGx4eUs2?oc=5", "source": "HDFC Sky", "published": "2026-10-21 04:43", "score": 0.796, "label": "Positive"}, {"symbol": "MARKET", "title": "Sensex, Nifty jump as IT stocks rally; Jio IPO in focus", "link": "https://news.google.com/rss/articles/CBMi8AFBVV95cUxPd3ZveERnLUZvSF93M3JqNXFNUmRMRVJ1eTZESTBxYkQ3QXZlNm1VV0FfRXI1N1NfbEhjZWMtT2RJMDMxaC1LNmdEQmFWT1RGdC1VdjF1amZXT0c3ZFZwZEFkYUF5UlM2cVNVbmdRZ09rUnhETnFSOWM5XzJMZWU1Q3ZoQ05kWDZKbzVGQ2FlMTFibDg2VzJORDNKcFYyZENHUHZHbW5WZE5zZmZQbzJGd21URDlVYjZ4Ujk2ODlHNjhENmZNZ3daM2pCVDRnekszQkotQ2RHSUFPNVUyR0wzSXFScEc0VzhBaDZNZDdaczPSAfYBQVVfeXFMTklzeGFkN1RscXY3b0lqYkhOenFwRXEwSFUyVFpaeVFTX2Fhalc2T1JsOUIySFNDbHlxQTVBeU90OG5WandWTWlVd1p3Y2NYQkV6Rm5JaWNSMDhkeFpvNkNqQnJiOXgtZ3FaT2JORnRBNm96dGwxYmdFaWNtS1pXYWFfRkdEWEZ5OVdNb1ZwbWQ5RGlSbkQ4U1BEQWM5SzlsMDVuMUpCX2Q2cmFRZEJVX0FxVjhJYXBkZmVpYy1hVXVGRXhMOUNxVG12RkE0MGdkZFBwQUhrY3dKVlZpUmxCaDNrUUtwSE92M1JqRUN4Vko1bHRZcmFR?oc=5", "source": "India Today", "published": "2026-10-21 03:47", "score": 0.818, "label": "Positive"}, {"symbol": "LAURUSLABS", "title": "Chartist Talk: Will Nifty 50\u2019s technical rebound sustain? Milan Vaishnav advises holding Laurus Labs,...", "link": "https://news.google.com/rss/articles/CBMiigJBVV95cUxQX1VFQnVWTVpjTEJwOXpaWUkzaEFlQ0Etd3BQU3pSdTF3enVMSndzQ0FlMlN5UVNpNXFENEFnSjdDYXV1RHZ0U1BFTTBwekNLWFV1Qm1XTy1fb0dDVlpmVzRYdl9TVzVpTDVoak5MM29qMnAtZnRNWHBNQW9kYjJILXNraU9Dd0VGVUVqQjhMMjZvZjJKVmhpby1KWEp5NXZXaENEUGtwa0ZtZlRMVU5MZGt0R2I4VEJkbWdLaXFsUXcxVkZJQ041MEdTTDJCN0xUaVlyaWg0TmllLUVvWjhKcFg2em9JaHFWaGNUNjhYVjlUcWtDcmhvc3otVk9sTUdCT2Y3LWdUbVZoQdIBjwJBVV95cUxQb2E2X1V4MkpKTnRhREpxZDRBYllSaHVwY2NmQVZkMnFNRUcxY21SeG80QmpIT2d1cjdjaHJMcjV1d1AtcXlqc2ZSbjVFOVFjN3MtT05Ib0xvc1hPOExQakJ2c3hkei1aS2lUMUxZTnVWX2ptNTNuY01qVUJfaFlxcDVjTkcyd3BIb0tQNHY1am9oUThfX0taTWNzZDVuR3U1ZlExNHppLWRQNU5ESXNRWVIwSFVTei00Q1lDUE1XVFlpM0R6aU5KQ2ZYOUo0N1NSS25McHhXS1MxRmplZDhxREVrc1lCVEtKR3E0QTVaUWlYcEtfeE93NEpNSWV0T2lnYVgzQkFXZTRGMHI3RGNF?oc=5", "source": "Moneycontrol.com", "published": "2026-10-21 02:34", "score": 0.402, "label": "Positive"}, {"symbol": "DIACABS", "title": "DIACABS.NS (DIACABS) Share Price Today, Live Chart & News", "link": "https://news.google.com/rss/articles/CBMiYEFVX3lxTE5JV0lHeHF2MFVvUUczOUVwMTlLcGJQZ0ZGNzhBaUtlRDBtUFB2aVpCQ1F1WExTUGYwTTZBcVVMNkVHY3RBLWhRUHQzSExqOTIyQms5WV9sN3JyRnQybmprXw?oc=5", "source": "TechGraph", "published": "2026-10-21 00:00", "score": 0.0, "label": "Neutral"}, {"symbol": "LAURUSLABS", "title": "8 Stocks Hit 52-Week Highs: PC Jeweller (NSE: PCJEWELLER), Sky Gold and More", "link": "https://news.google.com/rss/articles/CBMi6gFBVV95cUxPT2tpMEx5Rmc5cVQ2aXlMMXZZVmxpNXYtQ0tqNWVtS09Id0JCcmRBS2lUV1MxM1VtbkdtYWNuZWJ0VFhncVhRcEtTYkJsekFxUXlSaGVDeW5Pa3QxM2V3dGtZazZaUHd0N283UG9zOV9JQkR0LW0xWHI4VVZvVWlUNnhVcC1nWWVUdGUway13dVhjSHc4MkptMmg4MzczRWxxSUh4aEhJWWNqbmZHaE1aRGFFWHRNTnhHY3hLYldKdnZwZHhWSHJLVUFXc3h4eU9kMzVMdmF5SUtiSzIxT3k0eUF0VmZEYlBodEE?oc=5", "source": "Kalkine India", "published": "2026-10-20 11:24", "score": -0.153, "label": "Neutral"}, {"symbol": "E2E", "title": "We Ran A Stock Scan For Earnings Growth And E2E Networks (NSE:E2E) Passed With Ease", "link": "https://news.google.com/rss/articles/CBMi0gFBVV95cUxNZkY2dmdRZHEzVFptTVlQTS0xalRUWm1PY05FeXFkSVFnVEN0SVE2UVFicnFyaXdJbFlndUw1Y3lmdlpoMFowMk9HdDBDOE9jM3QyLVI5Y2haU09oc1p4U09kOFdKLWozQ2ZCbjJwamh5TW81ZlNoQTBkamVSbVJMWnBJaGVnODRWbk9mVmtpbzNYWXhncWZJS3dZanp0ekJXTXhNR1ZOVDZYekYyZzdzdmFtd2ZBYndLb1pINGtOMEFWZXVnRkpGSHBzbHY2TmhmMEHSAdcBQVVfeXFMTWRheF9vX0E2QUZEdVluYkllRWRIbEFXTEhzMm4tMmhCSGZrXzFwYlFKNDNlQ01CSE9tNHF1dGRSSWpqSzJiLXVEQ19MeTU5aHpYSFNHbzdSRmI2M2c4ZmZLcU40cGZUNmZDY000d3lmTGl1WjNLT0RmSkdBYWZRYXpMcU9IZlA0a293ZV9OcTBpTTBnb3lfRHZIdGF0WEo4UmkwaEFWcW9GVlZ5YnVFa1pOMUo5bTNTaHpJS3JzcmhvUG10OXktWENsZ1l0YUliNWRpdXlGMm8?oc=5", "source": "Simply Wall Street", "published": "2026-10-20 00:35", "score": 0.612, "label": "Positive"}, {"symbol": "LAURUSLABS", "title": "Laurus Labs - PC Jeweller among 8 stocks that hit 52-week high and rallied up to 42% in a month", "link": "https://news.google.com/rss/articles/CBMi9wFBVV95cUxNT0ItTTgzWFNXNlcxeXFsdzdJTldjZWQ0WWdveGtaTHVzcERHVzBFXzBLdVZqM3VLaFN5a0EtZWtLYVF3WWw4ZzdUUG5SN3M3b09KeG9RZzNZMFRfb3N6SEs0djdrQ1Y5MHVJUnpJUF9Fcy13MDNZbDh1UU42cTkxd1VyOVRzUklWOTV1b2ZXcG5Ia3hZUmhHUlFrUTI2TGktd2E2enN1dDBGVWVNaExuMFRLT2dMMHVWUGdMQ0NPTktnVk1MV2huWTVfOWZfQi1nMVMzOWFtdTBkUWxIenNDbTNuZ2U5TjVrTXFxMjBMcmV3WVhnQTRR?oc=5", "source": "The Economic Times", "published": "2026-10-19 14:13", "score": 0.052, "label": "Neutral"}, {"symbol": "MARKET", "title": "Nifty Sensex Today: Stock Market Crashes as Sensex Falls 876 Points, Nifty Drops 1.11%; Banking and IT Stocks Lead the Losses", "link": "https://news.google.com/rss/articles/CBMi9wFBVV95cUxQa1ZydU56V2ZLWkw1MTV6bW0zNThMcTRUVU44WFN4SHpfMHlmTndYMm9YZXJMVmE3V0w5S05ZU19Mc2F6Z1drT05NOG5vQzg3X0diWkh0eFV2dzhkMzV5WXVlbEYxaUtiY0RmT3B3bGVMWXVCTHRNdUloNzctX3d2eEdPRnlZaGp2eUhkQmhydkNwOEl4cFdiNklIYnc2ZjZUQ3BhZlZlY05Hb2dFVm1lS3B3M3dlb1NqM3BEQ0xtaWtfY0pNSlIyRkQ0MzR0ZGJLQkt5U3R5S3FDU01saE1NdGxwRXQyc1d2ZDRldE5wbDNRTjl4aXBv?oc=5", "source": "India Infoline", "published": "2026-10-19 13:06", "score": -0.0, "label": "Neutral"}, {"symbol": "DIACABS", "title": "Diamond Power Infrastructure (NSE:DIACABS): Who Is the New CFO Appointed on 19 October 2026?", "link": "https://news.google.com/rss/articles/CBMi0AFBVV95cUxOQjAyWlFlUEZVVkZEek13cTE1OTRTNmJaLUV2X3pIbHJZOHFod2JPa2toTGQwaUFVVzhXcVIyUGV3NWNpb3lwaFV6aVJwc3p1Z0pqYVJTamFkWDFBLXdjdUlaRUR1dGtvOFpMQi1Ic2NhN0JxUGpmcFA4NVVqbnRBcEVrYzZtNldFY2RvMVRJaU1oN3V6UElHOXJ4MG5tVWFtem5QM3RZM2NtYmEzZVVvZ1lZRk05ZE8tWWViM2FxSUNfM2c4LWEycTM5ZGRPSVNr?oc=5", "source": "Kalkine India", "published": "2026-10-19 12:29", "score": 0.34, "label": "Positive"}, {"symbol": "MARKET", "title": "Manic Monday at Indian stock market: Sensex, Nifty bleed - \u20b93.6 lakh cr gone in 6 hours | What went wrong? Big reasons", "link": "https://news.google.com/rss/articles/CBMikAJBVV95cUxQWGYxbjJtM1hTam1JMFMxZXlUaXk1VDltRkVZc0pwelhEbUJEeDNKM2lWVXVEUExUSGJxdDJCaUNTd250a2MwXzVscE1fR2w1N2ktZVAzd3JqRDI2YmJId1JnVU5mX2Ixd3FEUWxNTFltZnlRUUdyWXY5X1JnWFRlQ3RldnJKZTFmenpxVmZRZVVESnAzMEU4eEdFYU8yd0NGYXpYZ01pUldYdnoyWjlXXzBUQk93QmJzSlhtRW9UdzVXTVN6QkluUUk5WkdiVVMybEtVVldsOUhGcXFNb1hHM191QkxWX3dNeUFSdG5ZcWl0NzVXTnlUV0JhMWxaMXoxRW9lNnRla2NxaTRsSW1IU9IBlgJBVV95cUxNVVIyNVUzY2lGS2EtUGJ4ODV5T1NCYldQNXAxd1dJY0dLSTl4bzVDVlNhODRpZlJDMmJqOGhsUHEtTXpwWktvZFdtbTVzaTZsWFk5N3JGNWNTNl9DY0FJdHB6SzdOSkNxNXVrTnFxZjJlZUJFMXhja0wweDV6Ulh5T0N5aDltQ21oTm1GbUxYTGw1OEswZHBTbUUzWWdwTEsyeHllUWlnV040b19HbU9QOVlaZi1pNmRDUm1rQ0g1VjZsR012d3AzX3FkblRBVm5kc1BYX2Y0RkRZWVJNNUhKLWVSQmtLWlg4ZEh0MmdNRUJqRUxHUUxqUUtsd1NKQnNOSllhcmxkeTNxQS1WNVZxZE9KSW4xUQ?oc=5", "source": "Livemint", "published": "2026-10-19 11:35", "score": -0.103, "label": "Neutral"}, {"symbol": "AEROFLEX", "title": "Aeroflex Industries Braided Hose Design Patent and CAD Technology Explained", "link": "https://news.google.com/rss/articles/CBMi0gFBVV95cUxPV193MzZqa1duYVcwVGs1UmdCX3JuTE05QXBZVERzU0Y4Qkgwd19kNUlFdy1LbWVFNll5QlpqTmpacF9ydGFhWGZMVFA3M0Etd1RYa1g3R3E2QVQ1SXhETDhIODM0OG9ZNHpWdHFsZElJN05CcV9vVGFIcW1UQUZKbDdDTmpjRjVpTHpUTGY3a3NQczIwb2VFaFhCOHFCM2FMNm9DMWloeHAwbmtzQm5NcnZWd3pxbGFwR1VjMkFObm1YRWVQVjVoU3d4WVB6V19zakE?oc=5", "source": "Kalkine India", "published": "2026-10-19 11:05", "score": 0.0, "label": "Neutral"}, {"symbol": "AEROFLEX", "title": "Aeroflex Industries Ltd granted a patent for its innovative technology", "link": "https://news.google.com/rss/articles/CBMirwFBVV95cUxPWkFoVnJudVByWHVCbS1fRk5TaDEzV2cwbklGU3hEbFJGM3M0cWhudmtIeVA4YWlfekNicFhyaTdDNHpQbWZiblRiX0RkanFJaVRlZno2QlhOUVNRYWk0RG5DY1I3NDZ5ZHBuQVlrT0t2NEhRcHVuaWUzM0ZubmpmWkxuSWExekZCR0w5RTN3QTZULU5zX1JwQVJvdmxhYmZGN1VLOU8yR1NhSGZKT21r?oc=5", "source": "EquityBulls", "published": "2026-10-19 09:06", "score": 0.599, "label": "Positive"}, {"symbol": "AEROFLEX", "title": "Aeroflex Industries Patent: 3D Braided Hose Tech Granted", "link": "https://news.google.com/rss/articles/CBMiwwFBVV95cUxQaXNlZmlYVkVyMERnTGRiNjdSVUhUcDQ0QWRQbUlNTExWajBiNUtERGRsblZibkpXRFpyOC1GTVdyTEg1MTZVX2laS21MYUswS29Ub2pPRGR3aXFJVDR5dURYM1dMeDJHU1pNN0FTTkJ1aGh2TGJGVkVSX2tkcXczaDZtRm1xQ25EYkJIdnBxU1RFS3BkYzAtX1N4MmZEeGtYbmpRNjV5OGctUHlmLXhjTzRaUGVlVjNYS2VDOW5PMHBzb2c?oc=5", "source": "Kalkine India", "published": "2026-10-19 08:10", "score": 0.25, "label": "Positive"}, {"symbol": "E2E", "title": "E2E Networks AI Cloud Infrastructure and GPU Services Explained", "link": "https://news.google.com/rss/articles/CBMisgFBVV95cUxOQjVNam4yMXFWbnEzQ0ttOXpNWmtJR2xuMTlBemFzbGViRkUwOVByYzNCUGJVcGxJd3p5eDNWNkh1WG9CeGxfSWN3a09YbnUyRTBxazY2TGpBajZLUnBRZ2V3dHlzWlRHbTh5XzRfdVBTZklpbW1MNlhkWTBwd2ZjLUE3RXNqYlVHWE9hdHZFbG5ZNU94ajM2LUZIMVBoSnV2bHgzRG9wOHBtUzhGRnhwVGtR?oc=5", "source": "Kalkine India", "published": "2026-10-19 07:40", "score": 0.0, "label": "Neutral"}, {"symbol": "LAURUSLABS", "title": "Laurus Labs zooms 128% from March low; hits new high in weak market", "link": "https://news.google.com/rss/articles/CBMi3AFBVV95cUxQUzRiZktZNXRkdHoxamJxZzlTQTJMYURYV01memJpSW5fQXJiQmwwNk1pOGVacmpsNWNIaExZbE1jQWxlWTFWdmxxR0swbWhMSWZQZ1dJRGNvZ0FyMDcxOGlEbUM2bXctOG5KcW5TVTFoVWt3VTZzRWtrZzQ4c0dGNDcxUE9ELUk2ck5vN0hXZElEVXhhd2lROVZVd3UwUml4U2xCNmVhVkt4X01ZTC1talB3VF9fMW02dUJLcldLWk5iR2dSOHBGVENXR1E4TXdLQVlvZ0RzVTBPZzR50gHiAUFVX3lxTE5SU3V5TUIxcktuai12Mm5LR3pEZ2J0ZEdIcE1ld2VvT2VJQno0ZVhTOU9YV0hCN3hCUk9Za1Vhbm9jNkY0eUtkUmJVOEYyd1NweTlNYjFILWR0TG52LXJ4SUVRTUhzdE9Naml0UmFCNVVUSUpESDY4UHN0Y0dJM1BMYzRwVlVEdnNyZXhBVEc1X1dQeWJOXzFra1ZYbXkzcHJkejJjeDZyLS1yZ180LUxXYlNVMHVhSGZXcjhoYUJ3eHcydzFCSDhkREF1NjZJMV9jVVlFLVdQcWMwaFhtNk9JWWc?oc=5", "source": "Business Standard", "published": "2026-10-19 07:20", "score": -0.542, "label": "Negative"}, {"symbol": "KIRLOSENG", "title": "Kirloskar Oil Engines Share Price: price fall and valuation", "link": "https://news.google.com/rss/articles/CBMihAFBVV95cUxQVTBCYlNyeThHejZrRTVGVG5VTHhVZ0VFUUUybnZDRGtKSERtZ1laVGN1RGN4cWdVMHlQYVFmaElKR0RCbkxwVWtfdjE1OWFQNllYXzJjd01SS3pNZU96UU5GNkFjeDZkcVYxdHotUzYyWm9LOGM1WVRUSGF6YTVWMVluSm8?oc=5", "source": "Univest", "published": "2026-10-19 07:00", "score": -0.34, "label": "Negative"}, {"symbol": "LAURUSLABS", "title": "Laurus Labs Share Price: fresh 52-week high and valuation", "link": "https://news.google.com/rss/articles/CBMihwFBVV95cUxPTE5xQzJmMk9oR3NOTmNLUFZRYUZkZ1lDZXVoTWt1a0dxaEdVYnBzT0YySXE2ZXZ5VlFER0taX21FVDBudG5PQXY4MWNtZk0zZWl4a2l1clZQUmw4SWlfT21KdDJLTkFMVWtOckwzZmlSRktvQVMyd3dTWVBiVDZNSFFtbjE0cmM?oc=5", "source": "Univest", "published": "2026-10-19 07:00", "score": 0.477, "label": "Positive"}, {"symbol": "LAURUSLABS", "title": "3 Top Hyderabad-based Stocks to Watch for Future Multibagger Potential: Divi's Labs, Laurus Labs and NMDC", "link": "https://news.google.com/rss/articles/CBMihAFBVV95cUxOYnZPOHBWT0JBbGkzbzZ2dl9xOGNDZ0dKSFR4V1YtbENNSm1IaUQwb0xmRkZnd0xFNFZ3bGdoQXNUTERBblFjZ0NfMTg3aS00YVlHY3I0cnFiN2dpem5aS3cxMVRIYzVDV1VxQTFSWGZXWFZFS3VZQ3dFeGpLZE40elB0Qko?oc=5", "source": "Univest", "published": "2026-10-19 04:51", "score": 0.586, "label": "Positive"}, {"symbol": "DIACABS", "title": "Diamond Power Infrastructure (DIACABS.NS) Slips 3.28% to \u20b9361.5 as Traders Watch \u20b9343.43 Support - McClellan Summation", "link": "https://news.google.com/rss/articles/CBMiygFBVV95cUxQb0pTQ2ZFdTB1dnA5Q2FtZlAyamg4RWtXZlRQMkRJR3ByOTNaTEs4Z2tKMmZRZkpEdzBGcXBaV2steFVDcFdKWkZKcE1oS19CTG04QVpDaFB6dVhfdVN3X1h4SjVzSWdsdENsZkVHclpfUlJ5RjNJTFZ3b2ZQMUhVUmNHdG5nbTB1OS1GVUcxaDBKd3VVb3JjSlJLellHYkpKaUhIXzg5V2E1Tjl4TW80U1Fic2ZSYVF5RnI3Z0FEc0ZVZ3M4dC04SVd3?oc=5", "source": "www.siam.in", "published": "2026-10-19 02:34", "score": 0.402, "label": "Positive"}, {"symbol": "E2E", "title": "E2E Networks Publishes Q2 FY26 Unaudited Financial Results", "link": "https://news.google.com/rss/articles/CBMi1gFBVV95cUxQbDYtY0FjTy05eDRrUjJ0YlVHZjNsUW14ZFlaM2p5UmdvcW5JV1FpT3VrUDVVNDVDV2kzVjdieXlCTm1XaFYxWmprU21kYndPNWlmSmVIN0N6cGNiWlE3TzUyUDBobGJUVURBZWdmbjFVRVF1SzBmc2xCSm9jVjJ1TUlmZkc5RENPRDlPLXNSemRLVjBkWUh1WW9VQU95WllKWl9JYzIwSXl3M1hjQ1pZX1h4ZUs1Z192NWxVUl9DV3BhaWpGSGRIcnQ2dHFCdGVqTVQ5VERn?oc=5", "source": "The Globe and Mail", "published": "2026-10-18 09:01", "score": 0.0, "label": "Neutral"}, {"symbol": "ACUTAAS", "title": "Acutaas Chemicals completes acquisition of Enchem Ami Organics", "link": "https://news.google.com/rss/articles/CBMitwFBVV95cUxNMDVaazJFSUV2alBkdW9fZ0hROEdaZkdfdVFBdWF3cEFIZ2dBdGgwdzU1VFF6MkFKd0xHTUhUWkxGelZEZnlfajJZM1lSMGR6blR6M3pVTjcwaXNuTnRUQUotcDZzQWFMOXptTGtENHZVTFBUTlg0TzVDaXNfS1dFakpMeWM5SHlYaWVRMS1JazBoeVVYempvNndFVmJpV2FnZ3JuNm02cGNmdV9mX0E3ZjhoeERqMTg?oc=5", "source": "scanx.trade", "published": "2026-10-17 09:58", "score": 0.0, "label": "Neutral"}, {"symbol": "E2E", "title": "E2E Networks pays \u20b910,000 fine to exchanges for compliance delay", "link": "https://news.google.com/rss/articles/CBMiswFBVV95cUxPcmtYR3dlcWdXU1lkZlc2XzJzQUU2N3IwWEZEejd1c3c2Y1dEU2M5Y3hOZWh3aHF0ZUpGY2tvU1lYVEZXbFNRUkl6ampycXh3Y1JZRmh3eDkzTUtqTnhWRnF4VlhZU1FycDdXaVNvWGMxT3ppM2lmVUZiSnYzSGk3QWRLZUdLcnlPYXdZTDZPSVkxOHZLLTFvbXZMR0lsQmNTcXpSWVFmWHc3eTVSNXVsM1ZQbw?oc=5", "source": "scanx.trade", "published": "2026-10-17 09:32", "score": -0.128, "label": "Neutral"}, {"symbol": "E2E", "title": "E2E Networks Ltd (NSE:E2E) Q2 2027 Earnings Call Highlights: Revenue Surges 411% YoY on ...", "link": "https://news.google.com/rss/articles/CBMikwFBVV95cUxQTGY5bk82SXRsTUdRWldyX0FMNE9heHk4NHRjTFBMOVJzcWZYamVaRHpGaVZNZ0s3WV8tMmZUTzVLZlhXZnBsemtZMm1aeXFGZUM2RmM1eEdRdjk3MFNlX0ZIMV9aRktwdHh5cF9CTE1lR0IxMkhUME5femU4Rm45UlBDOVlVdUZsMjZNOGt6YjVmRE0?oc=5", "source": "Yahoo Finance", "published": "2026-10-16 21:00", "score": 0.494, "label": "Positive"}], "errors": []}, "created": "2026-09-28T13:27:26", "last_updated": "2026-10-23T17:22:28", "research": {"method": "notes", "generated": "2026-09-28 13:27", "title": "Stock by stock", "stocks": {"TDPOWERSYS": {"symbol": "TDPOWERSYS", "name": "TD Power Systems", "view": "Bullish", "view_score": 1.5, "tone": "bull", "summary": "The stock is 10% below its high, a shallow pullback within a strong uptrend.", "why": "Guidance raised, shallow pullback. Check for a fundraise.", "points": [{"text": "The stock is 10% below its high, a shallow pullback within a strong uptrend.", "kind": "context", "source": "", "url": ""}, {"text": "Q1 FY27 revenue rose about 72% YoY.", "kind": "catalyst", "source": "5paisa", "url": "https://www.google.com/search?q=TD%20Power%20Systems%20site%3A5paisa.com"}, {"text": "It raised its FY27 revenue guidance to \u20b92,600 crore.", "kind": "catalyst", "source": "fyers", "url": "https://www.google.com/search?q=TD%20Power%20Systems%20site%3Afyers.in"}, {"text": "A board meeting on 14 Aug was set to consider raising funds, so check whether a dilutive QIP is pending.", "kind": "risk", "source": "5paisa", "url": "https://www.google.com/search?q=TD%20Power%20Systems%20site%3A5paisa.com"}, {"text": "Valuation is stretched (P/E around 70).", "kind": "risk", "source": "5paisa", "url": "https://www.google.com/search?q=TD%20Power%20Systems%20site%3A5paisa.com"}], "short_view": "Bullish"}, "AEROFLEX": {"symbol": "AEROFLEX", "name": "Aeroflex Industries", "view": "Bullish, high risk", "view_score": 1.25, "tone": "bull", "summary": "Q1 FY27 revenue grew 72.4% and PAT rose 162%.", "why": "Strong growth, expensive, volatile, thin liquidity", "points": [{"text": "Q1 FY27 revenue grew 72.4% and PAT rose 162%.", "kind": "catalyst", "source": "sahi", "url": "https://www.google.com/search?q=Aeroflex%20Industries%20site%3Asahi.com"}, {"text": "Liquid-cooling skid capacity was raised 50%, with further expansion planned.", "kind": "catalyst", "source": "sahi", "url": "https://www.google.com/search?q=Aeroflex%20Industries%20site%3Asahi.com"}, {"text": "P/E is about 102, volatility is the highest of the ten (67%), and liquidity is thin (\u20b953 cr/day).", "kind": "risk", "source": "share", "url": "https://www.google.com/search?q=Aeroflex%20Industries%20share"}, {"text": "That makes it the most fragile in a falling market.", "kind": "risk", "source": "share", "url": "https://www.google.com/search?q=Aeroflex%20Industries%20share"}], "short_view": "Bullish, risky"}, "ATHERENERG": {"symbol": "ATHERENERG", "name": "Ather Energy", "view": "Bullish, mid-pullback", "view_score": 1.25, "tone": "bull", "summary": "Q1 revenue grew 89% and the loss narrowed 71%.", "why": "Strong catalysts and brokers, but still pulling back", "points": [{"text": "Q1 revenue grew 89% and the loss narrowed 71%.", "kind": "catalyst", "source": "indmoney", "url": "https://www.google.com/search?q=Ather%20Energy%20site%3Aindmoney.com"}, {"text": "It was also added to the MSCI India Domestic Small Cap Index.", "kind": "catalyst", "source": "indmoney", "url": "https://www.google.com/search?q=Ather%20Energy%20site%3Aindmoney.com"}, {"text": "Hero MotoCorp is lifting its stake to about 32.8%.", "kind": "catalyst", "source": "freepressjournal", "url": "https://www.google.com/search?q=Ather%20Energy%20site%3Afreepressjournal.in"}, {"text": "A global broker raised its target to \u20b91,926.", "kind": "catalyst", "source": "hdfcsky", "url": "https://www.google.com/search?q=Ather%20Energy%20site%3Ahdfcsky.com"}, {"text": "The stock has slid about 16% from its early-September high, so the story is intact but the price is digesting a big run.", "kind": "context", "source": "", "url": ""}, {"text": "High oil prices are a tailwind for the EV theme.", "kind": "catalyst", "source": "", "url": ""}], "short_view": "Bullish"}, "RRKABEL": {"symbol": "RRKABEL", "name": "RR Kabel", "view": "Moderately bullish", "view_score": 1.0, "tone": "mod-bull", "summary": "Q1 PAT jumped 129% and EBITDA doubled.", "why": "Strong Q1, moderate volatility", "points": [{"text": "Q1 PAT jumped 129% and EBITDA doubled.", "kind": "catalyst", "source": "5paisa", "url": "https://www.google.com/search?q=RR%20Kabel%20site%3A5paisa.com"}, {"text": "CLSA initiated at Outperform with a \u20b92,850 target.", "kind": "catalyst", "source": "fyers", "url": "https://www.google.com/search?q=RR%20Kabel%20site%3Afyers.in"}, {"text": "The stock is 16% off its high, so it is consolidating.", "kind": "context", "source": "", "url": ""}, {"text": "Volatility is moderate (44%), which is better than most here.", "kind": "catalyst", "source": "", "url": ""}], "short_view": "Moderately bullish"}, "E2E": {"symbol": "E2E", "name": "E2E Networks", "view": "Speculative, neutral to bullish", "view_score": 0.5, "tone": "spec", "summary": "Q1 revenue was \u20b9156.76 crore vs \u20b936.11 crore a year earlier, with a profit of \u20b943.88 crore, on GPU cluster expansion.", "why": "Big revenue jump, P/E near 400", "points": [{"text": "Q1 revenue was \u20b9156.76 crore vs \u20b936.11 crore a year earlier, with a profit of \u20b943.88 crore, on GPU cluster expansion.", "kind": "catalyst", "source": "angelone", "url": "https://www.google.com/search?q=E2E%20Networks%20site%3Aangelone.in"}, {"text": "P/E is about 398 and the stock fell 11.8% in the month to 18 Sep.", "kind": "risk", "source": "anandrathi", "url": "https://www.google.com/search?q=E2E%20Networks%20site%3Aanandrathi.com"}, {"text": "It has bounced since.", "kind": "context", "source": "anandrathi", "url": "https://www.google.com/search?q=E2E%20Networks%20site%3Aanandrathi.com"}, {"text": "It is an AI-theme stock with thin liquidity and gap risk in both directions.", "kind": "risk", "source": "", "url": ""}], "short_view": "Speculative"}, "ACUTAAS": {"symbol": "ACUTAAS", "name": "Acutaas Chemicals", "view": "Neutral", "view_score": 0.0, "tone": "neutral", "summary": "It received PLI approval for an electrolyte additives plan and commissioned a high-potency API pilot plant.", "why": "No catalyst, sideways trend", "points": [{"text": "It received PLI approval for an electrolyte additives plan and commissioned a high-potency API pilot plant.", "kind": "catalyst", "source": "fyers", "url": "https://www.google.com/search?q=Acutaas%20Chemicals%20site%3Afyers.in"}, {"text": "Quarterly revenue and profit were lower sequentially (\u20b9327 cr and \u20b976 cr in Jun vs \u20b9436 cr and \u20b9137 cr in Mar).", "kind": "risk", "source": "anandrathi", "url": "https://www.google.com/search?q=Acutaas%20Chemicals%20site%3Aanandrathi.com"}, {"text": "The 6-1 return is negative.", "kind": "risk", "source": "anandrathi", "url": "https://www.google.com/search?q=Acutaas%20Chemicals%20site%3Aanandrathi.com"}, {"text": "The price has moved sideways since June.", "kind": "risk", "source": "", "url": ""}, {"text": "There is no clear trigger for a 21-day move.", "kind": "risk", "source": "", "url": ""}], "short_view": "Neutral"}, "DIACABS": {"symbol": "DIACABS", "name": "Diamond Power Infra", "view": "Neutral to bearish short term", "view_score": -1.0, "tone": "mod-bear", "summary": "It hit a 52-week high of about \u20b9395 on 17 Sep, up 202% in six months, with a P/E near 128.", "why": "Extended, weak balance sheet", "points": [{"text": "It hit a 52-week high of about \u20b9395 on 17 Sep, up 202% in six months, with a P/E near 128.", "kind": "risk", "source": "anandrathi", "url": "https://www.google.com/search?q=Diamond%20Power%20Infra%20site%3Aanandrathi.com"}, {"text": "Book value per share was negative in the July data.", "kind": "risk", "source": "bajajfinserv", "url": "https://www.google.com/search?q=Diamond%20Power%20Infra%20site%3Abajajfinserv.in"}, {"text": "It is now 14% off that high.", "kind": "risk", "source": "", "url": ""}, {"text": "The T&D order-book story is real, but the valuation and balance sheet make it a momentum-only trade.", "kind": "context", "source": "", "url": ""}], "short_view": "Neutral to bearish"}, "KIRLOSENG": {"symbol": "KIRLOSENG", "name": "Kirloskar Oil Engines", "view": "Neutral to bearish", "view_score": -1.0, "tone": "mod-bear", "summary": "June-quarter revenue was \u20b91,482 cr vs \u20b91,284 cr a year ago, but EBITDA slipped to \u20b9176 cr from \u20b9184 cr, so margins are compressing.", "why": "Margins and momentum fading", "points": [{"text": "June-quarter revenue was \u20b91,482 cr vs \u20b91,284 cr a year ago, but EBITDA slipped to \u20b9176 cr from \u20b9184 cr, so margins are compressing.", "kind": "risk", "source": "anandrathi", "url": "https://www.google.com/search?q=Kirloskar%20Oil%20Engines%20site%3Aanandrathi.com"}, {"text": "The 6-1 return is \u221211% and the stock is 16.5% below its high.", "kind": "risk", "source": "", "url": ""}, {"text": "Momentum is fading.", "kind": "risk", "source": "", "url": ""}], "short_view": "Neutral to bearish"}, "THANGAMAYL": {"symbol": "THANGAMAYL", "name": "Thangamayil Jewellery", "view": "Bearish", "view_score": -2.0, "tone": "bear", "summary": "It hit a high of \u20b97,429 and traded near \u20b95,085 on 22 Sep.", "why": "Downtrend, avoid", "points": [{"text": "It hit a high of \u20b97,429 and traded near \u20b95,085 on 22 Sep.", "kind": "context", "source": "anandrathi", "url": "https://www.google.com/search?q=Thangamayil%20Jewellery%20site%3Aanandrathi.com"}, {"text": "It is now about 31% below the peak.", "kind": "risk", "source": "anandrathi", "url": "https://www.google.com/search?q=Thangamayil%20Jewellery%20site%3Aanandrathi.com"}, {"text": "Q1 EBITDA (\u20b9145 cr) fell from \u20b9214 cr in the March quarter.", "kind": "risk", "source": "anandrathi", "url": "https://www.google.com/search?q=Thangamayil%20Jewellery%20site%3Aanandrathi.com"}, {"text": "It has the weakest chart in the batch: a clear downtrend, a negative 6-1 return, and a gold-price-sensitive business.", "kind": "risk", "source": "", "url": ""}], "short_view": "Bearish"}, "LAURUSLABS": {"symbol": "LAURUSLABS", "name": "Laurus Labs", "view": "Strongest, bullish", "view_score": 2.0, "tone": "strong-bull", "summary": "Its close is only 1.1% below its 12-month high, and its volatility is the lowest of the ten (28%).", "why": "Relative strength near highs, lowest volatility, defensive sector", "points": [{"text": "Its close is only 1.1% below its 12-month high, and its volatility is the lowest of the ten (28%).", "kind": "catalyst", "source": "", "url": ""}, {"text": "FY26 profit after tax was \u20b9740 crore vs \u20b9380 crore the year before.", "kind": "catalyst", "source": "torusdigital", "url": "https://www.google.com/search?q=Laurus%20Labs%20site%3Atorusdigital.com"}, {"text": "It is up about 94% in six months and holding near highs while the index falls.", "kind": "catalyst", "source": "anandrathi", "url": "https://www.google.com/search?q=Laurus%20Labs%20site%3Aanandrathi.com"}, {"text": "Pharma is also defensive in a risk-off tape.", "kind": "catalyst", "source": "anandrathi", "url": "https://www.google.com/search?q=Laurus%20Labs%20site%3Aanandrathi.com"}, {"text": "P/E is high, so it can still pull back.", "kind": "risk", "source": "anandrathi", "url": "https://www.google.com/search?q=Laurus%20Labs%20site%3Aanandrathi.com"}], "short_view": "Bullish"}}, "shortlist": ["LAURUSLABS", "TDPOWERSYS", "ATHERENERG", "RRKABEL", "AEROFLEX", "E2E", "ACUTAAS", "DIACABS", "KIRLOSENG", "THANGAMAYL"], "missing": []}, "research_notes": "Stock by stock\n\n1. TD Power Systems (TDPOWERSYS): bullish\n\nThe stock is 10% below its high, a shallow pullback within a strong uptrend.\nQ1 FY27 revenue rose about 72% YoY.\n5paisa\nIt raised its FY27 revenue guidance to \u20b92,600 crore.\nfyers\nA board meeting on 14 Aug was set to consider raising funds, so check whether a dilutive QIP is pending. Valuation is stretched (P/E around 70).\n5paisa\n\n2. Aeroflex Industries (AEROFLEX): bullish, high risk\n\nQ1 FY27 revenue grew 72.4% and PAT rose 162%. Liquid-cooling skid capacity was raised 50%, with further expansion planned.\nsahi\nP/E is about 102, volatility is the highest of the ten (67%), and liquidity is thin (\u20b953 cr/day). That makes it the most fragile in a falling market.\nshare\n\n3. Ather Energy (ATHERENERG): bullish, mid-pullback\n\nQ1 revenue grew 89% and the loss narrowed 71%. It was also added to the MSCI India Domestic Small Cap Index.\nindmoney\nHero MotoCorp is lifting its stake to about 32.8%.\nfreepressjournal\nA global broker raised its target to \u20b91,926.\nhdfcsky\nThe stock has slid about 16% from its early-September high, so the story is intact but the price is digesting a big run. High oil prices are a tailwind for the EV theme.\n\n4. RR Kabel (RRKABEL): moderately bullish\n\nQ1 PAT jumped 129% and EBITDA doubled.\n5paisa\nCLSA initiated at Outperform with a \u20b92,850 target.\nfyers\nThe stock is 16% off its high, so it is consolidating. Volatility is moderate (44%), which is better than most here.\n\n5. E2E Networks (E2E): speculative, neutral to bullish\n\nQ1 revenue was \u20b9156.76 crore vs \u20b936.11 crore a year earlier, with a profit of \u20b943.88 crore, on GPU cluster expansion.\nangelone\nP/E is about 398 and the stock fell 11.8% in the month to 18 Sep. It has bounced since.\nanandrathi\nIt is an AI-theme stock with thin liquidity and gap risk in both directions.\n\n6. Acutaas Chemicals (ACUTAAS): neutral\n\nIt received PLI approval for an electrolyte additives plan and commissioned a high-potency API pilot plant.\nfyers\nQuarterly revenue and profit were lower sequentially (\u20b9327 cr and \u20b976 cr in Jun vs \u20b9436 cr and \u20b9137 cr in Mar). The 6-1 return is negative.\nanandrathi\nThe price has moved sideways since June. There is no clear trigger for a 21-day move.\n\n7. Diamond Power Infra (DIACABS): neutral to bearish short term\n\nIt hit a 52-week high of about \u20b9395 on 17 Sep, up 202% in six months, with a P/E near 128.\nanandrathi\nBook value per share was negative in the July data.\nbajajfinserv\nIt is now 14% off that high. The T&D order-book sto
A6: ry is real, but the valuation and balance sheet make it a momentum-only trade.\n\n8. Kirloskar Oil Engines (KIRLOSENG): neutral to bearish\n\nJune-quarter revenue was \u20b91,482 cr vs \u20b91,284 cr a year ago, but EBITDA slipped to \u20b9176 cr from \u20b9184 cr, so margins are compressing.\nanandrathi\nThe 6-1 return is \u221211% and the stock is 16.5% below its high. Momentum is fading.\n\n9. Thangamayil Jewellery (THANGAMAYL): bearish\n\nIt hit a high of \u20b97,429 and traded near \u20b95,085 on 22 Sep. It is now about 31% below the peak.\nanandrathi\nQ1 EBITDA (\u20b9145 cr) fell from \u20b9214 cr in the March quarter.\nanandrathi\nIt has the weakest chart in the batch: a clear downtrend, a negative 6-1 return, and a gold-price-sensitive business.\n\n10. Laurus Labs (LAURUSLABS): strongest, bullish\n\nIts close is only 1.1% below its 12-month high, and its volatility is the lowest of the ten (28%).\nFY26 profit after tax was \u20b9740 crore vs \u20b9380 crore the year before.\ntorusdigital\nIt is up about 94% in six months and holding near highs while the index falls. Pharma is also defensive in a risk-off tape. P/E is high, so it can still pull back.\nanandrathi\nSwing-trade shortlist (21-session hold)\nRank\tStock\tView\tWhy\n1\tLAURUSLABS\tBullish\tRelative strength near highs, lowest volatility, defensive sector\n2\tTDPOWERSYS\tBullish\tGuidance raised, shallow pullback. Check for a fundraise.\n3\tATHERENERG\tBullish\tStrong catalysts and brokers, but still pulling back\n4\tRRKABEL\tModerately bullish\tStrong Q1, moderate volatility\n5\tAEROFLEX\tBullish, risky\tStrong growth, expensive, volatile, thin liquidity\n6\tE2E\tSpeculative\tBig revenue jump, P/E near 400\n7\tACUTAAS\tNeutral\tNo catalyst, sideways trend\n8\tDIACABS\tNeutral to bearish\tExtended, weak balance sheet\n9\tKIRLOSENG\tNeutral to bearish\tMargins and momentum fading\n10\tTHANGAMAYL\tBearish\tDowntrend, avoid\n", "fundamentals": {"TDPOWERSYS": {"name": "TD POWER SYSTEMS LTD.", "pe": 85.44379, "fwd_pe": 48.537815, "sector": "Industrials", "industry": "Specialty Industrial Machinery", "mcap_cr": 22649.634816, "pb": 21.047108, "rev_growth": 0.721, "earn_growth": 0.72}, "AEROFLEX": {"name": "AEROFLEX INDUSTRIES LTD", "pe": 102.0676, "fwd_pe": 51.85859, "sector": "Industrials", "industry": "Metal Fabrication", "mcap_cr": 6793.8619392, "pb": 15.18935, "rev_growth": 0.724, "earn_growth": 1.582}, "ATHERENERG": {"name": "ATHER ENERGY LIMITED", "pe": null, "fwd_pe": 516.02814, "sector": "Consumer Cyclical", "industry": "Auto Manufacturers", "mcap_cr": 57631.3819136, "pb": 21.641281, "rev_growth": 0.888, "earn_growth": null}, "THANGAMAYL": {"name": "THANGAMAYIL JEWELLERY LTD", "pe": 39.837044, "fwd_pe": 27.495428, "sector": "Consumer Cyclical", "industry": "Luxury Goods", "mcap_cr": 15576.7537664, "pb": 11.000529, "rev_growth": 0.712, "earn_growth": 0.861}, "RRKABEL": {"name": "R R KABEL LIMITED", "pe": 45.891792, "fwd_pe": 31.331299, "sector": "Industrials", "industry": "Electrical Equipment & Parts", "mcap_cr": 27821.6933376, "pb": 10.807082, "rev_growth": 0.539, "earn_growth": 1.285}, "ACUTAAS": {"name": "ACUTAAS CHEMICALS LIMITED", "pe": 68.217316, "fwd_pe": 43.793648, "sector": "Basic Materials", "industry": "Specialty Chemicals", "mcap_cr": 26316.652544, "pb": 15.918781, "rev_growth": 0.591, "earn_growth": 0.671}, "DIACABS": {"name": "DIAMOND POWER INFRA LTD", "pe": 89.51187, "fwd_pe": null, "sector": "Industrials", "industry": "Specialty Industrial Machinery", "mcap_cr": 20289.560576, "pb": -29.587477, "rev_growth": 1.272, "earn_growth": 2.083}, "KIRLOSENG": {"name": "KIRLOSKAR OIL ENG LTD", "pe": 57.251335, "fwd_pe": 37.53199, "sector": "Industrials", "industry": "Specialty Industrial Machinery", "mcap_cr": 31168.6397952, "pb": 8.596884, "rev_growth": 0.134, "earn_growth": -0.199}, "E2E": {"name": "E2E NETWORKS LIMITED", "pe": 237.98479, "fwd_pe": null, "sector": "Technology", "industry": "Software - Infrastructure", "mcap_cr": 12859.6099072, "pb": 7.4469357, "rev_growth": 3.341, "earn_growth": null}, "LAURUSLABS": {"name": "LAURUS LABS LIMITED", "pe": 99.195854, "fwd_pe": 69.47338, "sector": "Healthcare", "industry": "Drug Manufacturers - Specialty & Generic", "mcap_cr": 108640.567296, "pb": 20.480774, "rev_growth": 0.291, "earn_growth": 1.252}}, "telegram_sent": "2026-10-23", "corp_actions": [], "pending_alerts": []}
